Workbook

Sheet Sheet1
A1: Item Name | B1: Item Unit | C1: Main Category | D1: Sub Category 1 | E1: Sub Category 2 | F1: C1 | G1: C2 | H1: Indexed | I1: Unit Price | J1: District | K1: Index
A2: Earth work in surface excavation not exceeding 30 cm in depth but exceeding 1.5m in width as well as 10 sqm on plan including disposal of excavated earth up to 50 m and lift up to 1.5 m, disposed soil to be levelled and neatly dressed: All Kinds of soil (Code: 2.1.1) | B2: sqm | C2: PRICE (DSR 2021) | D2: Earth Work | E2: Others | F2: 0 | G2: 92.9 | H2: =G2*$K$2 -> 0 | I2: =ROUND(SUM(F2:H2),2) -> 92.9 | J2: Name | K2: 0
A3: Earth work in rough excavation, banking excavated earth in layers not exceeding 20 cm in depth, breaking clods, watering, rolling each layer with 1/2 tonne roller or wooden or steel rammers, and rolling every 3rd and top-most layer with power roller of minimum 8 tonnes and dressing up in embankments for roads, flood banks, marginal banks and guide banks or filling up ground depressions, lead up to 50 m and lift up to 1.5 m: All kinds of soil (Code: 2.2.1) | B3: cum | C3: PRICE (DSR 2021) | D3: Earth Work | E3: Others | F3: 0 | G3: 748.95 | H3: =G3*$K$2 -> 0 | I3: =ROUND(SUM(F3:H3),2) -> 748.95
A4: Banking excavated earth in layers not exceeding 20 cm in depth, breaking clods, watering, rolling each layer with 1/2 tonne roller, or wooden or steel rammers, and rolling every 3rd and top-most layer with power roller of minimum 8 tonnes and dressing up, in embankments for roads, flood banks, marginal banks, and guide banks etc., lead up to 50 m and lift up to 1.5 m : All kinds of soil (Code: 2.3.1) | B4: cum | C4: PRICE (DSR 2021) | D4: Earth Work | E4: Others | F4: 0 | G4: 471.75 | H4: =G4*$K$2 -> 0 | I4: =ROUND(SUM(F4:H4),2) -> 471.75
A5: Deduct for not rolling with power roller of minimum 8 tonnes for banking excavated earth in layers not exceeding 20 cm in depth (Code: 2.4) | B5: cum | C5: PRICE (DSR 2021) | D5: Earth Work | E5: Others | F5: 0 | G5: 3.83 | H5: =G5*$K$2 -> 0 | I5: =ROUND(SUM(F5:H5),2) -> 3.83
A6: Deduct for not watering the excavated earth for banking (Code: 2.5) | B6: cum | C6: PRICE (DSR 2021) | D6: Earth Work | E6: Others | F6: 0 | G6: 33.17 | H6: =G6*$K$2 -> 0 | I6: =ROUND(SUM(F6:H6),2) -> 33.17
A7: Earth work in excavation by mechanical means (Hydraulic excavator)/manual means over areas (exceeding 30 cm in depth, 1.5 m in width as well as 10 sqm on plan) including disposal of excavated earth, lead up to 50 m and lift up to 1.5 m, disposed earth to be levelled and neatly dressed. All kinds of soil (Code: 2.6.1) | B7: cum | C7: PRICE (DSR 2021) | D7: Earth Work | E7: Others | F7: 0 | G7: 178.35 | H7: =G7*$K$2 -> 0 | I7: =ROUND(SUM(F7:H7),2) -> 178.35
A8: Earth work in excavation by mechanical means (Hydraulic excavator )/ manual means over areas (exceeding 30 cm in depth, 1.5 m in width as well as 10 sqm on plan) including disposal of excavated earth, lead up to 50 m and lift up to 1.5 m, disposed earth to be levelled and neatly dressed. Ordinary rock (Code: 2.7.1) | B8: cum | C8: PRICE (DSR 2021) | D8: Earth Work | E8: Others | F8: 0 | G8: 358.51 | H8: =G8*$K$2 -> 0 | I8: =ROUND(SUM(F8:H8),2) -> 358.51
A9: Earth work in excavation by mechanical means (Hydraulic excavator )/ manual means over areas (exceeding 30 cm in depth, 1.5 m in width as well as 10 sqm on plan) including disposal of excavated earth, lead up to 50 m and lift up to 1.5 m, disposed earth to be levelled and neatly dressed. Hard rock (requiring blasting) (Code: 2.7.2) | B9: cum | C9: PRICE (DSR 2021) | D9: Earth Work | E9: Others | F9: 0 | G9: 617.55 | H9: =G9*$K$2 -> 0 | I9: =ROUND(SUM(F9:H9),2) -> 617.55
A10: Earth work in excavation by mechanical means (Hydraulic excavator )/ manual means over areas (exceeding 30 cm in depth, 1.5 m in width as well as 10 sqm on plan) including disposal of excavated earth, lead up to 50 m and lift up to 1.5 m, disposed earth to be levelled and neatly dressed. Hard rock (blasting prohibited) (Code: 2.7.3) | B10: cum | C10: PRICE (DSR 2021) | D10: Earth Work | E10: Others | F10: 0 | G10: 1028.11 | H10: =G10*$K$2 -> 0 | I10: =ROUND(SUM(F10:H10),2) -> 1028.11
A11: Earth work in excavation by mechanical means (Hydraulic excavator) /manual means in foundation trenches or drains (not exceeding 1.5 m in width or 10 sqm on plan), including dressing of sides and ramming of bottoms, lift up to 1.5 m, including getting out the excavated soil and disposal of surplus excavated soil as directed, within a lead of 50 m. All kinds of soil (Code: 2.8.1) | B11: cum | C11: PRICE (DSR 2021) | D11: Earth Work | E11: Others | F11: 0 | G11: 249.04 | H11: =G11*$K$2 -> 0 | I11: =ROUND(SUM(F11:H11),2) -> 249.04
A12: Excavation work by mechanical means (Hydraulic excavator) / manual means in foundation trenches or drains (not exceeding 1.5 m in width or 10 sqm on plan), including dressing of sides and ramming of bottoms, lift up to 1.5 m, including getting out the excavated soil and disposal of surplus excavated soils as directed, within a lead of 50 m. Ordinary rock (Code: 2.9.1) | B12: cum | C12: PRICE (DSR 2021) | D12: Earth Work | E12: Others | F12: 0 | G12: 454.46 | H12: =G12*$K$2 -> 0 | I12: =ROUND(SUM(F12:H12),2) -> 454.46
A13: Excavation work by mechanical means (Hydraulic excavator) / manual means in foundation trenches or drains (not exceeding 1.5 m in width or 10 sqm on plan), including dressing of sides and ramming of bottoms, lift up to 1.5 m, including getting out the excavated soil and disposal of surplus excavated soils as directed, within a lead of 50 m. Hard rock (requiring blasting) (Code: 2.9.2) | B13: cum | C13: PRICE (DSR 2021) | D13: Earth Work | E13: Others | F13: 0 | G13: 734.65 | H13: =G13*$K$2 -> 0 | I13: =ROUND(SUM(F13:H13),2) -> 734.65
A14: Excavation work by mechanical means (Hydraulic excavator) / manual means in foundation trenches or drains (not exceeding 1.5 m in width or 10 sqm on plan), including dressing of sides and ramming of bottoms, lift up to 1.5 m, including getting out the excavated soil and disposal of surplus excavated soils as directed, within a lead of 50 m. Hard rock (blasting prohibited) (Code: 2.9.3) | B14: cum | C14: PRICE (DSR 2021) | D14: Earth Work | E14: Others | F14: 0 | G14: 1092.62 | H14: =G14*$K$2 -> 0 | I14: =ROUND(SUM(F14:H14),2) -> 1092.62
... A6971: Acrylic modified resin based texture (Code: 8513 - Water Charge and CPOH Added) | B6971: kg | C6971: DSR 21 Basic Rates | D6971: DSR Basic Rates | E6971: DSR 21 Basic Rates | F6971: 0 | G6971: 48.783 | H6971: =G6971*$K$2 -> 0 | I6971: =ROUND(SUM(F6971:H6971),2) -> 48.78
A6972: 40 mm long S.S screws with plastic rawl plugs (Code: 8514 - Water Charge and CPOH Added) | B6972: 100 | C6972: DSR 21 Basic Rates | D6972: DSR Basic Rates | E6972: DSR 21 Basic Rates | F6972: 0 | G6972: 48.783 | H6972: =G6972*$K$2 -> 0 | I6972: =ROUND(SUM(F6972:H6972),2) -> 48.78
A6973: Galavanised MS 8 mm outer diameter M-6 dash fastener 50mm long (Code: 8515 - Water Charge and CPOH Added) | B6973: each | C6973: DSR 21 Basic Rates | D6973: DSR Basic Rates | E6973: DSR 21 Basic Rates | F6973: 0 | G6973: 48.783 | H6973: =G6973*$K$2 -> 0 | I6973: =ROUND(SUM(F6973:H6973),2) -> 48.78
A6974: ZMB 60/equivalent (Code: 8516 - Water Charge and CPOH Added) | B6974: kg | C6974: DSR 21 Basic Rates | D6974: DSR Basic Rates | E6974: DSR 21 Basic Rates | F6974: 0 | G6974: 127.765 | H6974: =G6974*$K$2 -> 0 | I6974: =ROUND(SUM(F6974:H6974),2) -> 127.77
A6975: ZMB thinner (Code: 8517 - Water Charge and CPOH Added) | B6975: litre | C6975: DSR 21 Basic Rates | D6975: DSR Basic Rates | E6975: DSR 21 Basic Rates | F6975: 0 | G6975: 255.53 | H6975: =G6975*$K$2 -> 0 | I6975: =ROUND(SUM(F6975:H6975),2) -> 255.53
A6976: Zycoprime / equivalent (Code: 8518 - Water Charge and CPOH Added) | B6976: litre | C6976: DSR 21 Basic Rates | D6976: DSR Basic Rates | E6976: DSR 21 Basic Rates | F6976: 0 | G6976: 267.145 | H6976: =G6976*$K$2 -> 0 | I6976: =ROUND(SUM(F6976:H6976),2) -> 267.15
A6977: Zycosil / equivalent (Code: 8519 - Water Charge and CPOH Added) | B6977: litre | C6977: DSR 21 Basic Rates | D6977: DSR Basic Rates | E6977: DSR 21 Basic Rates | F6977: 0 | G6977: 2090.7 | H6977: =G6977*$K$2 -> 0 | I6977: =ROUND(SUM(F6977:H6977),2) -> 2090.7
A6978: Elastobar / equivalent (Code: 8520 - Water Charge and CPOH Added) | B6978: kg | C6978: DSR 21 Basic Rates | D6978: DSR Basic Rates | E6978: DSR 21 Basic Rates | F6978: 0 | G6978: 348.45 | H6978: =G6978*$K$2 -> 0 | I6978: =ROUND(SUM(F6978:H6978),2) -> 348.45
A6979: Mineral fibre beveled tegular edged ceiling tiles 595 x595mm,16 mm thick (Code: 8552 - Water Charge and CPOH Added) | B6979: sqm | C6979: DSR 21 Basic Rates | D6979: DSR Basic Rates | E6979: DSR 21 Basic Rates | F6979: 0 | G6979: 969.8525 | H6979: =G6979*$K$2 -> 0 | I6979: =ROUND(SUM(F6979:H6979),2) -> 969.85
A6980: Mineral fibre beveled tegular edged ceiling tiles 595 x595mm,16 mm thick with bio-block conforming to ISO 5 (class 100) specifications. (Code: 8553 - Water Charge and CPOH Added) | B6980: sqm | C6980: DSR 21 Basic Rates | D6980: DSR Basic Rates | E6980: DSR 21 Basic Rates | F6980: 0 | G6980: 1074.3875 | H6980: =G6980*$K$2 -> 0 | I6980: =ROUND(SUM(F6980:H6980),2) -> 1074.39
A6981: Mineral fiber beveled tegular edged ceiling tiles 595 x595mm,20 mm thick. (Code: 8554 - Water Charge and CPOH Added) | B6981: sqm | C6981: DSR 21 Basic Rates | D6981: DSR Basic Rates | E6981: DSR 21 Basic Rates | F6981: 0 | G6981: 1213.7675 | H6981: =G6981*$K$2 -> 0 | I6981: =ROUND(SUM(F6981:H6981),2) -> 1213.77
A6982: G.I main runner 15 x32 mm of 3000 mm length, 0.33 mm thick (Code: 8555 - Water Charge and CPOH Added) | B6982: each | C6982: DSR 21 Basic Rates | D6982: DSR Basic Rates | E6982: DSR 21 Basic Rates | F6982: 0 | G6982: 220.685 | H6982: =G6982*$K$2 -> 0 | I6982: =ROUND(SUM(F6982:H6982),2) -> 220.69
A6983: G.I cross-T 15 x32 mm of 1200 mm length, 0.33 mm thick (Code: 8556 - Water Charge and CPOH Added) | B6983: each | C6983: DSR 21 Basic Rates | D6983: DSR Basic Rates | E6983: DSR 21 Basic Rates | F6983: 0 | G6983: 90.597 | H6983: =G6983*$K$2 -> 0 | I6983: =ROUND(SUM(F6983:H6983),2) -> 90.6
A6984: G.I cross-T 15 x32 mm of 600 mm length, 0.33 mm thick (Code: 8557 - Water Charge and CPOH Added) | B6984: each | C6984: DSR 21 Basic Rates | D6984: DSR Basic Rates | E6984: DSR 21 Basic Rates | F6984: 0 | G6984: 40.6525 | H6984: =G6984*$K$2 -> 0 | I6984: =ROUND(SUM(F6984:H6984),2) -> 40.65
... A9812: S&F Digital Timer Switch (Code: GWDMR194) | B9812: each | C9812: GWD MR | D9812: MWSS | E9812: Motor Starter | F9812: 6500 | G9812: 0 | H9812: =G9812*$K$2 -> 0 | I9812: =ROUND(SUM(F9812:H9812),2) -> 6500

Sheet Sheet2
A1: username | B1: password | C1: index | D1: office
A2: gwdtvm | B2: gwdtvm | C2: 0.4766 | D2: thiruvananthapuram
A3: gwdklm | B3: gwdklm | C3: 0.4445 | D3: kollam
A4: gwdpta | B4: gwdpta | C4: 0.4445 | D4: pathanamthitta
A5: gwdalp | B5: gwdalp | C5: 0.4445 | D5: alappuzha
A6: gwdktm | B6: gwdktm | C6: 0.4445 | D6: kottayam
A7: gwdidk | B7: gwdidk | C7: 0.4445 | D7: idukki
A8: gwdekm | B8: gwdekm | C8: 0.4445 | D8: ernakulam
A9: gwdtsr | B9: gwdtsr | C9: 0.4445 | D9: thrissur
A10: gwdpkd | B10: gwdpkd | C10: 0.4445 | D10: palakkad
A11: gwdmlp | B11: gwdmlp | C11: 0.3268 | D11: malappuram
A12: gwdkkd | B12: gwdkkd | C12: 0.3268 | D12: kozhikode
A13: gwdwyd | B13: gwdwyd | C13: 0.3482 | D13: wayanad
... A16: admin | B16: admin | C16: 0 | D16: admin

Sheet admin
A1: =Sheet1!A1:G1 -> Item Name
A2: =Sheet1!A2:G2 -> Earth work in surface excavation not exceeding 30 cm in depth but exceeding 1.5m in width as well as 10 sqm on plan including disposal of excavated earth up to 50 m and lift up to 1.5 m, disposed soil to be levelled and neatly dressed: All Kinds of soil (Code: 2.1.1)
A3: =Sheet1!A3:G3 -> Earth work in rough excavation, banking excavated earth in layers not exceeding 20 cm in depth, breaking clods, watering, rolling each layer with 1/2 tonne roller or wooden or steel rammers, and rolling every 3rd and top-most layer with power roller of minimum 8 tonnes and dressing up in embankments for roads, flood banks, marginal banks and guide banks or filling up ground depressions, lead up to 50 m and lift up to 1.5 m: All kinds of soil (Code: 2.2.1)
A4: =Sheet1!A4:G4 -> Banking excavated earth in layers not exceeding 20 cm in depth, breaking clods, watering, rolling each layer with 1/2 tonne roller, or wooden or steel rammers, and rolling every 3rd and top-most layer with power roller of minimum 8 tonnes and dressing up, in embankments for roads, flood banks, marginal banks, and guide banks etc., lead up to 50 m and lift up to 1.5 m : All kinds of soil (Code: 2.3.1)
A5: =Sheet1!A5:G5 -> Deduct for not rolling with power roller of minimum 8 tonnes for banking excavated earth in layers not exceeding 20 cm in depth (Code: 2.4)
A6: =Sheet1!A6:G6 -> Deduct for not watering the excavated earth for banking (Code: 2.5)
A7: =Sheet1!A7:G7 -> Earth work in excavation by mechanical means (Hydraulic excavator)/manual means over areas (exceeding 30 cm in depth, 1.5 m in width as well as 10 sqm on plan) including disposal of excavated earth, lead up to 50 m and lift up to 1.5 m, disposed earth to be levelled and neatly dressed. All kinds of soil (Code: 2.6.1)
A8: =Sheet1!A8:G8 -> Earth work in excavation by mechanical means (Hydraulic excavator )/ manual means over areas (exceeding 30 cm in depth, 1.5 m in width as well as 10 sqm on plan) including disposal of excavated earth, lead up to 50 m and lift up to 1.5 m, disposed earth to be levelled and neatly dressed. Ordinary rock (Code: 2.7.1)
A9: =Sheet1!A9:G9 -> Earth work in excavation by mechanical means (Hydraulic excavator )/ manual means over areas (exceeding 30 cm in depth, 1.5 m in width as well as 10 sqm on plan) including disposal of excavated earth, lead up to 50 m and lift up to 1.5 m, disposed earth to be levelled and neatly dressed. Hard rock (requiring blasting) (Code: 2.7.2)
A10: =Sheet1!A10:G10 -> Earth work in excavation by mechanical means (Hydraulic excavator )/ manual means over areas (exceeding 30 cm in depth, 1.5 m in width as well as 10 sqm on plan) including disposal of excavated earth, lead up to 50 m and lift up to 1.5 m, disposed earth to be levelled and neatly dressed. Hard rock (blasting prohibited) (Code: 2.7.3)
A11: =Sheet1!A11:G11 -> Earth work in excavation by mechanical means (Hydraulic excavator) /manual means in foundation trenches or drains (not exceeding 1.5 m in width or 10 sqm on plan), including dressing of sides and ramming of bottoms, lift up to 1.5 m, including getting out the excavated soil and disposal of surplus excavated soil as directed, within a lead of 50 m. All kinds of soil (Code: 2.8.1)
A12: =Sheet1!A12:G12 -> Excavation work by mechanical means (Hydraulic excavator) / manual means in foundation trenches or drains (not exceeding 1.5 m in width or 10 sqm on plan), including dressing of sides and ramming of bottoms, lift up to 1.5 m, including getting out the excavated soil and disposal of surplus excavated soils as directed, within a lead of 50 m. Ordinary rock (Code: 2.9.1)
... A9812: =Sheet1!A9812:G9812 -> S&F Digital Timer Switch (Code: GWDMR194)
