Workbook
Name MRCodes: 'zPAMR Gen ID 40'!$D:$D
Name LMRCodes: zLMR!$A:$A
Name MRRates: 'zPAMR Gen ID 40'!$F:$F
Name DerivedCodes: zDerived!$A:$A
Name CostIndex: 'zCost Index'!$B$2:$B$16
Name District: 'zCost Index'!$A$2:$A$16
Name DerivedRates: zDerived!$D:$D
Name LMRRates: zLMR!$C:$C

Sheet GWD DR Abstract
A1: GWD Revised Derived Rates Based on DSR 21/PRICE (Gen ID 40) | J1: Select Distrct | L1: Index
J2: ADMIN | L2: {=((IFERROR(INDEX(CostIndex,MATCH(J2,District,0), ), )))} -> 1
A3: Sl No | B3: Code | C3: Item Name | D3: Item Name With Code | E3: Unit | F3: Main Category | G3: Sub Category 1 | H3: Sub Category 2 | I3: C1 | J3: C2 | K3: Indexed | L3: Total
A4: 1 | B4: GWDDR001 | C4: ='Well Protection'!A1 -> Well Protection Cover | D4: =CONCATENATE(C4," (Code: ",B4,")") -> Well Protection Cover (Code: GWDDR001) | E4: each | F4: GWD DR | G4: MWSS | H4: MWSS Accessories | I4: 0 | J4: ='Well Protection'!J30 -> 3800.0026 | K4: =J4*($L$2-1) -> 0 | L4: =SUM(I4:K4) -> 3800.0026
A5: 2 | B5: GWDDR002 | C5: ='Iron Structure'!A1 -> Angle Iron Structure To Support 5000 Litres Capacity Water Tank At 4 m Height | D5: =CONCATENATE(C5," (Code: ",B5,")") -> Angle Iron Structure To Support 5000 Litres Capacity Water Tank At 4 m Height (Code: GWDDR002) | E5: each | F5: GWD DR | G5: MWSS | H5: Iron Structure | I5: 0 | J5: ='Iron Structure'!J42 -> 71000.003 | K5: =J5*($L$2-1) -> 0 | L5: =SUM(I5:K5) -> 71000.003
A6: 3 | B6: GWDDR003 | C6: ='Iron Structure'!A44 -> Angle Iron Structure To Support 3000 Litres Capacity Water Tank At 4 m Height | D6: =CONCATENATE(C6," (Code: ",B6,")") -> Angle Iron Structure To Support 3000 Litres Capacity Water Tank At 4 m Height (Code: GWDDR003) | E6: each | F6: GWD DR | G6: MWSS | H6: Iron Structure | I6: 0 | J6: ='Iron Structure'!J85 -> 62000 | K6: =J6*($L$2-1) -> 0 | L6: =SUM(I6:K6) -> 62000
A7: 4 | B7: GWDDR004 | C7: ='Iron Structure'!A87 -> Angle Iron Structure To Support 5000 Litres Capacity Water Tank At 6 m Height | D7: =CONCATENATE(C7," (Code: ",B7,")") -> Angle Iron Structure To Support 5000 Litres Capacity Water Tank At 6 m Height (Code: GWDDR004) | E7: each | F7: GWD DR | G7: MWSS | H7: Iron Structure | I7: 0 | J7: ='Iron Structure'!J130 -> 93999.997 | K7: =J7*($L$2-1) -> 0 | L7: =SUM(I7:K7) -> 93999.997
A8: 5 | B8: GWDDR005 | C8: ='Iron Structure'!A132 -> Angle Iron Structure To Support 3000 Litres Capacity Water Tank At 6 m Height | D8: =CONCATENATE(C8," (Code: ",B8,")") -> Angle Iron Structure To Support 3000 Litres Capacity Water Tank At 6 m Height (Code: GWDDR005) | E8: each | F8: GWD DR | G8: MWSS | H8: Iron Structure | I8: 0 | J8: ='Iron Structure'!J175 -> 83000 | K8: =J8*($L$2-1) -> 0 | L8: =SUM(I8:K8) -> 83000
A9: 6 | B9: GWDDR006 | C9: ='Metallic PH'!A1 -> Metallic Pump House of size 1.2 x 0.9 x 2 m | D9: =CONCATENATE(C9," (Code: ",B9,")") -> Metallic Pump House of size 1.2 x 0.9 x 2 m (Code: GWDDR006) | E9: each | F9: GWD DR | G9: MWSS | H9: MWSS Accessories | I9: 0 | J9: ='Metallic PH'!J62 -> 25999.996 | K9: =J9*($L$2-1) -> 0 | L9: =SUM(I9:K9) -> 25999.996
A10: 7 | B10: GWDDR007 | C10: ='BW Casing Pipes'!B2 -> Supplying, assembling, lowering and fixing in vertical position in Borewell, PVC 140 mm 6 Kg/cm2 well casing pipe of required dia, conforming to IS : 4985:2000, including required hire and labour charges, fittings & accessories etc. all complete, for all depths, as per direction of Engineer- in- Charge. | D10: =CONCATENATE(C10," (Code: ",B10,")") -> Supplying, assembling, lowering and fixing in vertical position in Borewell, PVC 140 mm 6 Kg/cm2 well casing pipe of required dia, conforming to IS : 4985:2000, including required hire and labour charges, fittings & accessories etc. all complete, for all depths, as per direction of Engineer- in- Charge. (Code: GWDDR007) | E10: metre | F10: GWD DR | G10: Borewell | H10: PVC Casing Pipe (BW/FPW) | I10: ='BW Casing Pipes'!F13 -> 326.4 | J10: ='BW Casing Pipes'!F26 -> 11.2 | K10: =J10*($L$2-1) -> 0 | L10: =SUM(I10:K10) -> 337.6
A11: 8 | B11: GWDDR008 | C11: ='BW Casing Pipes'!B28 -> Supplying, assembling, lowering and fixing in vertical position in Borewell, PVC 140 mm 8 Kg/cm2 well casing pipe of required dia, conforming to IS : 4985:2000, including required hire and labour charges, fittings & accessories etc. all complete, for all depths, as per direction of Engineer- in- Charge. | D11: =CONCATENATE(C11," (Code: ",B11,")") -> Supplying, assembling, lowering and fixing in vertical position in Borewell, PVC 140 mm 8 Kg/cm2 well casing pipe of required dia, conforming to IS : 4985:2000, including required hire and labour charges, fittings & accessories etc. all complete, for all depths, as per direction of Engineer- in- Charge. (Code: GWDDR008) | E11: metre | F11: GWD DR | G11: Borewell | H11: PVC Casing Pipe (BW/FPW) | I11: ='BW Casing Pipes'!F39 -> 462.3 | J11: ='BW Casing Pipes'!F52 -> 11.2 | K11: =J11*($L$2-1) -> 0 | L11: =SUM(I11:K11) -> 473.5
A12: 9 | B12: GWDDR009 | C12: ='BW Casing Pipes'!B54 -> Supplying, assembling, lowering and fixing in vertical position in Borewell, PVC 160mm 6 Kg/cm2 well casing pipe of required dia, conforming to IS : 4985:2000, including required hire and labour charges, fittings & accessories etc. all complete, for all depths, as per direction of Engineer- in- Charge. | D12: =CONCATENATE(C12," (Code: ",B12,")") -> Supplying, assembling, lowering and fixing in vertical position in Borewell, PVC 160mm 6 Kg/cm2 well casing pipe of required dia, conforming to IS : 4985:2000, including required hire and labour charges, fittings & accessories etc. all complete, for all depths, as per direction of Engineer- in- Charge. (Code: GWDDR009) | E12: metre | F12: GWD DR | G12: Borewell | H12: PVC Casing Pipe (BW/FPW) | I12: ='BW Casing Pipes'!F65 -> 449.5 | J12: ='BW Casing Pipes'!F78 -> 11.2 | K12: =J12*($L$2-1) -> 0 | L12: =SUM(I12:K12) -> 460.7
A13: 10 | B13: GWDDR010 | C13: ='BW Casing Pipes'!B80 -> Supplying, assembling, lowering and fixing in vertical position in Borewell, PVC 180mm 6 Kg/cm2 well casing pipe of required dia, conforming to IS : 4985:2000, including required hire and labour charges, fittings & accessories etc. all complete, for all depths, as per direction of Engineer- in- Charge. | D13: =CONCATENATE(C13," (Code: ",B13,")") -> Supplying, assembling, lowering and fixing in vertical position in Borewell, PVC 180mm 6 Kg/cm2 well casing pipe of required dia, conforming to IS : 4985:2000, including required hire and labour charges, fittings & accessories etc. all complete, for all depths, as per direction of Engineer- in- Charge. (Code: GWDDR010) | E13: metre | F13: GWD DR | G13: Borewell | H13: PVC Casing Pipe (BW/FPW) | I13: ='BW Casing Pipes'!F91 -> 565.65 | J13: ='BW Casing Pipes'!F104 -> 11.2 | K13: =J13*($L$2-1) -> 0 | L13: =SUM(I13:K13) -> 576.85
A14: 11 | B14: GWDDR011 | C14: ='BW Casing Pipes'!B106 -> Supplying, assembling, lowering and fixing in vertical position in Borewell, PVC 180mm 8 Kg/cm2 well casing pipe of required dia, conforming to IS : 4985:2000, including required hire and labour charges, fittings & accessories etc. all complete, for all depths, as per direction of Engineer- in- Charge. | D14: =CONCATENATE(C14," (Code: ",B14,")") -> Supplying, assembling, lowering and fixing in vertical position in Borewell, PVC 180mm 8 Kg/cm2 well casing pipe of required dia, conforming to IS : 4985:2000, including required hire and labour charges, fittings & accessories etc. all complete, for all depths, as per direction of Engineer- in- Charge. (Code: GWDDR011) | E14: metre | F14: GWD DR | G14: Borewell | H14: PVC Casing Pipe (BW/FPW) | I14: ='BW Casing Pipes'!F117 -> 759.6 | J14: ='BW Casing Pipes'!F130 -> 11.2 | K14: =J14*($L$2-1) -> 0 | L14: =SUM(I14:K14) -> 770.8
A15: 12 | B15: GWDDR012 | C15: ='BW Casing Pipes'!B132 -> Supplying, assembling, lowering and fixing in vertical position in Borewell, PVC 200mm 8 Kg/cm2 well casing pipe of required dia, conforming to IS : 4985:2000, including required hire and labour charges, fittings & accessories etc. all complete, for all depths, as per direction of Engineer- in- Charge. | D15: =CONCATENATE(C15," (Code: ",B15,")") -> Supplying, assembling, lowering and fixing in vertical position in Borewell, PVC 200mm 8 Kg/cm2 well casing pipe of required dia, conforming to IS : 4985:2000, including required hire and labour charges, fittings & accessories etc. all complete, for all depths, as per direction of Engineer- in- Charge. (Code: GWDDR012) | E15: metre | F15: GWD DR | G15: Borewell | H15: PVC Casing Pipe (BW/FPW) | I15: ='BW Casing Pipes'!F143 -> 944.3 | J15: ='BW Casing Pipes'!F156 -> 11.2 | K15: =J15*($L$2-1) -> 0 | L15: =SUM(I15:K15) -> 955.5
A16: 13 | B16: GWDDR013 | C16: ='BW Casing Pipes'!B158 -> Supplying, assembling, lowering and fixing in vertical position in Borewell, PVC 200mm 10 Kg/cm2 well casing pipe of required dia, conforming to IS : 4985:2000, including required hire and labour charges, fittings & accessories etc. all complete, for all depths, as per direction of Engineer- in- Charge. | D16: =CONCATENATE(C16," (Code: ",B16,")") -> Supplying, assembling, lowering and fixing in vertical position in Borewell, PVC 200mm 10 Kg/cm2 well casing pipe of required dia, conforming to IS : 4985:2000, including required hire and labour charges, fittings & accessories etc. all complete, for all depths, as per direction of Engineer- in- Charge. (Code: GWDDR013) | E16: metre | F16: GWD DR | G16: Borewell | H16: PVC Casing Pipe (BW/FPW) | I16: ='BW Casing Pipes'!F169 -> 1111.55 | J16: ='BW Casing Pipes'!F182 -> 11.2 | K16: =J16*($L$2-1) -> 0 | L16: =SUM(I16:K16) -> 1122.75
A17: 14 | B17: GWDDR014 | C17: ='BW Casing Pipes'!B184 -> Supplying, assembling, lowering and fixing in vertical position in Borewell, PVC 110 mm 6 Kg/cm2 well casing pipe of required dia, conforming to IS : 4985:2000, including required hire and labour charges, fittings & accessories etc. all complete, for all depths, as per direction of Engineer- in- Charge. | D17: =CONCATENATE(C17," (Code: ",B17,")") -> Supplying, assembling, lowering and fixing in vertical position in Borewell, PVC 110 mm 6 Kg/cm2 well casing pipe of required dia, conforming to IS : 4985:2000, including required hire and labour charges, fittings & accessories etc. all complete, for all depths, as per direction of Engineer- in- Charge. (Code: GWDDR014) | E17: metre | F17: GWD DR | G17: Borewell | H17: PVC Casing Pipe (BW/FPW) | I17: ='BW Casing Pipes'!F195 -> 209.05 | J17: ='BW Casing Pipes'!F208 -> 11.2 | K17: =J17*($L$2-1) -> 0 | L17: =SUM(I17:K17) -> 220.25
A18: 15 | B18: GWDDR015 | C18: ='BW Casing Pipes'!B210 -> Supplying, assembling, lowering and fixing in vertical position in Borewell, PVC 110 mm 4 Kg/cm2 well casing pipe of required dia, conforming to IS : 4985:2000, including required hire and labour charges, fittings & accessories etc. all complete, for all depths, as per direction of Engineer- in- Charge. | D18: =CONCATENATE(C18," (Code: ",B18,")") -> Supplying, assembling, lowering and fixing in vertical position in Borewell, PVC 110 mm 4 Kg/cm2 well casing pipe of required dia, conforming to IS : 4985:2000, including required hire and labour charges, fittings & accessories etc. all complete, for all depths, as per direction of Engineer- in- Charge. (Code: GWDDR015) | E18: metre | F18: GWD DR | G18: Borewell | H18: PVC Casing Pipe (BW/FPW) | I18: ='BW Casing Pipes'!F221 -> 197.45 | J18: ='BW Casing Pipes'!F234 -> 11.2 | K18: =J18*($L$2-1) -> 0 | L18: =SUM(I18:K18) -> 208.65
A19: 16 | B19: GWDDR016 | C19: ='BW Casing Pipes'!B236 -> Supplying, assembling, lowering and fixing in vertical position in Borewell, PVC 140 mm 10 Kg/cm2 well casing pipe of required dia, conforming to IS : 4985:2000, including required hire and labour charges, fittings & accessories etc. all complete, for all depths, as per direction of Engineer- in- Charge. | D19: =CONCATENATE(C19," (Code: ",B19,")") -> Supplying, assembling, lowering and fixing in vertical position in Borewell, PVC 140 mm 10 Kg/cm2 well casing pipe of required dia, conforming to IS : 4985:2000, including required hire and labour charges, fittings & accessories etc. all complete, for all depths, as per direction of Engineer- in- Charge. (Code: GWDDR016) | E19: metre | F19: GWD DR | G19: Borewell | H19: PVC Casing Pipe (BW/FPW) | I19: ='BW Casing Pipes'!F247 -> 557.5 | J19: ='BW Casing Pipes'!F260 -> 11.2 | K19: =J19*($L$2-1) -> 0 | L19: =SUM(I19:K19) -> 568.7
A20: 17 | B20: GWDDR017 | C20: ='BW Casing Pipes'!B262 -> Supplying, assembling, lowering and fixing in vertical position in Borewell, PVC 180mm 10 Kg/cm2 well casing pipe of required dia, conforming to IS : 4985:2000, including required hire and labour charges, fittings & accessories etc. all complete, for all depths, as per direction of Engineer- in- Charge. | D20: =CONCATENATE(C20," (Code: ",B20,")") -> Supplying, assembling, lowering and fixing in vertical position in Borewell, PVC 180mm 10 Kg/cm2 well casing pipe of required dia, conforming to IS : 4985:2000, including required hire and labour charges, fittings & accessories etc. all complete, for all depths, as per direction of Engineer- in- Charge. (Code: GWDDR017) | E20: metre | F20: GWD DR | G20: Borewell | H20: PVC Casing Pipe (BW/FPW) | I20: ='BW Casing Pipes'!F273 -> 914.1 | J20: ='BW Casing Pipes'!F286 -> 11.2 | K20: =J20*($L$2-1) -> 0 | L20: =SUM(I20:K20) -> 925.3
A21: 18 | B21: GWDDR018 | C21: ='TW Casing Pipes'!B2 -> Supplying, assembling, lowering and fixing in vertical position in bore well, unplasticized PVC medium well casing (CM) pipe of required dia, conforming to IS : 12818, including required hire and labour charges, fittings & accessories etc. all complete, for all depths, as per direction of Engineer- in- Charge. 200 mm nominal size dia (23.3.3) | D21: =CONCATENATE(C21," (Code: ",B21,")") -> Supplying, assembling, lowering and fixing in vertical position in bore well, unplasticized PVC medium well casing (CM) pipe of required dia, conforming to IS : 12818, including required hire and labour charges, fittings & accessories etc. all complete, for all depths, as per direction of Engineer- in- Charge. 200 mm nominal size dia (23.3.3) (Code: GWDDR018) | E21: metre | F21: GWD DR | G21: Tubewell | H21: UPVC Casing Pipe (TW) | I21: 0 | J21: ='TW Casing Pipes'!C2 -> 826.44 | K21: =J21*($L$2-1) -> 0 | L21: =SUM(I21:K21) -> 826.44
A22: 19 | B22: GWDDR019 | C22: ='TW Casing Pipes'!B3 -> Supplying, assembling, lowering and fixing in vertical position in bore well unplasticized PVC medium well screen (RMS) pipes with ribs, conforming to IS: 12818, including hire & labour charges, fittings & accessories etc. all complete, for all depths, as per direction of Engineer - in-charge 200 mm nominal size dia (23.4.3) | D22: =CONCATENATE(C22," (Code: ",B22,")") -> Supplying, assembling, lowering and fixing in vertical position in bore well unplasticized PVC medium well screen (RMS) pipes with ribs, conforming to IS: 12818, including hire & labour charges, fittings & accessories etc. all complete, for all depths, as per direction of Engineer - in-charge 200 mm nominal size dia (23.4.3) (Code: GWDDR019) | E22: metre | F22: GWD DR | G22: Tubewell | H22: UPVC Casing Pipe (TW) | I22: 0 | J22: ='TW Casing Pipes'!C3 -> 954.28 | K22: =J22*($L$2-1) -> 0 | L22: =SUM(I22:K22) -> 954.28
A23: 20 | B23: GWDDR020 | C23: ='TW Casing Pipes'!B4 -> M.S. cap 200 mm dia (7748 - Water Charge and CPOH Added) | D23: =CONCATENATE(C23," (Code: ",B23,")") -> M.S. cap 200 mm dia (7748 - Water Charge and CPOH Added) (Code: GWDDR020) | E23: each | F23: GWD DR | G23: Tubewell | H23: Tubewell Fittings | I23: 0 | J23: ='TW Casing Pipes'!C4 -> 232.3 | K23: =J23*($L$2-1) -> 0 | L23: =SUM(I23:K23) -> 232.3
A24: 21 | B24: GWDDR021 | C24: ='TW Casing Pipes'!B5 -> Providing and fixing Bail plug / Bottom plug of required dia to the bottom of pipe assembly of tubewell as per IS : 2800 (part I). 200 mm dia (23.15.3) | D24: =CONCATENATE(C24," (Code: ",B24,")") -> Providing and fixing Bail plug / Bottom plug of required dia to the bottom of pipe assembly of tubewell as per IS : 2800 (part I). 200 mm dia (23.15.3) (Code: GWDDR021) | E24: each | F24: GWD DR | G24: Tubewell | H24: Tubewell Fittings | I24: 0 | J24: ='TW Casing Pipes'!C5 -> 267.85 | K24: =J24*($L$2-1) -> 0 | L24: =SUM(I24:K24) -> 267.85
A25: 22 | B25: GWDDR022 | C25: ='TW Casing Pipes'!B6 -> Supplying, assembling, lowering and fixing in vertical position in bore well, unplasticized PVC medium well casing (CM) pipe of required dia, conforming to IS : 12818, including required hire and labour charges, fittings & accessories etc. all complete, for all depths, as per direction of Engineer- in- Charge. 150 mm nominal size dia (23.3.2) | D25: =CONCATENATE(C25," (Code: ",B25,")") -> Supplying, assembling, lowering and fixing in vertical position in bore well, unplasticized PVC medium well casing (CM) pipe of required dia, conforming to IS : 12818, including required hire and labour charges, fittings & accessories etc. all complete, for all depths, as per direction of Engineer- in- Charge. 150 mm nominal size dia (23.3.2) (Code: GWDDR022) | E25: metre | F25: GWD DR | G25: Tubewell | H25: UPVC Casing Pipe (TW) | I25: 0 | J25: ='TW Casing Pipes'!C6 -> 580.35 | K25: =J25*($L$2-1) -> 0 | L25: =SUM(I25:K25) -> 580.35
A26: 23 | B26: GWDDR023 | C26: ='TW Casing Pipes'!B7 -> Supplying, assembling, lowering and fixing in vertical position in bore well unplasticized PVC medium well screen (RMS) pipes with ribs, conforming to IS: 12818, including hire & labour charges, fittings & accessories etc. all complete, for all depths, as per direction of Engineer - in-charge 150 mm nominal size dia (23.4.2) | D26: =CONCATENATE(C26," (Code: ",B26,")") -> Supplying, assembling, lowering and fixing in vertical position in bore well unplasticized PVC medium well screen (RMS) pipes with ribs, conforming to IS: 12818, including hire & labour charges, fittings & accessories etc. all complete, for all depths, as per direction of Engineer - in-charge 150 mm nominal size dia (23.4.2) (Code: GWDDR023) | E26: metre | F26: GWD DR | G26: Tubewell | H26: UPVC Casing Pipe (TW) | I26: 0 | J26: ='TW Casing Pipes'!C7 -> 591.96 | K26: =J26*($L$2-1) -> 0 | L26: =SUM(I26:K26) -> 591.96
A27: 24 | B27: GWDDR024 | C27: ='TW Casing Pipes'!B8 -> M.S. cap 150 mm dia (7747 - Water Charge and CPOH Added) | D27: =CONCATENATE(C27," (Code: ",B27,")") -> M.S. cap 150 mm dia (7747 - Water Charge and CPOH Added) (Code: GWDDR024) | E27: each | F27: GWD DR | G27: Tubewell | H27: Tubewell Fittings | I27: 0 | J27: ='TW Casing Pipes'!C8 -> 174.225 | K27: =J27*($L$2-1) -> 0 | L27: =SUM(I27:K27) -> 174.225
A28: 25 | B28: GWDDR025 | C28: ='TW Casing Pipes'!B9 -> Providing and fixing Bail plug / Bottom plug of required dia to the bottom of pipe assembly of tubewell as per IS : 2800 (part I). 150 mm dia (23.15.2) | D28: =CONCATENATE(C28," (Code: ",B28,")") -> Providing and fixing Bail plug / Bottom plug of required dia to the bottom of pipe assembly of tubewell as per IS : 2800 (part I). 150 mm dia (23.15.2) (Code: GWDDR025) | E28: each | F28: GWD DR | G28: Tubewell | H28: Tubewell Fittings | I28: 0 | J28: ='TW Casing Pipes'!C9 -> 244.62 | K28: =J28*($L$2-1) -> 0 | L28: =SUM(I28:K28) -> 244.62
A29: 26 | B29: GWDDR026 | C29: ='TW Casing Pipes'!B10 -> Supplying, assembling, lowering and fixing in vertical position in bore well, unplasticized PVC medium well casing (CM) pipe of required dia, conforming to IS : 12818, including required hire and labour charges, fittings & accessories etc. all complete, for all depths, as per direction of Engineer- in- Charge. 100 mm nominal size dia (23.3.1) | D29: =CONCATENATE(C29," (Code: ",B29,")") -> Supplying, assembling, lowering and fixing in vertical position in bore well, unplasticized PVC medium well casing (CM) pipe of required dia, conforming to IS : 12818, including required hire and labour charges, fittings & accessories etc. all complete, for all depths, as per direction of Engineer- in- Charge. 100 mm nominal size dia (23.3.1) (Code: GWDDR026) | E29: metre | F29: GWD DR | G29: Tubewell | H29: UPVC Casing Pipe (TW) | I29: 0 | J29: ='TW Casing Pipes'!C10 -> 480.23 | K29: =J29*($L$2-1) -> 0 | L29: =SUM(I29:K29) -> 480.23
A30: 27 | B30: GWDDR027 | C30: ='TW Casing Pipes'!B11 -> Supplying, assembling, lowering and fixing in vertical position in bore well unplasticized PVC medium well screen (RMS) pipes with ribs, conforming to IS: 12818, including hire & labour charges, fittings & accessories etc. all complete, for all depths, as per direction of Engineer - in-charge 100 mm nominal size dia (23.4.1) | D30: =CONCATENATE(C30," (Code: ",B30,")") -> Supplying, assembling, lowering and fixing in vertical position in bore well unplasticized PVC medium well screen (RMS) pipes with ribs, conforming to IS: 12818, including hire & labour charges, fittings & accessories etc. all complete, for all depths, as per direction of Engineer - in-charge 100 mm nominal size dia (23.4.1) (Code: GWDDR027) | E30: metre | F30: GWD DR | G30: Tubewell | H30: UPVC Casing Pipe (TW) | I30: 0 | J30: ='TW Casing Pipes'!C11 -> 503.46 | K30: =J30*($L$2-1) -> 0 | L30: =SUM(I30:K30) -> 503.46
A31: 28 | B31: GWDDR028 | C31: ='TW Casing Pipes'!B12 -> M.S. cap 100 mm dia (7760 - Water Charge and CPOH Added) | D31: =CONCATENATE(C31," (Code: ",B31,")") -> M.S. cap 100 mm dia (7760 - Water Charge and CPOH Added) (Code: GWDDR028) | E31: each | F31: GWD DR | G31: Tubewell | H31: Tubewell Fittings | I31: 0 | J31: ='TW Casing Pipes'!C12 -> 156.8025 | K31: =J31*($L$2-1) -> 0 | L31: =SUM(I31:K31) -> 156.8025
A32: 29 | B32: GWDDR029 | C32: ='TW Casing Pipes'!B13 -> Providing and fixing Bail plug / Bottom plug of required dia to the bottom of pipe assembly of tubewell as per IS : 2800 (part I). 100 mm dia (23.15.1) | D32: =CONCATENATE(C32," (Code: ",B32,")") -> Providing and fixing Bail plug / Bottom plug of required dia to the bottom of pipe assembly of tubewell as per IS : 2800 (part I). 100 mm dia (23.15.1) (Code: GWDDR029) | E32: each | F32: GWD DR | G32: Tubewell | H32: Tubewell Fittings | I32: 0 | J32: ='TW Casing Pipes'!C13 -> 198.15 | K32: =J32*($L$2-1) -> 0 | L32: =SUM(I32:K32) -> 198.15
A33: 30 | B33: GWDDR030 | C33: ='GI wo Trench'!B2 -> Providing and fixing G.I. pipes complete with G.I fittings: 25 mm dia nominal bore | D33: =CONCATENATE(C33," (Code: ",B33,")") -> Providing and fixing G.I. pipes complete with G.I fittings: 25 mm dia nominal bore (Code: GWDDR030) | E33: metre | F33: GWD DR | G33: MWSS | H33: GI Pipes Without Trenching | I33: 0 | J33: ='GI wo Trench'!F21 -> 263.95 | K33: =J33*($L$2-1) -> 0 | L33: =SUM(I33:K33) -> 263.95
A34: 31 | B34: GWDDR031 | C34: ='GI wo Trench'!B22 -> Providing and fixing G.I. pipes complete with G.I fittings: 32 mm dia nominal bore | D34: =CONCATENATE(C34," (Code: ",B34,")") -> Providing and fixing G.I. pipes complete with G.I fittings: 32 mm dia nominal bore (Code: GWDDR031) | E34: metre | F34: GWD DR | G34: MWSS | H34: GI Pipes Without Trenching | I34: 0 | J34: ='GI wo Trench'!F41 -> 298.45 | K34: =J34*($L$2-1) -> 0 | L34: =SUM(I34:K34) -> 298.45
A35: 32 | B35: GWDDR032 | C35: ='GI wo Trench'!B42 -> Providing and fixing G.I. pipes complete with G.I fittings: 40 mm dia nominal bore | D35: =CONCATENATE(C35," (Code: ",B35,")") -> Providing and fixing G.I. pipes complete with G.I fittings: 40 mm dia nominal bore (Code: GWDDR032) | E35: metre | F35: GWD DR | G35: MWSS | H35: GI Pipes Without Trenching | I35: 0 | J35: ='GI wo Trench'!F61 -> 385.85 | K35: =J35*($L$2-1) -> 0 | L35: =SUM(I35:K35) -> 385.85
A36: 33 | B36: GWDDR033 | C36: ='GI wo Trench'!B62 -> Providing and fixing G.I. pipes complete with G.I fittings: 50 mm dia nominal bore | D36: =CONCATENATE(C36," (Code: ",B36,")") -> Providing and fixing G.I. pipes complete with G.I fittings: 50 mm dia nominal bore (Code: GWDDR033) | E36: metre | F36: GWD DR | G36: MWSS | H36: GI Pipes Without Trenching | I36: 0 | J36: ='GI wo Trench'!F81 -> 469 | K36: =J36*($L$2-1) -> 0 | L36: =SUM(I36:K36) -> 469
A37: 34 | B37: GWDDR034 | C37: ='GI wo Trench'!B82 -> Providing and fixing G.I. pipes complete with G.I fittings: 65 mm dia nominal bore | D37: =CONCATENATE(C37," (Code: ",B37,")") -> Providing and fixing G.I. pipes complete with G.I fittings: 65 mm dia nominal bore (Code: GWDDR034) | E37: metre | F37: GWD DR | G37: MWSS | H37: GI Pipes Without Trenching | I37: 0 | J37: ='GI wo Trench'!F101 -> 568.35 | K37: =J37*($L$2-1) -> 0 | L37: =SUM(I37:K37) -> 568.35
A38: 35 | B38: GWDDR035 | C38: ='GI wo Trench'!B102 -> Providing and fixing G.I. pipes complete with G.I fittings: 80 mm dia nominal bore | D38: =CONCATENATE(C38," (Code: ",B38,")") -> Providing and fixing G.I. pipes complete with G.I fittings: 80 mm dia nominal bore (Code: GWDDR035) | E38: metre | F38: GWD DR | G38: MWSS | H38: GI Pipes Without Trenching | I38: 0 | J38: ='GI wo Trench'!F121 -> 699 | K38: =J38*($L$2-1) -> 0 | L38: =SUM(I38:K38) -> 699
A39: 36 | B39: GWDDR036 | C39: ='PVC wo Trench PRICE'!B24 -> Providing and fixing PVC pipes includes jointing of pipes with one step PVC solvent cement & testing of joints complete as per direction of Engineer in Charge. 25 mm dia 10KGF/cm2 | D39: =CONCATENATE(C39," (Code: ",B39,")") -> Providing and fixing PVC pipes includes jointing of pipes with one step PVC solvent cement & testing of joints complete as per direction of Engineer in Charge. 25 mm dia 10KGF/cm2 (Code: GWDDR036) | E39: metre | F39: GWD DR | G39: MWSS | H39: PVC Pipes Without Trenching | I39: ='PVC wo Trench PRICE'!F35 -> 64.11 | J39: ='PVC wo Trench PRICE'!F44 -> 29.66 | K39: =J39*($L$2-1) -> 0 | L39: =SUM(I39:K39) -> 93.77
A40: 37 | B40: GWDDR037 | C40: ='PVC wo Trench PRICE'!B46 -> Providing and fixing PVC pipes includes jointing of pipes with one step PVC solvent cement & testing of joints complete as per direction of Engineer in Charge. 32 mm dia 10KGF/cm2 | D40: =CONCATENATE(C40," (Code: ",B40,")") -> Providing and fixing PVC pipes includes jointing of pipes with one step PVC solvent cement & testing of joints complete as per direction of Engineer in Charge. 32 mm dia 10KGF/cm2 (Code: GWDDR037) | E40: metre | F40: GWD DR | G40: MWSS | H40: PVC Pipes Without Trenching | I40: ='PVC wo Trench PRICE'!F57 -> 86.82 | J40: ='PVC wo Trench PRICE'!F66 -> 29.66 | K40: =J40*($L$2-1) -> 0 | L40: =SUM(I40:K40) -> 116.48
A41: 38 | B41: GWDDR038 | C41: ='PVC wo Trench PRICE'!B68 -> Providing and fixing PVC pipes includes jointing of pipes with one step PVC solvent cement & testing of joints complete as per direction of Engineer in Charge. 32 mm dia 6 KGF/cm2 | D41: =CONCATENATE(C41," (Code: ",B41,")") -> Providing and fixing PVC pipes includes jointing of pipes with one step PVC solvent cement & testing of joints complete as per direction of Engineer in Charge. 32 mm dia 6 KGF/cm2 (Code: GWDDR038) | E41: metre | F41: GWD DR | G41: MWSS | H41: PVC Pipes Without Trenching | I41: ='PVC wo Trench PRICE'!F79 -> 69.46 | J41: ='PVC wo Trench PRICE'!F88 -> 29.66 | K41: =J41*($L$2-1) -> 0 | L41: =SUM(I41:K41) -> 99.12
A42: 39 | B42: GWDDR039 | C42: ='PVC wo Trench PRICE'!B90 -> Providing and fixing PVC pipes includes jointing of pipes with one step PVC solvent cement & testing of joints complete as per direction of Engineer in Charge. 40 mm dia 6 KGF/cm2 | D42: =CONCATENATE(C42," (Code: ",B42,")") -> Providing and fixing PVC pipes includes jointing of pipes with one step PVC solvent cement & testing of joints complete as per direction of Engineer in Charge. 40 mm dia 6 KGF/cm2 (Code: GWDDR039) | E42: metre | F42: GWD DR | G42: MWSS | H42: PVC Pipes Without Trenching | I42: ='PVC wo Trench PRICE'!F101 -> 70.79 | J42: ='PVC wo Trench PRICE'!F110 -> 29.66 | K42: =J42*($L$2-1) -> 0 | L42: =SUM(I42:K42) -> 100.45
A43: 40 | B43: GWDDR040 | C43: ='PVC wo Trench PRICE'!B112 -> Providing and fixing PVC pipes includes jointing of pipes with one step PVC solvent cement & testing of joints complete as per direction of Engineer in Charge. 40 mm dia 10 KGF/cm2 | D43: =CONCATENATE(C43," (Code: ",B43,")") -> Providing and fixing PVC pipes includes jointing of pipes with one step PVC solvent cement & testing of joints complete as per direction of Engineer in Charge. 40 mm dia 10 KGF/cm2 (Code: GWDDR040) | E43: metre | F43: GWD DR | G43: MWSS | H43: PVC Pipes Without Trenching | I43: ='PVC wo Trench PRICE'!F123 -> 112.2 | J43: ='PVC wo Trench PRICE'!F132 -> 29.66 | K43: =J43*($L$2-1) -> 0 | L43: =SUM(I43:K43) -> 141.86
A44: 41 | B44: GWDDR041 | C44: ='PVC wo Trench PRICE'!B134 -> Providing and fixing PVC pipes includes jointing of pipes with one step PVC solvent cement & testing of joints complete as per direction of Engineer in Charge. 50 mm dia 6 KGF/cm2 | D44: =CONCATENATE(C44," (Code: ",B44,")") -> Providing and fixing PVC pipes includes jointing of pipes with one step PVC solvent cement & testing of joints complete as per direction of Engineer in Charge. 50 mm dia 6 KGF/cm2 (Code: GWDDR041) | E44: metre | F44: GWD DR | G44: MWSS | H44: PVC Pipes Without Trenching | I44: ='PVC wo Trench PRICE'!F145 -> 80.14 | J44: ='PVC wo Trench PRICE'!F154 -> 29.66 | K44: =J44*($L$2-1) -> 0 | L44: =SUM(I44:K44) -> 109.8
A45: 42 | B45: GWDDR042 | C45: ='PVC wo Trench PRICE'!B156 -> Providing and fixing PVC pipes includes jointing of pipes with one step PVC solvent cement & testing of joints complete as per direction of Engineer in Charge. 50 mm dia 10 KGF/cm2 | D45: =CONCATENATE(C45," (Code: ",B45,")") -> Providing and fixing PVC pipes includes jointing of pipes with one step PVC solvent cement & testing of joints complete as per direction of Engineer in Charge. 50 mm dia 10 KGF/cm2 (Code: GWDDR042) | E45: metre | F45: GWD DR | G45: MWSS | H45: PVC Pipes Without Trenching | I45: ='PVC wo Trench PRICE'!F167 -> 120.22 | J45: ='PVC wo Trench PRICE'!F176 -> 29.66 | K45: =J45*($L$2-1) -> 0 | L45: =SUM(I45:K45) -> 149.88
A46: 43 | B46: GWDDR043 | C46: ='PVC wo Trench PRICE'!B178 -> Providing and fixing PVC pipes includes jointing of pipes with one step PVC solvent cement & testing of joints complete as per direction of Engineer in Charge.63 mm dia 6 KGF/cm2 | D46: =CONCATENATE(C46," (Code: ",B46,")") -> Providing and fixing PVC pipes includes jointing of pipes with one step PVC solvent cement & testing of joints complete as per direction of Engineer in Charge.63 mm dia 6 KGF/cm2 (Code: GWDDR043) | E46: metre | F46: GWD DR | G46: MWSS | H46: PVC Pipes Without Trenching | I46: ='PVC wo Trench PRICE'!F189 -> 157.62 | J46: ='PVC wo Trench PRICE'!F198 -> 29.66 | K46: =J46*($L$2-1) -> 0 | L46: =SUM(I46:K46) -> 187.28
A47: 44 | B47: GWDDR044 | C47: ='PVC wo Trench PRICE'!B200 -> Providing and fixing PVC pipes includes jointing of pipes with one step PVC solvent cement & testing of joints complete as per direction of Engineer in Charge.75 mm dia 6 KGF/cm2 | D47: =CONCATENATE(C47," (Code: ",B47,")") -> Providing and fixing PVC pipes includes jointing of pipes with one step PVC solvent cement & testing of joints complete as per direction of Engineer in Charge.75 mm dia 6 KGF/cm2 (Code: GWDDR044) | E47: metre | F47: GWD DR | G47: MWSS | H47: PVC Pipes Without Trenching | I47: ='PVC wo Trench PRICE'!F211 -> 172.31 | J47: ='PVC wo Trench PRICE'!F220 -> 29.66 | K47: =J47*($L$2-1) -> 0 | L47: =SUM(I47:K47) -> 201.97
A48: 45 | B48: GWDDR045 | C48: ='PVC wo Trench PRICE'!B222 -> Providing and fixing PVC pipes includes jointing of pipes with one step PVC solvent cement & testing of joints complete as per direction of Engineer in Charge.110 mm dia 6 KGF/cm2 | D48: =CONCATENATE(C48," (Code: ",B48,")") -> Providing and fixing PVC pipes includes jointing of pipes with one step PVC solvent cement & testing of joints complete as per direction of Engineer in Charge.110 mm dia 6 KGF/cm2 (Code: GWDDR045) | E48: metre | F48: GWD DR | G48: MWSS | H48: PVC Pipes Without Trenching | I48: ='PVC wo Trench PRICE'!F233 -> 281.84 | J48: ='PVC wo Trench PRICE'!F242 -> 29.66 | K48: =J48*($L$2-1) -> 0 | L48: =SUM(I48:K48) -> 311.5
A49: 46 | B49: GWDDR046 | C49: ='PVC wo Trench PRICE'!B244 -> Providing and fixing PVC pipes includes jointing of pipes with one step PVC solvent cement & testing of joints complete as per direction of Engineer in Charge.150 mm dia 6 KGF/cm2 | D49: =CONCATENATE(C49," (Code: ",B49,")") -> Providing and fixing PVC pipes includes jointing of pipes with one step PVC solvent cement & testing of joints complete as per direction of Engineer in Charge.150 mm dia 6 KGF/cm2 (Code: GWDDR046) | E49: metre | F49: GWD DR | G49: MWSS | H49: PVC Pipes Without Trenching | I49: ='PVC wo Trench PRICE'!F255 -> 694.58 | J49: ='PVC wo Trench PRICE'!F264 -> 29.66 | K49: =J49*($L$2-1) -> 0 | L49: =SUM(I49:K49) -> 724.24
A50: 47 | B50: GWDDR047 | C50: ='PVC wo Trench'!B1 -> Providing and fixing PVC pipes includes jointing of pipes with one step PVC solvent cement & testing of joints complete as per direction of Engineer in Charge. 140 mm dia 6 KGF/cm2 | D50: =CONCATENATE(C50," (Code: ",B50,")") -> Providing and fixing PVC pipes includes jointing of pipes with one step PVC solvent cement & testing of joints complete as per direction of Engineer in Charge. 140 mm dia 6 KGF/cm2 (Code: GWDDR047) | E50: metre | F50: GWD DR | G50: MWSS | H50: PVC Pipes Without Trenching | I50: ='PVC wo Trench'!F12 -> 375.34 | J50: ='PVC wo Trench'!F21 -> 93.63 | K50: =J50*($L$2-1) -> 0 | L50: =SUM(I50:K50) -> 468.97
A51: 48 | B51: GWDDR048 | C51: ='PVC With Trench'!B2 -> Providing and fixing PVC pipes includes jointing of pipes with one step PVC solvent cement, trenching, refilling & testing of joints complete as per direction of Engineer in Charge. 140 mm dia 6 KGF/cm2 | D51: =CONCATENATE(C51," (Code: ",B51,")") -> Providing and fixing PVC pipes includes jointing of pipes with one step PVC solvent cement, trenching, refilling & testing of joints complete as per direction of Engineer in Charge. 140 mm dia 6 KGF/cm2 (Code: GWDDR048) | E51: metre | F51: GWD DR | G51: MWSS | H51: PVC Pipes With Trenching | I51: ='PVC With Trench'!F13 -> 375.34 | J51: ='PVC With Trench'!F25 -> 226.23 | K51: =J51*($L$2-1) -> 0 | L51: =SUM(I51:K51) -> 601.57
A52: 49 | B52: GWDDR049 | C52: ='Pump Erection '!B2 -> Borewell submersible pump erection charges upto 3 HP | D52: =CONCATENATE(C52," (Code: ",B52,")") -> Borewell submersible pump erection charges upto 3 HP (Code: GWDDR049) | E52: each | F52: GWD DR | G52: MWSS | H52: Pump Erection | I52: ='Pump Erection '!F9 -> 1086.0025 | J52: ='Pump Erection '!F17 -> 5972.433 | K52: =J52*($L$2-1) -> 0 | L52: =SUM(I52:K52) -> 7058.4355
A53: 50 | B53: GWDDR050 | C53: ='Pump Erection '!B19 -> Borewell submersible pump erection charges above 3 h.P. To 7.5 H.P. | D53: =CONCATENATE(C53," (Code: ",B53,")") -> Borewell submersible pump erection charges above 3 h.P. To 7.5 H.P. (Code: GWDDR050) | E53: each | F53: GWD DR | G53: MWSS | H53: Pump Erection | I53: ='Pump Erection '!F26 -> 1086.0025 | J53: ='Pump Erection '!F34 -> 7592.7255 | K53: =J53*($L$2-1) -> 0 | L53: =SUM(I53:K53) -> 8678.728
A54: 51 | B54: GWDDR051 | C54: ='Pump Erection '!B36 -> Borewell submersible pump erection charges above 7.5 H.P. | D54: =CONCATENATE(C54," (Code: ",B54,")") -> Borewell submersible pump erection charges above 7.5 H.P. (Code: GWDDR051) | E54: each | F54: GWD DR | G54: MWSS | H54: Pump Erection | I54: ='Pump Erection '!F43 -> 1086.0025 | J54: ='Pump Erection '!F51 -> 9213.018 | K54: =J54*($L$2-1) -> 0 | L54: =SUM(I54:K54) -> 10299.021
A55: 52 | B55: GWDDR052 | C55: ='HP Erection and Pullout'!B2 -> Hand pump erection (deep well) | D55: =CONCATENATE(C55," (Code: ",B55,")") -> Hand pump erection (deep well) (Code: GWDDR052) | E55: each | F55: GWD DR | G55: Hand Pump | H55: HP Erection | I55: 0 | J55: ='HP Erection and Pullout'!F11 -> 4310 | K55: =J55*($L$2-1) -> 0 | L55: =SUM(I55:K55) -> 4310
A56: 53 | B56: GWDDR053 | C56: ='HP Erection and Pullout'!B13 -> Hand pump erection (extra deep well) | D56: =CONCATENATE(C56," (Code: ",B56,")") -> Hand pump erection (extra deep well) (Code: GWDDR053) | E56: each | F56: GWD DR | G56: Hand Pump | H56: HP Erection | I56: 0 | J56: ='HP Erection and Pullout'!F22 -> 5569 | K56: =J56*($L$2-1) -> 0 | L56: =SUM(I56:K56) -> 5569
A57: 54 | B57: GWDDR054 | C57: ='HP Erection and Pullout'!B24 -> Hand pump pullout (deep well) | D57: =CONCATENATE(C57," (Code: ",B57,")") -> Hand pump pullout (deep well) (Code: GWDDR054) | E57: each | F57: GWD DR | G57: Hand Pump | H57: HP Pullout | I57: 0 | J57: ='HP Erection and Pullout'!F33 -> 2155 | K57: =J57*($L$2-1) -> 0 | L57: =SUM(I57:K57) -> 2155
A58: 55 | B58: GWDDR055 | C58: ='Pump Erection '!B53 -> Compressor pump fitting charge | D58: =CONCATENATE(C58," (Code: ",B58,")") -> Compressor pump fitting charge (Code: GWDDR055) | E58: each | F58: GWD DR | G58: MWSS | H58: Pump Erection | I58: 0 | J58: ='Pump Erection '!F62 -> 3615.7495 | K58: =J58*($L$2-1) -> 0 | L58: =SUM(I58:K58) -> 3615.7495
A59: 56 | B59: GWDDR056 | C59: ='Gutter&Clamp'!B2 -> Providing and fixing PVC full pipe as gutter pipes includes laying jointing of pipes complete as per direction of Engineer in Charge for 140 mm dia 6 KGF/cm2 | D59: =CONCATENATE(C59," (Code: ",B59,")") -> Providing and fixing PVC full pipe as gutter pipes includes laying jointing of pipes complete as per direction of Engineer in Charge for 140 mm dia 6 KGF/cm2 (Code: GWDDR056) | E59: metre | F59: GWD DR | G59: ARS | H59: ARS Pipes | I59: ='Gutter&Clamp'!F14 -> 342.7 | J59: ='Gutter&Clamp'!F24 -> 93.19 | K59: =J59*($L$2-1) -> 0 | L59: =SUM(I59:K59) -> 435.89
A60: 57 | B60: GWDDR057 | C60: ='Gutter&Clamp'!B26 -> Providing and fixing PVC gutter pipes includes laying jointing of pipes, complete as per direction of Engineer in Charge.for 160 mm dia 6 KGF/cm2 | D60: =CONCATENATE(C60," (Code: ",B60,")") -> Providing and fixing PVC gutter pipes includes laying jointing of pipes, complete as per direction of Engineer in Charge.for 160 mm dia 6 KGF/cm2 (Code: GWDDR057) | E60: metre | F60: GWD DR | G60: ARS | H60: ARS Pipes | I60: ='Gutter&Clamp'!F38 -> 471.98 | J60: ='Gutter&Clamp'!F48 -> 93.19 | K60: =J60*($L$2-1) -> 0 | L60: =SUM(I60:K60) -> 565.17
A61: 58 | B61: GWDDR058 | C61: ='Gutter&Clamp'!B50 -> Providing and fixing 140mm square PVC gutter pipes includes laying jointing of pipes including clamp, complete as per direction of Engineer in Charge | D61: =CONCATENATE(C61," (Code: ",B61,")") -> Providing and fixing 140mm square PVC gutter pipes includes laying jointing of pipes including clamp, complete as per direction of Engineer in Charge (Code: GWDDR058) | E61: metre | F61: GWD DR | G61: ARS | H61: ARS Pipes | I61: ='Gutter&Clamp'!F62 -> 414.66 | J61: ='Gutter&Clamp'!F72 -> 93.19 | K61: =J61*($L$2-1) -> 0 | L61: =SUM(I61:K61) -> 507.85
A62: 59 | B62: GWDDR059 | C62: ='Gutter&Clamp'!B74 -> Providing and fixing 160mm square PVC gutter pipes includes laying jointing of pipes including clamp, complete as per direction of Engineer in Charge | D62: =CONCATENATE(C62," (Code: ",B62,")") -> Providing and fixing 160mm square PVC gutter pipes includes laying jointing of pipes including clamp, complete as per direction of Engineer in Charge (Code: GWDDR059) | E62: metre | F62: GWD DR | G62: ARS | H62: ARS Pipes | I62: ='Gutter&Clamp'!F86 -> 467.5 | J62: ='Gutter&Clamp'!F96 -> 93.19 | K62: =J62*($L$2-1) -> 0 | L62: =SUM(I62:K62) -> 560.69
A63: 60 | B63: GWDDR060 | C63: ='Gutter&Clamp'!B98 -> Providing and fixing MS Clamp for gutter pipe as per direction of Engineer in Charge. | D63: =CONCATENATE(C63," (Code: ",B63,")") -> Providing and fixing MS Clamp for gutter pipe as per direction of Engineer in Charge. (Code: GWDDR060) | E63: each | F63: GWD DR | G63: ARS | H63: ARS Fittings | I63: ='Gutter&Clamp'!F109 -> 40.65 | J63: ='Gutter&Clamp'!F119 -> 29.44 | K63: =J63*($L$2-1) -> 0 | L63: =SUM(I63:K63) -> 70.09
A64: 61 | B64: GWDDR061 | C64: =Hydrants!A1 -> Hydrants with tap (for common use of size 0.8 x 0.5 m platform) | D64: =CONCATENATE(C64," (Code: ",B64,")") -> Hydrants with tap (for common use of size 0.8 x 0.5 m platform) (Code: GWDDR061) | E64: each | F64: GWD DR | G64: MWSS | H64: Hydrants | I64: =Hydrants!G13 -> 671.93 | J64: =Hydrants!G25 -> 1562.02 | K64: =J64*($L$2-1) -> 0 | L64: =SUM(I64:K64) -> 2233.95
A65: 62 | B65: GWDDR062 | C65: =Hydrants!A27 -> Hydrants with tap ( for individual families of size 0.6 X 0.3 M platform) | D65: =CONCATENATE(C65," (Code: ",B65,")") -> Hydrants with tap ( for individual families of size 0.6 X 0.3 M platform) (Code: GWDDR062) | E65: each | F65: GWD DR | G65: MWSS | H65: Hydrants | I65: =Hydrants!G39 -> 671.93 | J65: =Hydrants!G51 -> 1030.38 | K65: =J65*($L$2-1) -> 0 | L65: =SUM(I65:K65) -> 1702.31
A66: 63 | B66: GWDDR063 | C66: ='HP Repair Labour'!A1 -> India Mark II Hand Pump Pullout, Repairing and Re-Erection Labour Charges | D66: =CONCATENATE(C66," (Code: ",B66,")") -> India Mark II Hand Pump Pullout, Repairing and Re-Erection Labour Charges (Code: GWDDR063) | E66: each | F66: GWD DR | G66: Hand Pump | H66: Hand Pump Repair | I66: ='HP Repair Labour'!H14 -> 0 | J66: ='HP Repair Labour'!I14 -> 6485.82 | K66: =J66*($L$2-1) -> 0 | L66: =SUM(I66:K66) -> 6485.82
A67: 64 | B67: GWDDR064 | C67: =WTP!B3 -> Supplying, assembling, fibre reinforced polymer vessel (FRP) size (14" Dia 65" Height) Weight - 21 kg, Tank Volume - 150 liter, Material- Polyethylene, Max Pressure -150 PSI, Max Vacuum- 5" Hg, Max temperature-49'c, Capacity- 1000-10000 L, opening at top & bottom including hire & labour charges, fittings & accessories etc.complete, as per direction of Engineer-in-charge | D67: =CONCATENATE(C67," (Code: ",B67,")") -> Supplying, assembling, fibre reinforced polymer vessel (FRP) size (14" Dia 65" Height) Weight - 21 kg, Tank Volume - 150 liter, Material- Polyethylene, Max Pressure -150 PSI, Max Vacuum- 5" Hg, Max temperature-49'c, Capacity- 1000-10000 L, opening at top & bottom including hire & labour charges, fittings & accessories etc.complete, as per direction of Engineer-in-charge (Code: GWDDR064) | E67: each | F67: GWD DR | G67: WTP | H67: WTP FRP Vessel | I67: =WTP!H16 -> 19164.75 | J67: =WTP!I16 -> 497.93505 | K67: =J67*($L$2-1) -> 0 | L67: =SUM(I67:K67) -> 19662.685
A68: 65 | B68: GWDDR065 | C68: =WTP!B17 -> Supplying, assembling, fibre reinforced polymer vessel (FRP) size (16" Dia 65" Height) Weight - 22 kg, Tank Volume - 185 liter, Material- Polyethylene, Max Pressure -150 PSI, Max Vacuum- 5" Hg, Max temperature-49'c, Capacity- 1000-10000 L, opening at top & bottom including hire & labour charges, fittings & accessories etc.complete, as per direction of Engineer-in-charge | D68: =CONCATENATE(C68," (Code: ",B68,")") -> Supplying, assembling, fibre reinforced polymer vessel (FRP) size (16" Dia 65" Height) Weight - 22 kg, Tank Volume - 185 liter, Material- Polyethylene, Max Pressure -150 PSI, Max Vacuum- 5" Hg, Max temperature-49'c, Capacity- 1000-10000 L, opening at top & bottom including hire & labour charges, fittings & accessories etc.complete, as per direction of Engineer-in-charge (Code: GWDDR065) | E68: each | F68: GWD DR | G68: WTP | H68: WTP FRP Vessel | I68: =WTP!H30 -> 30779.75 | J68: =WTP!I30 -> 497.93505 | K68: =J68*($L$2-1) -> 0 | L68: =SUM(I68:K68) -> 31277.685
A69: 66 | B69: GWDDR066 | C69: =WTP!B31 -> Supplying, assembling, fibre reinforced polymer vessel (FRP) Size-(18" Dia 65" Height), Weight-30kg, Tank Volume - 242 liter , Material- Polyethylene, Max Pressure -150 PSI, Max Vacuum- 5" Hg, Max Temperature -49'c, Capacity- 1000-10000 L, opening at top & bottom including hire & labour charges, fittings & accessories etc.complete, as per direction of Engineer-in-charge | D69: =CONCATENATE(C69," (Code: ",B69,")") -> Supplying, assembling, fibre reinforced polymer vessel (FRP) Size-(18" Dia 65" Height), Weight-30kg, Tank Volume - 242 liter , Material- Polyethylene, Max Pressure -150 PSI, Max Vacuum- 5" Hg, Max Temperature -49'c, Capacity- 1000-10000 L, opening at top & bottom including hire & labour charges, fittings & accessories etc.complete, as per direction of Engineer-in-charge (Code: GWDDR066) | E69: each | F69: GWD DR | G69: WTP | H69: WTP FRP Vessel | I69: =WTP!H44 -> 41814 | J69: =WTP!I44 -> 497.93505 | K69: =J69*($L$2-1) -> 0 | L69: =SUM(I69:K69) -> 42311.935
A70: 67 | B70: GWDDR067 | C70: =WTP!B45 -> Supplying, assembling, fibre reinforced polymer vessel (FRP) Size-(21" Dia 62" Height), Weight-43kg, Tank Volume -318 liter , Material- Polyethylene, Max Pressure -150 PSI, Max Vacuum- 5" Hg, Temperature-49'c, Capacity- 1000-10000 L, opening at top & bottom including hire & labour charges, fittings & accessories etc.complete, as per direction of Engineer-in-charge | D70: =CONCATENATE(C70," (Code: ",B70,")") -> Supplying, assembling, fibre reinforced polymer vessel (FRP) Size-(21" Dia 62" Height), Weight-43kg, Tank Volume -318 liter , Material- Polyethylene, Max Pressure -150 PSI, Max Vacuum- 5" Hg, Temperature-49'c, Capacity- 1000-10000 L, opening at top & bottom including hire & labour charges, fittings & accessories etc.complete, as per direction of Engineer-in-charge (Code: GWDDR067) | E70: each | F70: GWD DR | G70: WTP | H70: WTP FRP Vessel | I70: =WTP!H58 -> 47040.75 | J70: =WTP!I58 -> 497.93505 | K70: =J70*($L$2-1) -> 0 | L70: =SUM(I70:K70) -> 47538.685
A71: 68 | B71: GWDDR068 | C71: =WTP!B59 -> Supplying, assembling, fibre reinforced polymer vessel (FRP) Size-(24" Dia 72" Height), Weight-49kg, Tank Volume -451 liter , Material- Polyethylene, Max Pressure -150 PSI, Max Vacuum- 5" Hg, Temperature-49'c, Capacity- 1000-10000 L, opening at top & bottom including hire & labour charges, fittings & accessories etc.complete, as per direction of Engineer-in-charge | D71: =CONCATENATE(C71," (Code: ",B71,")") -> Supplying, assembling, fibre reinforced polymer vessel (FRP) Size-(24" Dia 72" Height), Weight-49kg, Tank Volume -451 liter , Material- Polyethylene, Max Pressure -150 PSI, Max Vacuum- 5" Hg, Temperature-49'c, Capacity- 1000-10000 L, opening at top & bottom including hire & labour charges, fittings & accessories etc.complete, as per direction of Engineer-in-charge (Code: GWDDR068) | E71: each | F71: GWD DR | G71: WTP | H71: WTP FRP Vessel | I71: =WTP!H72 -> 56913.5 | J71: =WTP!I72 -> 572.8518 | K71: =J71*($L$2-1) -> 0 | L71: =SUM(I71:K71) -> 57486.352
A72: 69 | B72: GWDDR069 | C72: =WTP!B73 -> Supplying, assembling, fibre reinforced polymer vessel (FRP) Size-(30" Dia 72" Height), Weight-90kg, Tank Volume -708 liter , Material- Polyethylene, Max Pressure -150 PSI, Max Vacuum- 5" Hg, Temperature-49'c, Capacity- 1000-10000 L, opening at top & bottom including hire & labour charges, fittings & accessories etc.complete, as per direction of Engineer-in-charge | D72: =CONCATENATE(C72," (Code: ",B72,")") -> Supplying, assembling, fibre reinforced polymer vessel (FRP) Size-(30" Dia 72" Height), Weight-90kg, Tank Volume -708 liter , Material- Polyethylene, Max Pressure -150 PSI, Max Vacuum- 5" Hg, Temperature-49'c, Capacity- 1000-10000 L, opening at top & bottom including hire & labour charges, fittings & accessories etc.complete, as per direction of Engineer-in-charge (Code: GWDDR069) | E72: each | F72: GWD DR | G72: WTP | H72: WTP FRP Vessel | I72: =WTP!H86 -> 72013 | J72: =WTP!I86 -> 754.975 | K72: =J72*($L$2-1) -> 0 | L72: =SUM(I72:K72) -> 72767.975
A73: 70 | B73: GWDDR070 | C73: =WTP!B87 -> Supplying, assembling, fibre reinforced polymer vessel (FRP) Size-(36" Dia 72" Height), Weight-105kg, Tank Volume -1020 liter , Material- Polyethylene, Max Pressure -150 PSI, Max Vacuum- 5" Hg, Temperature-49'c, Capacity- 1000-10000 L, opening at top & bottom including hire & labour charges, fittings & accessories etc.complete, as per direction of Engineer-in-charge | D73: =CONCATENATE(C73," (Code: ",B73,")") -> Supplying, assembling, fibre reinforced polymer vessel (FRP) Size-(36" Dia 72" Height), Weight-105kg, Tank Volume -1020 liter , Material- Polyethylene, Max Pressure -150 PSI, Max Vacuum- 5" Hg, Temperature-49'c, Capacity- 1000-10000 L, opening at top & bottom including hire & labour charges, fittings & accessories etc.complete, as per direction of Engineer-in-charge (Code: GWDDR070) | E73: each | F73: GWD DR | G73: WTP | H73: WTP FRP Vessel | I73: =WTP!H100 -> 96404.5 | J73: =WTP!I100 -> 754.975 | K73: =J73*($L$2-1) -> 0 | L73: =SUM(I73:K73) -> 97159.475
A74: 71 | B74: GWDDR071 | C74: =WTP!B102 -> Supplying, assembling, manually operated multi port valve 40 NB Material -PVC, Max pressure - 4kg/cm2, including hire & labour charges, fittings & accessories etc. all complete, as per direction of Engineer-in-charge | D74: =CONCATENATE(C74," (Code: ",B74,")") -> Supplying, assembling, manually operated multi port valve 40 NB Material -PVC, Max pressure - 4kg/cm2, including hire & labour charges, fittings & accessories etc. all complete, as per direction of Engineer-in-charge (Code: GWDDR071) | E74: each | F74: GWD DR | G74: WTP | H74: WTP Multi Port Valve | I74: =WTP!H114 -> 8916.8355 | J74: =WTP!I114 -> 38.16689 | K74: =J74*($L$2-1) -> 0 | L74: =SUM(I74:K74) -> 8955.0024
A75: 72 | B75: GWDDR072 | C75: =WTP!B115 -> Supplying, assembling, manually operated multi port valve flower type 50NB Material -PVC, Max pressure - 4kg/cm2, including hire & labour charges, fittings & accessories etc. all complete, as per direction of Engineer-in-charge | D75: =CONCATENATE(C75," (Code: ",B75,")") -> Supplying, assembling, manually operated multi port valve flower type 50NB Material -PVC, Max pressure - 4kg/cm2, including hire & labour charges, fittings & accessories etc. all complete, as per direction of Engineer-in-charge (Code: GWDDR072) | E75: each | F75: GWD DR | G75: WTP | H75: WTP Multi Port Valve | I75: =WTP!H127 -> 11173.63 | J75: =WTP!I127 -> 38.16689 | K75: =J75*($L$2-1) -> 0 | L75: =SUM(I75:K75) -> 11211.797
A76: 73 | B76: GWDDR073 | C76: =WTP!B128 -> Supplying, assembling, multi port valve 65 NB Manually Material -PVC, Max pressure - 4kg/cm2, including hire & labour charges, fittings & accessories etc. all complete, as per direction of Engineer-in-charge including hire & labour charges, fittings & accessories etc. all complete, as per direction of Engineer-in-charge | D76: =CONCATENATE(C76," (Code: ",B76,")") -> Supplying, assembling, multi port valve 65 NB Manually Material -PVC, Max pressure - 4kg/cm2, including hire & labour charges, fittings & accessories etc. all complete, as per direction of Engineer-in-charge including hire & labour charges, fittings & accessories etc. all complete, as per direction of Engineer-in-charge (Code: GWDDR073) | E76: each | F76: GWD DR | G76: WTP | H76: WTP Multi Port Valve | I76: =WTP!H140 -> 13342.15 | J76: =WTP!I140 -> 38.16689 | K76: =J76*($L$2-1) -> 0 | L76: =SUM(I76:K76) -> 13380.317
A77: 74 | B77: GWDDR074 | C77: =WTP!B142 -> Supplying, assembling, distributer 40 NB including hire & labour charges, fittings & accessories etc. all complete, as per direction of Engineer-in-charge | D77: =CONCATENATE(C77," (Code: ",B77,")") -> Supplying, assembling, distributer 40 NB including hire & labour charges, fittings & accessories etc. all complete, as per direction of Engineer-in-charge (Code: GWDDR074) | E77: each | F77: GWD DR | G77: WTP | H77: WTP Distributer | I77: =WTP!H154 -> 5261.595 | J77: =WTP!I154 -> 38.16689 | K77: =J77*($L$2-1) -> 0 | L77: =SUM(I77:K77) -> 5299.7619
A78: 75 | B78: GWDDR075 | C78: =WTP!B155 -> Supplying, assembling, distributer 50 NB including hire & labour charges, fittings & accessories etc. all complete, as per direction of Engineer-in-charge | D78: =CONCATENATE(C78," (Code: ",B78,")") -> Supplying, assembling, distributer 50 NB including hire & labour charges, fittings & accessories etc. all complete, as per direction of Engineer-in-charge (Code: GWDDR075) | E78: each | F78: GWD DR | G78: WTP | H78: WTP Distributer | I78: =WTP!H167 -> 7840.125 | J78: =WTP!I167 -> 38.16689 | K78: =J78*($L$2-1) -> 0 | L78: =SUM(I78:K78) -> 7878.2919
A79: 76 | B79: GWDDR076 | C79: =WTP!B168 -> Supplying, assembling, distributer 65 NB including hire & labour charges, fittings & accessories etc. all complete, as per direction of Engineer-in-charge | D79: =CONCATENATE(C79," (Code: ",B79,")") -> Supplying, assembling, distributer 65 NB including hire & labour charges, fittings & accessories etc. all complete, as per direction of Engineer-in-charge (Code: GWDDR076) | E79: each | F79: GWD DR | G79: WTP | H79: WTP Distributer | I79: =WTP!H180 -> 11923.959 | J79: =WTP!I180 -> 38.16689 | K79: =J79*($L$2-1) -> 0 | L79: =SUM(I79:K79) -> 11962.126
A80: 77 | B80: GWDDR077 | C80: =WTP!B182 -> Supplying, assembling, and fixing Electrically operated Diaphragm type dosing pump 10 lph including hire & labour charges, fittings & accessories etc. all complete, as per direction of Engineer-in-charge | D80: =CONCATENATE(C80," (Code: ",B80,")") -> Supplying, assembling, and fixing Electrically operated Diaphragm type dosing pump 10 lph including hire & labour charges, fittings & accessories etc. all complete, as per direction of Engineer-in-charge (Code: GWDDR077) | E80: each | F80: GWD DR | G80: WTP | H80: WTP Dosing Pump | I80: =WTP!H195 -> 18191.413 | J80: =WTP!I195 -> 331.9567 | K80: =J80*($L$2-1) -> 0 | L80: =SUM(I80:K80) -> 18523.37
A81: 78 | B81: GWDDR078 | C81: =WTP!B196 -> Supplying, assembling, and fixing Electrically operated Diaphragm type dosing pump 40 lph including hire & labour charges, fittings & accessories etc. all complete, as per direction of Engineer-in-charge | D81: =CONCATENATE(C81," (Code: ",B81,")") -> Supplying, assembling, and fixing Electrically operated Diaphragm type dosing pump 40 lph including hire & labour charges, fittings & accessories etc. all complete, as per direction of Engineer-in-charge (Code: GWDDR078) | E81: each | F81: GWD DR | G81: WTP | H81: WTP Dosing Pump | I81: =WTP!H209 -> 49363.75 | J81: =WTP!I209 -> 331.9567 | K81: =J81*($L$2-1) -> 0 | L81: =SUM(I81:K81) -> 49695.707
A82: 79 | B82: GWDDR079 | C82: =WTP!B211 -> Supplying, assembling, and fixing single Phase Pure Copper , Self priming monoblock feed pump 1Hp including hire & labour charges, fittings & accessories etc. all complete, as per direction of Engineer-in-charge | D82: =CONCATENATE(C82," (Code: ",B82,")") -> Supplying, assembling, and fixing single Phase Pure Copper , Self priming monoblock feed pump 1Hp including hire & labour charges, fittings & accessories etc. all complete, as per direction of Engineer-in-charge (Code: GWDDR079) | E82: each | F82: GWD DR | G82: WTP | H82: WTP Feed Pump | I82: =WTP!H224 -> 14749.888 | J82: =WTP!I224 -> 331.9567 | K82: =J82*($L$2-1) -> 0 | L82: =SUM(I82:K82) -> 15081.845
A83: 80 | B83: GWDDR080 | C83: =WTP!B225 -> Supplying, assembling, and fixing single Phase Pure Copper , Self priming monoblock feed pump 1.5Hp including hire & labour charges, fittings & accessories etc. all complete, as per direction of Engineer-in-charge | D83: =CONCATENATE(C83," (Code: ",B83,")") -> Supplying, assembling, and fixing single Phase Pure Copper , Self priming monoblock feed pump 1.5Hp including hire & labour charges, fittings & accessories etc. all complete, as per direction of Engineer-in-charge (Code: GWDDR080) | E83: each | F83: GWD DR | G83: WTP | H83: WTP Feed Pump | I83: =WTP!H238 -> 17631.57 | J83: =WTP!I238 -> 331.9567 | K83: =J83*($L$2-1) -> 0 | L83: =SUM(I83:K83) -> 17963.527
A84: 81 | B84: GWDDR081 | C84: =WTP!B239 -> Supplying, assembling, and fixing single Phase Pure Copper , Self priming monoblock feed pump 2Hp including hire & labour charges, fittings & accessories etc. all complete, as per direction of Engineer-in-charge | D84: =CONCATENATE(C84," (Code: ",B84,")") -> Supplying, assembling, and fixing single Phase Pure Copper , Self priming monoblock feed pump 2Hp including hire & labour charges, fittings & accessories etc. all complete, as per direction of Engineer-in-charge (Code: GWDDR081) | E84: each | F84: GWD DR | G84: WTP | H84: WTP Feed Pump | I84: =WTP!H252 -> 25866.605 | J84: =WTP!I252 -> 331.9567 | K84: =J84*($L$2-1) -> 0 | L84: =SUM(I84:K84) -> 26198.562
A85: 82 | B85: GWDDR082 | C85: =WTP!B254 -> Supplying, assembling, and fixing sludge pump 1Hp, 220v, Max head 20m , 750W, Max flw 15000 lph including hire & labour charges, fittings & accessories etc. all complete, as per direction of Engineer-in-charge | D85: =CONCATENATE(C85," (Code: ",B85,")") -> Supplying, assembling, and fixing sludge pump 1Hp, 220v, Max head 20m , 750W, Max flw 15000 lph including hire & labour charges, fittings & accessories etc. all complete, as per direction of Engineer-in-charge (Code: GWDDR082) | E85: each | F85: GWD DR | G85: WTP | H85: WTP Sludge Pump | I85: =WTP!H267 -> 18911.543 | J85: =WTP!I267 -> 331.9567 | K85: =J85*($L$2-1) -> 0 | L85: =SUM(I85:K85) -> 19243.5
A86: 83 | B86: GWDDR083 | C86: =WTP!B269 -> Supplying, assembling, and fixing 5000 lph Stainless Steel UV Plant including hire & labour charges, fittings & accessories etc. all complete, as per direction of Engineer-in-charge | D86: =CONCATENATE(C86," (Code: ",B86,")") -> Supplying, assembling, and fixing 5000 lph Stainless Steel UV Plant including hire & labour charges, fittings & accessories etc. all complete, as per direction of Engineer-in-charge (Code: GWDDR083) | E86: each | F86: GWD DR | G86: WTP | H86: WTP UV Plant | I86: =WTP!H282 -> 47066.303 | J86: =WTP!I282 -> 331.9567 | K86: =J86*($L$2-1) -> 0 | L86: =SUM(I86:K86) -> 47398.26
A87: 84 | B87: GWDDR084 | C87: =WTP!B283 -> Supplying, assembling, and fixing 10000 lph UV Plant including hire & labour charges, fittings & accessories etc. all complete, as per direction of Engineer-in-charge | D87: =CONCATENATE(C87," (Code: ",B87,")") -> Supplying, assembling, and fixing 10000 lph UV Plant including hire & labour charges, fittings & accessories etc. all complete, as per direction of Engineer-in-charge (Code: GWDDR084) | E87: each | F87: GWD DR | G87: WTP | H87: WTP UV Plant | I87: =WTP!H296 -> 72593.75 | J87: =WTP!I296 -> 331.9567 | K87: =J87*($L$2-1) -> 0 | L87: =SUM(I87:K87) -> 72925.707
A88: 85 | B88: GWDDR085 | C88: =WTP!B297 -> Supplying, assembling, and fixing 15000 lph UV Plant including hire & labour charges, fittings & accessories etc. all complete, as per direction of Engineer-in-charge | D88: =CONCATENATE(C88," (Code: ",B88,")") -> Supplying, assembling, and fixing 15000 lph UV Plant including hire & labour charges, fittings & accessories etc. all complete, as per direction of Engineer-in-charge (Code: GWDDR085) | E88: each | F88: GWD DR | G88: WTP | H88: WTP UV Plant | I88: =WTP!H310 -> 82775.459 | J88: =WTP!I310 -> 331.9567 | K88: =J88*($L$2-1) -> 0 | L88: =SUM(I88:K88) -> 83107.416
A89: 86 | B89: GWDDR086 | C89: =WTP!B312 -> Supplying, assembling, and fixing automatic treatment plant controller including automation of plant, hire & labour charges, fittings & accessories etc. all complete, as per direction of Engineer-in-charge | D89: =CONCATENATE(C89," (Code: ",B89,")") -> Supplying, assembling, and fixing automatic treatment plant controller including automation of plant, hire & labour charges, fittings & accessories etc. all complete, as per direction of Engineer-in-charge (Code: GWDDR086) | E89: each | F89: GWD DR | G89: WTP | H89: WTP Plant Controller | I89: =WTP!H325 -> 37748.75 | J89: =WTP!I325 -> 331.9567 | K89: =J89*($L$2-1) -> 0 | L89: =SUM(I89:K89) -> 38080.707
A90: 87 | B90: GWDDR087 | C90: =WTP!B327 -> Supplying, assembling, and fixing 63mm pressure gauge including hire & labour charges, fittings & accessories etc. all complete, as per direction of Engineer-in-charge | D90: =CONCATENATE(C90," (Code: ",B90,")") -> Supplying, assembling, and fixing 63mm pressure gauge including hire & labour charges, fittings & accessories etc. all complete, as per direction of Engineer-in-charge (Code: GWDDR087) | E90: each | F90: GWD DR | G90: WTP | H90: WTP Pressure Gauge | I90: =WTP!H339 -> 3252.2 | J90: =WTP!I339 -> 38.16689 | K90: =J90*($L$2-1) -> 0 | L90: =SUM(I90:K90) -> 3290.3669
A91: 88 | B91: GWDDR088 | C91: =WTP!B341 -> Supplying and filling, Silex, Fine sand and Pressure sand including hire & labour charges, carriage etc complete, as per direction of Engineer-in-charge | D91: =CONCATENATE(C91," (Code: ",B91,")") -> Supplying and filling, Silex, Fine sand and Pressure sand including hire & labour charges, carriage etc complete, as per direction of Engineer-in-charge (Code: GWDDR088) | E91: 100 kg | F91: GWD DR | G91: WTP | H91: WTP Filter Media | I91: =WTP!H353 -> 2323 | J91: =WTP!I353 -> 449.5005 | K91: =J91*($L$2-1) -> 0 | L91: =SUM(I91:K91) -> 2772.5005
A92: 89 | B92: GWDDR089 | C92: =WTP!B354 -> Supplying and filling, Katalox iron remover including hire & labour charges, carriage etc. all complete, as per direction of Engineer-in-charge | D92: =CONCATENATE(C92," (Code: ",B92,")") -> Supplying and filling, Katalox iron remover including hire & labour charges, carriage etc. all complete, as per direction of Engineer-in-charge (Code: GWDDR089) | E92: 100 kg | F92: GWD DR | G92: WTP | H92: WTP Filter Media | I92: =WTP!H366 -> 40652.5 | J92: =WTP!I366 -> 449.5005 | K92: =J92*($L$2-1) -> 0 | L92: =SUM(I92:K92) -> 41102.001
A93: 90 | B93: GWDDR090 | C93: =WTP!B367 -> Supplying and filling, Activated carbon IV 1050 including hire & labour charges, carriage etc. all complete, as per direction of Engineer-in-charge | D93: =CONCATENATE(C93," (Code: ",B93,")") -> Supplying and filling, Activated carbon IV 1050 including hire & labour charges, carriage etc. all complete, as per direction of Engineer-in-charge (Code: GWDDR090) | E93: 100 kg | F93: GWD DR | G93: WTP | H93: WTP Filter Media | I93: =WTP!H379 -> 36006.5 | J93: =WTP!I379 -> 449.5005 | K93: =J93*($L$2-1) -> 0 | L93: =SUM(I93:K93) -> 36456.001
A94: 91 | B94: GWDDR091 | C94: =WTP!B381 -> Supplying and filling, liquid chlorine including hire & labour charges, carriage etc. all complete, as per direction of Engineer-in-charge | D94: =CONCATENATE(C94," (Code: ",B94,")") -> Supplying and filling, liquid chlorine including hire & labour charges, carriage etc. all complete, as per direction of Engineer-in-charge (Code: GWDDR091) | E94: 25 kg | F94: GWD DR | G94: WTP | H94: WTP Dosing Chemicals | I94: =WTP!H393 -> 1236.4168 | J94: =WTP!I393 -> 74.91675 | K94: =J94*($L$2-1) -> 0 | L94: =SUM(I94:K94) -> 1311.3335
A95: 92 | B95: GWDDR092 | C95: =WTP!B394 -> Supplying and filling, liquid alum including hire & labour charges, fittings & accessories etc. all complete, as per direction of Engineer-in-charge | D95: =CONCATENATE(C95," (Code: ",B95,")") -> Supplying and filling, liquid alum including hire & labour charges, fittings & accessories etc. all complete, as per direction of Engineer-in-charge (Code: GWDDR092) | E95: 25 kg | F95: GWD DR | G95: WTP | H95: WTP Dosing Chemicals | I95: =WTP!H406 -> 968.40062 | J95: =WTP!I406 -> 74.91675 | K95: =J95*($L$2-1) -> 0 | L95: =SUM(I95:K95) -> 1043.3174
A96: 93 | B96: GWDDR093 | C96: =WTP!B408 -> Plant installation charges including labour and materials for supports, stand, PVC connection pipes, PVC valves, air valves etc complete. all complete | D96: =CONCATENATE(C96," (Code: ",B96,")") -> Plant installation charges including labour and materials for supports, stand, PVC connection pipes, PVC valves, air valves etc complete. all complete (Code: GWDDR093) | E96: each | F96: GWD DR | G96: WTP | H96: WTP Plant Installation | I96: =WTP!H452 -> 18989.76 | J96: =WTP!I452 -> 7033.08 | K96: =J96*($L$2-1) -> 0 | L96: =SUM(I96:K96) -> 26022.84
A97: 94 | B97: GWDDR094 | C97: =WTP!B454 -> Plant inspection, maintenance, cleaning, back wash, sludge removal, sample collection and correction of Dosing etc complete, and water quality checking (except filling chemicals) | D97: =CONCATENATE(C97," (Code: ",B97,")") -> Plant inspection, maintenance, cleaning, back wash, sludge removal, sample collection and correction of Dosing etc complete, and water quality checking (except filling chemicals) (Code: GWDDR094) | E97: each visit | F97: GWD DR | G97: WTP | H97: WTP Plant Visit | I97: =WTP!H465 -> 5500 | J97: =WTP!I465 -> 869.9635 | K97: =J97*($L$2-1) -> 0 | L97: =SUM(I97:K97) -> 6369.9635
A98: 95 | B98: GWDDR095 | C98: ='GI Works'!A3 -> GI work in single section, fixed with or without connecting plate, including cutting, hoisting, fixing in position and applying a priming coat of approved steel primer all complete. | D98: =CONCATENATE(C98," (Code: ",B98,")") -> GI work in single section, fixed with or without connecting plate, including cutting, hoisting, fixing in position and applying a priming coat of approved steel primer all complete. (Code: GWDDR095) | E98: kg | F98: GWD DR | G98: MWSS | H98: GI Works | I98: 0 | J98: ='GI Works'!F29 -> 151.03996 | K98: =J98*($L$2-1) -> 0 | L98: =SUM(I98:K98) -> 151.03996
A99: 96 | B99: GWDDR096 | C99: =Services!B2 -> Hydrogeological Investigation (Domestic) | D99: =CONCATENATE(C99," (Code: ",B99,")") -> Hydrogeological Investigation (Domestic) (Code: GWDDR096) | E99: =Services!C2 -> each visit | F99: GWD DR | G99: Investigation & Logging | H99: Investigation & Logging | I99: =Services!D2 -> 585 | J99: 0 | K99: =J99*($L$2-1) -> 0 | L99: =SUM(I99:K99) -> 585
A100: 97 | B100: GWDDR097 | C100: =Services!B3 -> Hydrogeological Investigation (Institution) | D100: =CONCATENATE(C100," (Code: ",B100,")") -> Hydrogeological Investigation (Institution) (Code: GWDDR097) | E100: =Services!C3 -> each visit | F100: GWD DR | G100: Investigation & Logging | H100: Investigation & Logging | I100: =Services!D3 -> 1935 | J100: 0 | K100: =J100*($L$2-1) -> 0 | L100: =SUM(I100:K100) -> 1935
...

Sheet GWD MR Abstract
A1: GWD Revised Market Rates Based on DSR 21/PRICE (Gen ID 40) | J1: Select Distrct | L1: Index
J2: ADMIN | L2: {=((IFERROR(INDEX(CostIndex,MATCH(J2,District,0), ), )))} -> 1
A3: Sl No | B3: Code | C3: Item Name | D3: Item Name With Code | E3: Unit | F3: Main Category | G3: Sub Category 1 | H3: Sub Category 2 | I3: C1 | J3: C2 | K3: Indexed | L3: Total
A4: 1 | B4: GWDMR001 | C4: S&F PVC Bend 90 mm (DG) | D4: =CONCATENATE(C4," (Code: ",B4,")") -> S&F PVC Bend 90 mm (DG) (Code: GWDMR001) | E4: each | F4: GWD MR | G4: PVC Fittings | H4: PVC Bend | I4: 80 | J4: 31 | K4: =J4*($L$2-1) -> 0 | L4: =SUM(I4:K4) -> 111
A5: 2 | B5: GWDMR002 | C5: S&F PVC Bend 140 mm (DG) | D5: =CONCATENATE(C5," (Code: ",B5,")") -> S&F PVC Bend 140 mm (DG) (Code: GWDMR002) | E5: each | F5: GWD MR | G5: PVC Fittings | H5: PVC Bend | I5: 150 | J5: 35 | K5: =J5*($L$2-1) -> 0 | L5: =SUM(I5:K5) -> 185
A6: 3 | B6: GWDMR003 | C6: PVC End cap 140 mm (DG) | D6: =CONCATENATE(C6," (Code: ",B6,")") -> PVC End cap 140 mm (DG) (Code: GWDMR003) | E6: each | F6: GWD MR | G6: PVC Fittings | H6: PVC End Cap | I6: 38.5 | J6: 37 | K6: =J6*($L$2-1) -> 0 | L6: =SUM(I6:K6) -> 75.5
A7: 4 | B7: GWDMR004 | C7: PVC End cap 150 mm (DG) | D7: =CONCATENATE(C7," (Code: ",B7,")") -> PVC End cap 150 mm (DG) (Code: GWDMR004) | E7: each | F7: GWD MR | G7: PVC Fittings | H7: PVC End Cap | I7: 41.2 | J7: 39.5 | K7: =J7*($L$2-1) -> 0 | L7: =SUM(I7:K7) -> 80.7
A8: 5 | B8: GWDMR005 | C8: PVC End Cap 180 mm (DG) | D8: =CONCATENATE(C8," (Code: ",B8,")") -> PVC End Cap 180 mm (DG) (Code: GWDMR005) | E8: each | F8: GWD MR | G8: PVC Fittings | H8: PVC End Cap | I8: 47.8 | J8: 44 | K8: =J8*($L$2-1) -> 0 | L8: =SUM(I8:K8) -> 91.8
A9: 6 | B9: GWDMR006 | C9: PVC End Cap 200 mm (DG) | D9: =CONCATENATE(C9," (Code: ",B9,")") -> PVC End Cap 200 mm (DG) (Code: GWDMR006) | E9: each | F9: GWD MR | G9: PVC Fittings | H9: PVC End Cap | I9: 52.5 | J9: 48.5 | K9: =J9*($L$2-1) -> 0 | L9: =SUM(I9:K9) -> 101
A10: 7 | B10: GWDMR007 | C10: PVC Square End Cap 140 mm | D10: =CONCATENATE(C10," (Code: ",B10,")") -> PVC Square End Cap 140 mm (Code: GWDMR007) | E10: each | F10: GWD MR | G10: ARS | H10: ARS Fittings | I10: 200 | J10: 0 | K10: =J10*($L$2-1) -> 0 | L10: =SUM(I10:K10) -> 200
A11: 8 | B11: GWDMR008 | C11: PVC Square End Cap 160 mm | D11: =CONCATENATE(C11," (Code: ",B11,")") -> PVC Square End Cap 160 mm (Code: GWDMR008) | E11: each | F11: GWD MR | G11: ARS | H11: ARS Fittings | I11: 250 | J11: 0 | K11: =J11*($L$2-1) -> 0 | L11: =SUM(I11:K11) -> 250
A12: 9 | B12: GWDMR009 | C12: PVC Half End Cap 140 mm | D12: =CONCATENATE(C12," (Code: ",B12,")") -> PVC Half End Cap 140 mm (Code: GWDMR009) | E12: each | F12: GWD MR | G12: ARS | H12: ARS Fittings | I12: 150 | J12: 0 | K12: =J12*($L$2-1) -> 0 | L12: =SUM(I12:K12) -> 150
A13: 10 | B13: GWDMR010 | C13: PVC Half End Cap 160 mm | D13: =CONCATENATE(C13," (Code: ",B13,")") -> PVC Half End Cap 160 mm (Code: GWDMR010) | E13: each | F13: GWD MR | G13: ARS | H13: ARS Fittings | I13: 160 | J13: 0 | K13: =J13*($L$2-1) -> 0 | L13: =SUM(I13:K13) -> 160
A14: 11 | B14: GWDMR011 | C14: PVC Half Square End Cap 140 mm | D14: =CONCATENATE(C14," (Code: ",B14,")") -> PVC Half Square End Cap 140 mm (Code: GWDMR011) | E14: each | F14: GWD MR | G14: ARS | H14: ARS Fittings | I14: 150 | J14: 0 | K14: =J14*($L$2-1) -> 0 | L14: =SUM(I14:K14) -> 150
A15: 12 | B15: GWDMR012 | C15: PVC Half Square End Cap 160 mm | D15: =CONCATENATE(C15," (Code: ",B15,")") -> PVC Half Square End Cap 160 mm (Code: GWDMR012) | E15: each | F15: GWD MR | G15: ARS | H15: ARS Fittings | I15: 175 | J15: 0 | K15: =J15*($L$2-1) -> 0 | L15: =SUM(I15:K15) -> 175
... A23: 20 | B23: GWDMR020 | C23: PVC Reducer 160X110 mm | D23: =CONCATENATE(C23," (Code: ",B23,")") -> PVC Reducer 160X110 mm (Code: GWDMR020) | E23: each | F23: GWD MR | G23: PVC Fittings | H23: PVC Reducer | I23: 290 | J23: 0 | K23: =J23*($L$2-1) -> 0 | L23: =SUM(I23:K23) -> 290
A24: 20A | B24: GWDMR020A | C24: PVC Reducer 140X110 mm | D24: =CONCATENATE(C24," (Code: ",B24,")") -> PVC Reducer 140X110 mm (Code: GWDMR020A) | E24: each | F24: GWD MR | G24: PVC Fittings | H24: PVC Reducer | I24: 196 | J24: 0 | K24: =J24*($L$2-1) -> 0 | L24: =SUM(I24:K24) -> 196
A25: 21 | B25: GWDMR021 | C25: PVC Runner Drop 140 mm | D25: =CONCATENATE(C25," (Code: ",B25,")") -> PVC Runner Drop 140 mm (Code: GWDMR021) | E25: each | F25: GWD MR | G25: ARS | H25: ARS Fittings | I25: 210 | J25: 0 | K25: =J25*($L$2-1) -> 0 | L25: =SUM(I25:K25) -> 210
A26: 22 | B26: GWDMR022 | C26: PVC Runner Drop 160 mm | D26: =CONCATENATE(C26," (Code: ",B26,")") -> PVC Runner Drop 160 mm (Code: GWDMR022) | E26: each | F26: GWD MR | G26: ARS | H26: ARS Fittings | I26: 240 | J26: 0 | K26: =J26*($L$2-1) -> 0 | L26: =SUM(I26:K26) -> 240
A27: 23 | B27: GWDMR023 | C27: PVC End Drop 140 mm | D27: =CONCATENATE(C27," (Code: ",B27,")") -> PVC End Drop 140 mm (Code: GWDMR023) | E27: each | F27: GWD MR | G27: ARS | H27: ARS Fittings | I27: 192 | J27: 0 | K27: =J27*($L$2-1) -> 0 | L27: =SUM(I27:K27) -> 192
A28: 24 | B28: GWDMR024 | C28: PVC End Drop 160 mm | D28: =CONCATENATE(C28," (Code: ",B28,")") -> PVC End Drop 160 mm (Code: GWDMR024) | E28: each | F28: GWD MR | G28: ARS | H28: ARS Fittings | I28: 216 | J28: 0 | K28: =J28*($L$2-1) -> 0 | L28: =SUM(I28:K28) -> 216
A29: 25 | B29: GWDMR025 | C29: PVC Half End Drop 140 mm | D29: =CONCATENATE(C29," (Code: ",B29,")") -> PVC Half End Drop 140 mm (Code: GWDMR025) | E29: each | F29: GWD MR | G29: ARS | H29: ARS Fittings | I29: 174 | J29: 0 | K29: =J29*($L$2-1) -> 0 | L29: =SUM(I29:K29) -> 174
A30: 26 | B30: GWDMR026 | C30: PVC Half End Drop 160 mm | D30: =CONCATENATE(C30," (Code: ",B30,")") -> PVC Half End Drop 160 mm (Code: GWDMR026) | E30: each | F30: GWD MR | G30: ARS | H30: ARS Fittings | I30: 192 | J30: 0 | K30: =J30*($L$2-1) -> 0 | L30: =SUM(I30:K30) -> 192
A31: 27 | B31: GWDMR027 | C31: PVC Square End Drop 140 mm | D31: =CONCATENATE(C31," (Code: ",B31,")") -> PVC Square End Drop 140 mm (Code: GWDMR027) | E31: each | F31: GWD MR | G31: ARS | H31: ARS Fittings | I31: 198 | J31: 0 | K31: =J31*($L$2-1) -> 0 | L31: =SUM(I31:K31) -> 198
A32: 28 | B32: GWDMR028 | C32: PVC Square End Drop 160 mm | D32: =CONCATENATE(C32," (Code: ",B32,")") -> PVC Square End Drop 160 mm (Code: GWDMR028) | E32: each | F32: GWD MR | G32: ARS | H32: ARS Fittings | I32: 222 | J32: 0 | K32: =J32*($L$2-1) -> 0 | L32: =SUM(I32:K32) -> 222
A33: 29 | B33: GWDMR029 | C33: PVC Square Half End Drop 140 mm | D33: =CONCATENATE(C33," (Code: ",B33,")") -> PVC Square Half End Drop 140 mm (Code: GWDMR029) | E33: each | F33: GWD MR | G33: ARS | H33: ARS Fittings | I33: 180 | J33: 0 | K33: =J33*($L$2-1) -> 0 | L33: =SUM(I33:K33) -> 180
A34: 30 | B34: GWDMR030 | C34: PVC Square Half End Drop 160 mm | D34: =CONCATENATE(C34," (Code: ",B34,")") -> PVC Square Half End Drop 160 mm (Code: GWDMR030) | E34: each | F34: GWD MR | G34: ARS | H34: ARS Fittings | I34: 204 | J34: 0 | K34: =J34*($L$2-1) -> 0 | L34: =SUM(I34:K34) -> 204
A35: 31 | B35: GWDMR031 | C35: S&F PVC 45o Elbow 90 mm (DG) | D35: =CONCATENATE(C35," (Code: ",B35,")") -> S&F PVC 45o Elbow 90 mm (DG) (Code: GWDMR031) | E35: each | F35: GWD MR | G35: PVC Fittings | H35: PVC Elbow | I35: 45 | J35: 31.5 | K35: =J35*($L$2-1) -> 0 | L35: =SUM(I35:K35) -> 76.5
A36: 32 | B36: GWDMR032 | C36: S&F PVC 45o Elbow 140 mm (DG) | D36: =CONCATENATE(C36," (Code: ",B36,")") -> S&F PVC 45o Elbow 140 mm (DG) (Code: GWDMR032) | E36: each | F36: GWD MR | G36: PVC Fittings | H36: PVC Elbow | I36: 80 | J36: 38 | K36: =J36*($L$2-1) -> 0 | L36: =SUM(I36:K36) -> 118
... A78: 74 | B78: GWDMR075 | C78: 63 mm dia UPVC pipe | D78: =CONCATENATE(C78," (Code: ",B78,")") -> 63 mm dia UPVC pipe (Code: GWDMR075) | E78: metre | F78: GWD MR | G78: MWSS | H78: Pump Accessories | I78: 552 | J78: 0 | K78: =J78*($L$2-1) -> 0 | L78: =SUM(I78:K78) -> 552
A79: 75 | B79: GWDMR076 | C79: 20 mm dia HDPE pipe (DG) (8kg) | D79: =CONCATENATE(C79," (Code: ",B79,")") -> 20 mm dia HDPE pipe (DG) (8kg) (Code: GWDMR076) | E79: metre | F79: GWD MR | G79: MWSS | H79: Pump Accessories | I79: {=IFERROR(INDEX(DerivedRates,MATCH(B79,DerivedCodes,0), ), )} -> 20 | J79: 0 | K79: =J79*($L$2-1) -> 0 | L79: =SUM(I79:K79) -> 20
A80: 76 | B80: GWDMR077 | C80: 32 mm dia HDPE pipe (DG) (8kg) | D80: =CONCATENATE(C80," (Code: ",B80,")") -> 32 mm dia HDPE pipe (DG) (8kg) (Code: GWDMR077) | E80: metre | F80: GWD MR | G80: MWSS | H80: Pump Accessories | I80: {=IFERROR(INDEX(DerivedRates,MATCH(B80,DerivedCodes,0), ), )} -> 20 | J80: 0 | K80: =J80*($L$2-1) -> 0 | L80: =SUM(I80:K80) -> 20
A81: 77 | B81: GWDMR078 | C81: 40 mm dia HDPE pipe (DG) (8kg) | D81: =CONCATENATE(C81," (Code: ",B81,")") -> 40 mm dia HDPE pipe (DG) (8kg) (Code: GWDMR078) | E81: metre | F81: GWD MR | G81: MWSS | H81: Pump Accessories | I81: {=IFERROR(INDEX(DerivedRates,MATCH(B81,DerivedCodes,0), ), )} -> 29 | J81: 0 | K81: =J81*($L$2-1) -> 0 | L81: =SUM(I81:K81) -> 29
A82: 78 | B82: GWDMR079 | C82: 32 mm SS Adapter | D82: =CONCATENATE(C82," (Code: ",B82,")") -> 32 mm SS Adapter (Code: GWDMR079) | E82: each | F82: GWD MR | G82: MWSS | H82: Pump Accessories | I82: 804 | J82: 0 | K82: =J82*($L$2-1) -> 0 | L82: =SUM(I82:K82) -> 804
A83: 79 | B83: GWDMR080 | C83: 40 mm SS Adapter | D83: =CONCATENATE(C83," (Code: ",B83,")") -> 40 mm SS Adapter (Code: GWDMR080) | E83: each | F83: GWD MR | G83: MWSS | H83: Pump Accessories | I83: 960 | J83: 0 | K83: =J83*($L$2-1) -> 0 | L83: =SUM(I83:K83) -> 960
A84: 80 | B84: GWDMR081 | C84: 50 mm SS Adapter | D84: =CONCATENATE(C84," (Code: ",B84,")") -> 50 mm SS Adapter (Code: GWDMR081) | E84: each | F84: GWD MR | G84: MWSS | H84: Pump Accessories | I84: 1200 | J84: 0 | K84: =J84*($L$2-1) -> 0 | L84: =SUM(I84:K84) -> 1200
A85: 81 | B85: GWDMR082 | C85: 50 mm UPVC Union | D85: =CONCATENATE(C85," (Code: ",B85,")") -> 50 mm UPVC Union (Code: GWDMR082) | E85: each | F85: GWD MR | G85: MWSS | H85: Pump Accessories | I85: 360 | J85: 0 | K85: =J85*($L$2-1) -> 0 | L85: =SUM(I85:K85) -> 360
A86: 82 | B86: GWDMR083 | C86: 63 mm UPVC Union | D86: =CONCATENATE(C86," (Code: ",B86,")") -> 63 mm UPVC Union (Code: GWDMR083) | E86: each | F86: GWD MR | G86: MWSS | H86: Pump Accessories | I86: 540 | J86: 0 | K86: =J86*($L$2-1) -> 0 | L86: =SUM(I86:K86) -> 540
A87: 83 | B87: GWDMR084 | C87: 75 mm UPVC Union | D87: =CONCATENATE(C87," (Code: ",B87,")") -> 75 mm UPVC Union (Code: GWDMR084) | E87: each | F87: GWD MR | G87: MWSS | H87: Pump Accessories | I87: 1200 | J87: 0 | K87: =J87*($L$2-1) -> 0 | L87: =SUM(I87:K87) -> 1200
A88: 84 | B88: GWDMR085 | C88: Sodium Bentonite (ordinary) | D88: =CONCATENATE(C88," (Code: ",B88,")") -> Sodium Bentonite (ordinary) (Code: GWDMR085) | E88: tonne | F88: GWD MR | G88: Tubewell | H88: Tubewell Consumables | I88: 7000 | J88: 0 | K88: =J88*($L$2-1) -> 0 | L88: =SUM(I88:K88) -> 7000
A89: 85 | B89: GWDMR086 | C89: Sodium Bentonite (Super) | D89: =CONCATENATE(C89," (Code: ",B89,")") -> Sodium Bentonite (Super) (Code: GWDMR086) | E89: tonne | F89: GWD MR | G89: Tubewell | H89: Tubewell Consumables | I89: 13500 | J89: 0 | K89: =J89*($L$2-1) -> 0 | L89: =SUM(I89:K89) -> 13500
A90: 86 | B90: GWDMR087 | C90: MS Casing pipe 450 mm dia, 6 mm thickness | D90: =CONCATENATE(C90," (Code: ",B90,")") -> MS Casing pipe 450 mm dia, 6 mm thickness (Code: GWDMR087) | E90: metre | F90: GWD MR | G90: Tubewell | H90: Tubewell Fittings | I90: 8450 | J90: 0 | K90: =J90*($L$2-1) -> 0 | L90: =SUM(I90:K90) -> 8450
A91: 87 | B91: GWDMR088 | C91: Fibre mesh for placing inside filter tank (for recharge schemes) | D91: =CONCATENATE(C91," (Code: ",B91,")") -> Fibre mesh for placing inside filter tank (for recharge schemes) (Code: GWDMR088) | E91: sqm | F91: GWD MR | G91: ARS | H91: ARS Fittings | I91: 180 | J91: 0 | K91: =J91*($L$2-1) -> 0 | L91: =SUM(I91:K91) -> 180
A92: 88 | B92: GWDMR089 | C92: Coated mesh for placing inside filter tank (for recharge schemes) | D92: =CONCATENATE(C92," (Code: ",B92,")") -> Coated mesh for placing inside filter tank (for recharge schemes) (Code: GWDMR089) | E92: sqm | F92: GWD MR | G92: ARS | H92: ARS Fittings | I92: 300 | J92: 0 | K92: =J92*($L$2-1) -> 0 | L92: =SUM(I92:K92) -> 300
A93: 89 | B93: GWDMR090 | C93: Sieve mesh 110 mm (inside inspection chamber) (for recharge schemes) | D93: =CONCATENATE(C93," (Code: ",B93,")") -> Sieve mesh 110 mm (inside inspection chamber) (for recharge schemes) (Code: GWDMR090) | E93: sqm | F93: GWD MR | G93: ARS | H93: ARS Fittings | I93: 180 | J93: 0 | K93: =J93*($L$2-1) -> 0 | L93: =SUM(I93:K93) -> 180
... A96: 92 | B96: GWDMR093 | C96: PVC Wiring Pipe | D96: =CONCATENATE(C96," (Code: ",B96,")") -> PVC Wiring Pipe (Code: GWDMR093) | E96: metre | F96: GWD MR | G96: MWSS | H96: PVC Fittings | I96: 30 | J96: 0 | K96: =J96*($L$2-1) -> 0 | L96: =SUM(I96:K96) -> 30
A97: 93 | B97: GWDMR094 | C97: ='HP Repair Spares'!E1 -> Head Assembly complete (with Head, Handle, Ball Bearings and Chain Assembly) | D97: =CONCATENATE(C97," (Code: ",B97,")") -> Head Assembly complete (with Head, Handle, Ball Bearings and Chain Assembly) (Code: GWDMR094) | E97: each | F97: GWD MR | G97: Hand Pump | H97: Spares | I97: ='HP Repair Spares'!F1 -> 4800 | J97: ='HP Repair Spares'!G1 -> 0 | K97: =J97*($L$2-1) -> 0 | L97: =SUM(I97:K97) -> 4800
A98: 94 | B98: GWDMR095 | C98: ='HP Repair Spares'!E2 -> Head with welded components only without cover | D98: =CONCATENATE(C98," (Code: ",B98,")") -> Head with welded components only without cover (Code: GWDMR095) | E98: each | F98: GWD MR | G98: Hand Pump | H98: Spares | I98: ='HP Repair Spares'!F2 -> 2280 | J98: ='HP Repair Spares'!G2 -> 0 | K98: =J98*($L$2-1) -> 0 | L98: =SUM(I98:K98) -> 2280
A99: 95 | B99: GWDMR096 | C99: ='HP Repair Spares'!E3 -> Handle (welded components only) | D99: =CONCATENATE(C99," (Code: ",B99,")") -> Handle (welded components only) (Code: GWDMR096) | E99: each | F99: GWD MR | G99: Hand Pump | H99: Spares | I99: ='HP Repair Spares'!F3 -> 1800 | J99: ='HP Repair Spares'!G3 -> 0 | K99: =J99*($L$2-1) -> 0 | L99: =SUM(I99:K99) -> 1800
A100: 96 | B100: GWDMR097 | C100: ='HP Repair Spares'!E4 -> Additional Plate | D100: =CONCATENATE(C100," (Code: ",B100,")") -> Additional Plate (Code: GWDMR097) | E100: each | F100: GWD MR | G100: Hand Pump | H100: Spares | I100: ='HP Repair Spares'!F4 -> 450 | J100: ='HP Repair Spares'!G4 -> 0 | K100: =J100*($L$2-1) -> 0 | L100: =SUM(I100:K100) -> 450
A101: 97 | B101: GWDMR098 | C101: ='HP Repair Spares'!E5 -> Ball Bearing 6204 Z | D101: =CONCATENATE(C101," (Code: ",B101,")") -> Ball Bearing 6204 Z (Code: GWDMR098) | E101: each | F101: GWD MR | G101: Hand Pump | H101: Spares | I101: ='HP Repair Spares'!F5 -> 216 | J101: ='HP Repair Spares'!G5 -> 0 | K101: =J101*($L$2-1) -> 0 | L101: =SUM(I101:K101) -> 216
A102: 98 | B102: GWDMR099 | C102: ='HP Repair Spares'!E6 -> Chain with coupling | D102: =CONCATENATE(C102," (Code: ",B102,")") -> Chain with coupling (Code: GWDMR099) | E102: each | F102: GWD MR | G102: Hand Pump | H102: Spares | I102: ='HP Repair Spares'!F6 -> 240 | J102: ='HP Repair Spares'!G6 -> 0 | K102: =J102*($L$2-1) -> 0 | L102: =SUM(I102:K102) -> 240
A103: 99 | B103: GWDMR100 | C103: ='HP Repair Spares'!E7 -> Spacer for Axle Pin | D103: =CONCATENATE(C103," (Code: ",B103,")") -> Spacer for Axle Pin (Code: GWDMR100) | E103: each | F103: GWD MR | G103: Hand Pump | H103: Spares | I103: ='HP Repair Spares'!F7 -> 24 | J103: ='HP Repair Spares'!G7 -> 0 | K103: =J103*($L$2-1) -> 0 | L103: =SUM(I103:K103) -> 24
A104: 100 | B104: GWDMR101 | C104: ='HP Repair Spares'!E8 -> M 12 x 20 Hex Bolt for Top Head Cover | D104: =CONCATENATE(C104," (Code: ",B104,")") -> M 12 x 20 Hex Bolt for Top Head Cover (Code: GWDMR101) | E104: each | F104: GWD MR | G104: Hand Pump | H104: Spares | I104: ='HP Repair Spares'!F8 -> 18 | J104: ='HP Repair Spares'!G8 -> 0 | K104: =J104*($L$2-1) -> 0 | L104: =SUM(I104:K104) -> 18
A105: 101 | B105: GWDMR102 | C105: ='HP Repair Spares'!E9 -> M 12 x 40 Hex Bolt | D105: =CONCATENATE(C105," (Code: ",B105,")") -> M 12 x 40 Hex Bolt (Code: GWDMR102) | E105: each | F105: GWD MR | G105: Hand Pump | H105: Spares | I105: ='HP Repair Spares'!F9 -> 18 | J105: ='HP Repair Spares'!G9 -> 0 | K105: =J105*($L$2-1) -> 0 | L105: =SUM(I105:K105) -> 18
A106: 102 | B106: GWDMR103 | C106: ='HP Repair Spares'!E10 -> M 12 Nut | D106: =CONCATENATE(C106," (Code: ",B106,")") -> M 12 Nut (Code: GWDMR103) | E106: each | F106: GWD MR | G106: Hand Pump | H106: Spares | I106: ='HP Repair Spares'!F10 -> 12 | J106: ='HP Repair Spares'!G10 -> 0 | K106: =J106*($L$2-1) -> 0 | L106: =SUM(I106:K106) -> 12
A107: 103 | B107: GWDMR104 | C107: ='HP Repair Spares'!E11 -> M.12 Washer | D107: =CONCATENATE(C107," (Code: ",B107,")") -> M.12 Washer (Code: GWDMR104) | E107: each | F107: GWD MR | G107: Hand Pump | H107: Spares | I107: ='HP Repair Spares'!F11 -> 12 | J107: ='HP Repair Spares'!G11 -> 0 | K107: =J107*($L$2-1) -> 0 | L107: =SUM(I107:K107) -> 12
A108: 104 | B108: GWDMR105 | C108: ='HP Repair Spares'!E12 -> M 10 x 40 H.T Bolt | D108: =CONCATENATE(C108," (Code: ",B108,")") -> M 10 x 40 H.T Bolt (Code: GWDMR105) | E108: each | F108: GWD MR | G108: Hand Pump | H108: Spares | I108: ='HP Repair Spares'!F12 -> 18 | J108: ='HP Repair Spares'!G12 -> 0 | K108: =J108*($L$2-1) -> 0 | L108: =SUM(I108:K108) -> 18
... A139: 135 | B139: GWDMR136 | C139: ='HP Repair Spares'!E43 -> ISI marked India Mark II (Standard) Extra Deep well hand pumps confirming to IS: 15500 (Part II) 2004 complete with 20 Nos. GI pipe (B class) 3m long 32mm bore both end threaded with one end socket and 20 Nos connecting rods | D139: =CONCATENATE(C139," (Code: ",B139,")") -> ISI marked India Mark II (Standard) Extra Deep well hand pumps confirming to IS: 15500 (Part II) 2004 complete with 20 Nos. GI pipe (B class) 3m long 32mm bore both end threaded with one end socket and 20 Nos connecting rods (Code: GWDMR136) | E139: each | F139: GWD MR | G139: Hand Pump | H139: Spares | I139: ='HP Repair Spares'!F43 -> 49000 | J139: ='HP Repair Spares'!G43 -> 0 | K139: =J139*($L$2-1) -> 0 | L139: =SUM(I139:K139) -> 49000
A140: 136 | B140: GWDMR137 | C140: Supply of Single Phase Submersible Pump 1 HP, Discharge 2500-6000 lph, Head 49-17m without Panel Board | D140: =CONCATENATE(C140," (Code: ",B140,")") -> Supply of Single Phase Submersible Pump 1 HP, Discharge 2500-6000 lph, Head 49-17m without Panel Board (Code: GWDMR137) | E140: each | F140: GWD MR | G140: MWSS | H140: Submersible Pump | I140: 21162.53 | J140: 0 | K140: =J140*($L$2-1) -> 0 | L140: =SUM(I140:K140) -> 21162.53
A141: 137 | B141: GWDMR138 | C141: Supply of Single Phase Submersible Pump 1 HP, Discharge 2500-6000 lph, Head 57-14m without Panel Board | D141: =CONCATENATE(C141," (Code: ",B141,")") -> Supply of Single Phase Submersible Pump 1 HP, Discharge 2500-6000 lph, Head 57-14m without Panel Board (Code: GWDMR138) | E141: each | F141: GWD MR | G141: MWSS | H141: Submersible Pump | I141: 22126.575 | J141: 0 | K141: =J141*($L$2-1) -> 0 | L141: =SUM(I141:K141) -> 22126.575
A142: 138 | B142: GWDMR139 | C142: Supply of Single Phase Submersible Pump 1 HP, Discharge 1800-4320 lph, Head 65-39m without Panel Board | D142: =CONCATENATE(C142," (Code: ",B142,")") -> Supply of Single Phase Submersible Pump 1 HP, Discharge 1800-4320 lph, Head 65-39m without Panel Board (Code: GWDMR139) | E142: each | F142: GWD MR | G142: MWSS | H142: Submersible Pump | I142: 21047.772 | J142: 0 | K142: =J142*($L$2-1) -> 0 | L142: =SUM(I142:K142) -> 21047.772
A143: 139 | B143: GWDMR140 | C143: Supply of Single Phase Submersible Pump 1 HP, Discharge 2500-6000 lph, Head 69-17m without Panel Board | D143: =CONCATENATE(C143," (Code: ",B143,")") -> Supply of Single Phase Submersible Pump 1 HP, Discharge 2500-6000 lph, Head 69-17m without Panel Board (Code: GWDMR140) | E143: each | F143: GWD MR | G143: MWSS | H143: Submersible Pump | I143: 24391.5 | J143: 0 | K143: =J143*($L$2-1) -> 0 | L143: =SUM(I143:K143) -> 24391.5
A144: 140 | B144: GWDMR141 | C144: Supply of Single Phase Submersible Pump 1 HP, Discharge 1080-2880 lph, Head 91-50m without Panel Board | D144: =CONCATENATE(C144," (Code: ",B144,")") -> Supply of Single Phase Submersible Pump 1 HP, Discharge 1080-2880 lph, Head 91-50m without Panel Board (Code: GWDMR141) | E144: each | F144: GWD MR | G144: MWSS | H144: Submersible Pump | I144: 22498.716 | J144: 0 | K144: =J144*($L$2-1) -> 0 | L144: =SUM(I144:K144) -> 22498.716
A145: 141 | B145: GWDMR142 | C145: Supply of Single Phase Submersible Pump 1.5 HP, Discharge 3000-7500 lph, Head 65-32m without Panel Board | D145: =CONCATENATE(C145," (Code: ",B145,")") -> Supply of Single Phase Submersible Pump 1.5 HP, Discharge 3000-7500 lph, Head 65-32m without Panel Board (Code: GWDMR142) | E145: each | F145: GWD MR | G145: MWSS | H145: Submersible Pump | I145: 24937.405 | J145: 0 | K145: =J145*($L$2-1) -> 0 | L145: =SUM(I145:K145) -> 24937.405
A146: 142 | B146: GWDMR143 | C146: Supply of Single Phase Submersible Pump 1.5 HP, Discharge 1800-4320 lph, Head 83-52m without Panel Board | D146: =CONCATENATE(C146," (Code: ",B146,")") -> Supply of Single Phase Submersible Pump 1.5 HP, Discharge 1800-4320 lph, Head 83-52m without Panel Board (Code: GWDMR143) | E146: each | F146: GWD MR | G146: MWSS | H146: Submersible Pump | I146: 23219.316 | J146: 0 | K146: =J146*($L$2-1) -> 0 | L146: =SUM(I146:K146) -> 23219.316
A147: 143 | B147: GWDMR144 | C147: Supply of Single Phase Submersible Pump 1.5 HP, Discharge 1800-4320 lph, Head 105-57m without Panel Board | D147: =CONCATENATE(C147," (Code: ",B147,")") -> Supply of Single Phase Submersible Pump 1.5 HP, Discharge 1800-4320 lph, Head 105-57m without Panel Board (Code: GWDMR144) | E147: each | F147: GWD MR | G147: MWSS | H147: Submersible Pump | I147: 24493.248 | J147: 0 | K147: =J147*($L$2-1) -> 0 | L147: =SUM(I147:K147) -> 24493.248
A148: 144 | B148: GWDMR145 | C148: Supply of Single Phase Submersible Pump 1.5 HP, Discharge 500-3000 lph, Head 126-43m without Panel Board | D148: =CONCATENATE(C148," (Code: ",B148,")") -> Supply of Single Phase Submersible Pump 1.5 HP, Discharge 500-3000 lph, Head 126-43m without Panel Board (Code: GWDMR145) | E148: each | F148: GWD MR | G148: MWSS | H148: Submersible Pump | I148: 24159.2 | J148: 0 | K148: =J148*($L$2-1) -> 0 | L148: =SUM(I148:K148) -> 24159.2
A149: 145 | B149: GWDMR146 | C149: Supply of Single Phase Submersible Pump 1.5 HP, Discharge 1080-2880 lph, Head 137-75m without Panel Board | D149: =CONCATENATE(C149," (Code: ",B149,")") -> Supply of Single Phase Submersible Pump 1.5 HP, Discharge 1080-2880 lph, Head 137-75m without Panel Board (Code: GWDMR146) | E149: each | F149: GWD MR | G149: MWSS | H149: Submersible Pump | I149: 26133.75 | J149: 0 | K149: =J149*($L$2-1) -> 0 | L149: =SUM(I149:K149) -> 26133.75
A150: 146 | B150: GWDMR147 | C150: Supply of Single Phase Submersible Pump 1.5 HP, Discharge 500-3000 lph, Head 148-50m without Panel Board | D150: =CONCATENATE(C150," (Code: ",B150,")") -> Supply of Single Phase Submersible Pump 1.5 HP, Discharge 500-3000 lph, Head 148-50m without Panel Board (Code: GWDMR147) | E150: each | F150: GWD MR | G150: MWSS | H150: Submersible Pump | I150: 27980.535 | J150: 0 | K150: =J150*($L$2-1) -> 0 | L150: =SUM(I150:K150) -> 27980.535
A151: 147 | B151: GWDMR148 | C151: Supply of Single Phase Submersible Pump 1.5 HP, Discharge 300-2100 lph, Head 180-51m without Panel Board | D151: =CONCATENATE(C151," (Code: ",B151,")") -> Supply of Single Phase Submersible Pump 1.5 HP, Discharge 300-2100 lph, Head 180-51m without Panel Board (Code: GWDMR148) | E151: each | F151: GWD MR | G151: MWSS | H151: Submersible Pump | I151: 30082.85 | J151: 0 | K151: =J151*($L$2-1) -> 0 | L151: =SUM(I151:K151) -> 30082.85
... A197: 193 | B197: GWDMR194 | C197: S&F Digital Timer Switch | D197: =CONCATENATE(C197," (Code: ",B197,")") -> S&F Digital Timer Switch (Code: GWDMR194) | E197: each | F197: GWD MR | G197: MWSS | H197: Motor Starter | I197: 6500 | J197: 0 | K197: =J197*($L$2-1) -> 0 | L197: =SUM(I197:K197) -> 6500

Sheet ARS Filter Media
A1: Filter Media for ARS
A2: 0 | B2: Supply and filling of 40mm metal as filter medium
A3: Code | B3: Description | C3: Unit | D3: Quantity | E3: Rate | F3: Amount
B4: Details of cost for 1 cum
B5: MATERIAL:
A6: 293 | B6: Stone Aggregate (Single size) : 40 mm nominal size | C6: m3 | D6: 1 | E6: 1300 | F6: =D6*E6 -> 1300
B7: LABOUR:
A8: 2206 | B8: Carriage of Stone aggregate 40 mm nominal size and above | C8: m3 | D8: 1 | E8: 178.19 | F8: =D8*E8 -> 178.19
A9: 115 | B9: Coolie | C9: Day | D9: 0.4 | E9: 645 | F9: =E9*D9 -> 258
B10: TOTAL | F10: =SUM(F6:F9) -> 1736.19
B11: Add Water Charges @ 1% | F11: =F10*1% -> 17.3619
B12: TOTAL | F12: =SUM(F10:F11) -> 1753.5519
B13: Add CPOH @ 15% | F13: =F12*15% -> 263.03278
B14: TOTAL | F14: =SUM(F12:F13) -> 2016.5847
B15: Cost per 1 cum | F15: =F14 -> 2016.5847
B16: Say | F16: =MROUND(F15, 0.05) -> 2016.6
A17: =CONCATENATE("Say ",F16," x Cost Index") -> Say 2016.6 x Cost Index
A18: 0 | B18: Supply and filling of 25mm metal as filter medium
A19: Code | B19: Description | C19: Unit | D19: Quantity | E19: Rate | F19: Amount
B20: Details of cost for 1 cum
B21: MATERIAL:
A22: 294 | B22: Stone Aggregate (Single size) : 25 mm nominal size | C22: m3 | D22: 1 | E22: 1350 | F22: =D22*E22 -> 1350
B23: LABOUR:
A24: 2202 | B24: Carriage of Stone aggregate below 40 mm nominal size | C24: m3 | D24: 1 | E24: 163.93 | F24: =D24*E24 -> 163.93
A25: 115 | B25: Coolie | C25: Day | D25: 0.4 | E25: 645 | F25: =E25*D25 -> 258
B26: TOTAL | F26: =SUM(F22:F25) -> 1771.93
B27: Add Water Charges @ 1% | F27: =F26*1% -> 17.7193
B28: TOTAL | F28: =SUM(F26:F27) -> 1789.6493
B29: Add CPOH @ 15% | F29: =F28*15% -> 268.44739
B30: TOTAL | F30: =SUM(F28:F29) -> 2058.0967
B31: Cost per 1 cum | F31: =F30 -> 2058.0967
B32: Say | F32: =MROUND(F31, 0.05) -> 2058.1
A33: =CONCATENATE("Say ",F32," x Cost Index") -> Say 2058.1 x Cost Index
A34: 0 | B34: Supply and filling of 20mm/6mm metal as filter medium
A35: Code | B35: Description | C35: Unit | D35: Quantity | E35: Rate | F35: Amount
B36: Details of cost for 1 cum
B37: MATERIAL:
A38: 0295/0298 | B38: Stone Aggregate (Single size) : 20 mm / 6 mm nominal size | C38: m3 | D38: 1 | E38: 1400 | F38: =D38*E38 -> 1400
B39: LABOUR:
A40: 2202 | B40: Carriage of Stone aggregate below 40 mm nominal size | C40: m3 | D40: 1 | E40: 163.93 | F40: =D40*E40 -> 163.93
A41: 115 | B41: Coolie | C41: Day | D41: 0.4 | E41: 645 | F41: =E41*D41 -> 258
B42: TOTAL | F42: =SUM(F38:F41) -> 1821.93
B43: Add Water Charges @ 1% | F43: =F42*1% -> 18.2193
B44: TOTAL | F44: =SUM(F42:F43) -> 1840.1493
B45: Add CPOH @ 15% | F45: =F44*15% -> 276.0224
B46: TOTAL | F46: =SUM(F44:F45) -> 2116.1717
B47: Cost per 1 cum | F47: =F46 -> 2116.1717
B48: Say | F48: =MROUND(F47, 0.05) -> 2116.15
A49: =CONCATENATE("Say ",F48," x Cost Index") -> Say 2116.15 x Cost Index
A50: 0 | B50: Supply and filling of Coarse Sand as filter medium
A51: Code | B51: Description | C51: Unit | D51: Quantity | E51: Rate | F51: Amount
B52: Details of cost for 1 cum
B53: MATERIAL:
A54: 982 | B54: Coarse sand (zone III) | C54: m3 | D54: 1 | E54: 1500 | F54: =D54*E54 -> 1500
B55: LABOUR:
A56: 2203 | B56: Carriage of Coarse sand | C56: m3 | D56: 1 | E56: 163.93 | F56: =D56*E56 -> 163.93
A57: 115 | B57: Coolie | C57: Day | D57: 0.6 | E57: 645 | F57: =E57*D57 -> 387
B58: TOTAL | F58: =SUM(F54:F57) -> 2050.93
B59: Add Water Charges @ 1% | F59: =F58*1% -> 20.5093
B60: TOTAL | F60: =SUM(F58:F59) -> 2071.4393
B61: Add CPOH @ 15% | F61: =F60*15% -> 310.71589
B62: TOTAL | F62: =SUM(F60:F61) -> 2382.1552
B63: Cost per 1 cum | F63: =F62 -> 2382.1552
B64: Say | F64: =MROUND(F63, 0.05) -> 2382.15
A65: =CONCATENATE("Say ",F64," x Cost Index") -> Say 2382.15 x Cost Index
A66: 0 | B66: Supply and filling of Charcoal as filter medium
A67: Code | B67: Description | C67: Unit | D67: Quantity | E67: Rate | F67: Amount
B68: Details of cost for 1 quintal
B69: MATERIAL:
A70: MR1266 | B70: Charcoal | C70: quintal | D70: 1 | E70: 675 | F70: =D70*E70 -> 675
B71: LABOUR:
A72: 2200 | B72: Carriage of Steam coal | C72: tonne | D72: 0.1 | E72: 187 | F72: =D72*E72 -> 18.7
A73: 115 | B73: Coolie | C73: Day | D73: 0.6 | E73: 645 | F73: =E73*D73 -> 387
B74: TOTAL | F74: =SUM(F70:F73) -> 1080.7
B75: Add Water Charges @ 1% | F75: =F74*1% -> 10.807
B76: TOTAL | F76: =SUM(F74:F75) -> 1091.507
B77: Add CPOH @ 15% | F77: =F76*15% -> 163.72605
B78: TOTAL | F78: =SUM(F76:F77) -> 1255.2331
B79: Cost per 100 kg | F79: =F78 -> 1255.2331
B80: Cost per 1 kg | F80: =F79/100 -> 12.552331
B81: Cost per 1 cum (200 kg) | F81: =F80*200 -> 2510.4661
B82: Say | F82: =MROUND(F81, 0.05) -> 2510.45
A83: =CONCATENATE("Say ",F82," x Cost Index") -> Say 2510.45 x Cost Index

Sheet BW Casing Pipes
A1: Casing Pipe For Borewell , Tube Well And Filterpoint Well
A2: 0 | B2: Supplying, assembling, lowering and fixing in vertical position in Borewell, PVC 140 mm 6 Kg/cm2 well casing pipe of required dia, conforming to IS : 4985:2000, including required hire and labour charges, fittings & accessories etc. all complete, for all depths, as per direction of Engineer- in- Charge.
A3: Code | B3: Description | C3: Unit | D3: Quantity | E3: Rate | F3: Amount
B4: Details of cost for 100 metre
B5: MATERIAL:
A6: MR10215 | B6: PVC Pipe, 6kg/cm2, 140mm Dia | C6: metre | D6: 100 | E6: {=IFERROR(INDEX(LMRRates,MATCH(A6,LMRCodes,0), ), )} -> 281 | F6: =D6*E6 -> 28100
B7: TOTAL | F7: =SUM(F6) -> 28100
B8: Add Water Charges @ 1% | F8: =F7*1/100 -> 281
B9: TOTAL | F9: =SUM(F7:F8) -> 28381
B10: Add CPOH @ 15% | F10: =F9*0.15 -> 4257.15
B11: TOTAL | F11: =SUM(F9:F10) -> 32638.15
B12: Cost of 100 metre | F12: =F11 -> 32638.15
B13: Cost per metre | F13: =MROUND((F12/100), 0.05) -> 326.4
B14: LABOUR:
A15: 2321 | B15: Carriage of Spun iron S & S pipes 150 mm dia | C15: 100 meter | D15: 50 | E15: 597 | F15: =E15/2 -> 298.5
A16: 114 | B16: Beldar | C16: Day | D16: 0.5 | E16: 645 | F16: =E16*D16 -> 322.5
A17: 115 | B17: Coolie | C17: Day | D17: 0.5 | E17: 645 | F17: =E17*D17 -> 322.5
A18: 9999 | B18: Sundries-(Adhesive etc.) | C18: L.S | D18: 10.07 | E18: 2.12 | F18: =E18*D18 -> 21.3484
B19: TOTAL | F19: =SUM(F15:F18) -> 964.8484
B20: Add Water Charges @ 1% | F20: =F19*0.01 -> 9.648484
B21: TOTAL | F21: =SUM(F19:F20) -> 974.49688
B22: Add CPOH @ 15% | F22: =F21*0.15 -> 146.17453
B23: TOTAL | F23: =SUM(F21:F22) -> 1120.6714
B24: Cost of 100.0 metre | F24: =F23 -> 1120.6714
B25: Cost per metre | F25: =F24/100 -> 11.206714
B26: Say | F26: =MROUND(F25, 0.05) -> 11.2
A27: =CONCATENATE("Say ",F13," + ",F26," x Cost Index") -> Say 326.4 + 11.2 x Cost Index
A28: 0 | B28: Supplying, assembling, lowering and fixing in vertical position in Borewell, PVC 140 mm 8 Kg/cm2 well casing pipe of required dia, conforming to IS : 4985:2000, including required hire and labour charges, fittings & accessories etc. all complete, for all depths, as per direction of Engineer- in- Charge.
A29: Code | B29: Description | C29: Unit | D29: Quantity | E29: Rate | F29: Amount
B30: Details of cost for 100 metre
B31: MATERIAL:
A32: MR10225 | B32: PVC Pipe, 8kg/cm2, 140mm Dia. | C32: metre | D32: 100 | E32: {=IFERROR(INDEX(LMRRates,MATCH(A32,LMRCodes,0), ), )} -> 398 | F32: =D32*E32 -> 39800
B33: TOTAL | F33: =SUM(F32) -> 39800
B34: Add Water Charges @ 1% | F34: =F33*0.01 -> 398
B35: TOTAL | F35: =SUM(F33:F34) -> 40198
B36: Add CPOH @ 15% | F36: =F35*0.15 -> 6029.7
B37: TOTAL | F37: =SUM(F35:F36) -> 46227.7
B38: Cost of 100 metre | F38: =F37 -> 46227.7
B39: Cost per metre | F39: =MROUND((F38/100), 0.05) -> 462.3
B40: LABOUR:
A41: 2321 | B41: Carriage of Spun iron S & S pipes 150 mm dia | C41: 100 meter | D41: 50 | E41: 597 | F41: =E41/2 -> 298.5
A42: 114 | B42: Beldar | C42: Day | D42: 0.5 | E42: 645 | F42: =D42*E42 -> 322.5
A43: 115 | B43: Coolie | C43: Day | D43: 0.5 | E43: 645 | F43: =D43*E43 -> 322.5
A44: 9999 | B44: Sundries-(Adhesive etc.) | C44: L.S | D44: 10.07 | E44: 2.12 | F44: =D44*E44 -> 21.3484
B45: TOTAL | F45: =SUM(F41:F44) -> 964.8484
B46: Add Water Charges @ 1% | F46: =F45*0.01 -> 9.648484
B47: TOTAL | F47: =SUM(F45:F46) -> 974.49688
B48: Add CPOH @ 15% | F48: =F47*0.15 -> 146.17453
B49: TOTAL | F49: =SUM(F47:F48) -> 1120.6714
B50: Cost of 100.0 metre | F50: =F49 -> 1120.6714
B51: Cost per metre | F51: =F50/100 -> 11.206714
B52: Say | F52: =MROUND(F51, 0.05) -> 11.2
A53: =CONCATENATE("Say ",F39," + ",F52," x Cost Index") -> Say 462.3 + 11.2 x Cost Index
A54: 0 | B54: Supplying, assembling, lowering and fixing in vertical position in Borewell, PVC 160mm 6 Kg/cm2 well casing pipe of required dia, conforming to IS : 4985:2000, including required hire and labour charges, fittings & accessories etc. all complete, for all depths, as per direction of Engineer- in- Charge.
A55: Code | B55: Description | C55: Unit | D55: Quantity | E55: Rate | F55: Amount
B56: Details of cost for 100 metre
B57: MATERIAL:
A58: MR10216 | B58: PVC Pipe, 6kg/cm2, 160mm Dia | C58: metre | D58: 100 | E58: {=IFERROR(INDEX(LMRRates,MATCH(A58,LMRCodes,0), ), )} -> 387 | F58: =D58*E58 -> 38700
B59: TOTAL | F59: =SUM(F58) -> 38700
B60: Add Water Charges @ 1% | F60: =F59*0.01 -> 387
B61: TOTAL | F61: =SUM(F59:F60) -> 39087
A62: 114 | B62: Add CPOH @ 15% | F62: =F61*0.15 -> 5863.05
A63: 115 | B63: TOTAL | F63: =SUM(F61:F62) -> 44950.05
A64: 9999 | B64: Cost of 100 metre | F64: =F63 -> 44950.05
B65: Cost per metre | F65: =MROUND((F64/100), 0.05) -> 449.5
B66: LABOUR:
A67: 2321 | B67: Carriage of Spun iron S & S pipes 150 mm dia | C67: 100 meter | D67: 50 | E67: 597 | F67: =E67/2 -> 298.5
A68: 114 | B68: Beldar | C68: Day | D68: 0.5 | E68: 645 | F68: =D68*E68 -> 322.5
A69: 115 | B69: Coolie | C69: Day | D69: 0.5 | E69: 645 | F69: =D69*E69 -> 322.5
A70: 9999 | B70: Sundries-(Adhesive etc.) | C70: L.S | D70: 10.07 | E70: 2.12 | F70: =D70*E70 -> 21.3484
B71: TOTAL | F71: =SUM(F67:F70) -> 964.8484
B72: Add Water Charges @ 1% | F72: =F71*0.01 -> 9.648484
B73: TOTAL | F73: =SUM(F71:F72) -> 974.49688
B74: Add CPOH @ 15% | F74: =F73*0.15 -> 146.17453
B75: TOTAL | F75: =SUM(F73:F74) -> 1120.6714
B76: Cost of 100.0 metre | F76: =F75 -> 1120.6714
B77: Cost per metre | F77: =F76/100 -> 11.206714
B78: Say | F78: =MROUND(F77, 0.05) -> 11.2
A79: =CONCATENATE("Say ",F65," + ",F78," x Cost Index") -> Say 449.5 + 11.2 x Cost Index
A80: 0 | B80: Supplying, assembling, lowering and fixing in vertical position in Borewell, PVC 180mm 6 Kg/cm2 well casing pipe of required dia, conforming to IS : 4985:2000, including required hire and labour charges, fittings & accessories etc. all complete, for all depths, as per direction of Engineer- in- Charge.
A81: Code | B81: Description | C81: Unit | D81: Quantity | E81: Rate | F81: Amount
B82: Details of cost for 100 metre
B83: MATERIAL:
A84: DL1 | B84: PVC Pipe, 6kg/cm2, 180mm Dia. | C84: metre | D84: 100 | E84: {=IFERROR(INDEX(DerivedRates,MATCH(A84,DerivedCodes,0), ), )} -> 487 | F84: =D84*E84 -> 48700
B85: TOTAL | F85: =SUM(F84) -> 48700
B86: Add Water Charges @ 1% | F86: =F85*0.01 -> 487
B87: TOTAL | F87: =SUM(F85:F86) -> 49187
B88: Add CPOH @ 15% | F88: =F87*0.15 -> 7378.05
B89: TOTAL | F89: =SUM(F87:F88) -> 56565.05
B90: Cost of 100 metre | F90: =F89 -> 56565.05
B91: Cost per metre | F91: =MROUND((F90/100), 0.05) -> 565.65
B92: LABOUR:
A93: 2321 | B93: Carriage of Spun iron S & S pipes 150 mm dia | C93: 100 meter | D93: 50 | E93: 597 | F93: =E93/2 -> 298.5
A94: 114 | B94: Beldar | C94: Day | D94: 0.5 | E94: 645 | F94: =E94*D94 -> 322.5
A95: 115 | B95: Coolie | C95: Day | D95: 0.5 | E95: 645 | F95: =E95*D95 -> 322.5
A96: 9999 | B96: Sundries-(Adhesive etc.) | C96: L.S | D96: 10.07 | E96: 2.12 | F96: =E96*D96 -> 21.3484
B97: TOTAL | F97: =SUM(F93:F96) -> 964.8484
B98: Add Water Charges @ 1% | F98: =F97*0.01 -> 9.648484
B99: TOTAL | F99: =SUM(F97:F98) -> 974.49688
B100: Add CPOH @ 15% | F100: =F99*0.15 -> 146.17453
...

Sheet BW Casing Pipe Erection Charge
A1: Casing Pipe For Borewell , Tube Well And Filterpoint Well
A2: 0 | B2: Assembling, lowering and fixing in vertical position in Borewell, PVC 140 mm 6 Kg/cm2 well casing pipe of required dia, conforming to IS : 4985:2000, including required hire and labour charges, fittings & accessories etc. all complete, for all depths, as per direction of Engineer- in- Charge. (Excluding Material)
A3: Code | B3: Description | C3: Unit | D3: Quantity | E3: Rate | F3: Amount
B4: Details of cost for 100 metre
B5: LABOUR:
A6: 2321 | B6: Carriage of Spun iron S & S pipes 150 mm dia | C6: 100 meter | D6: 50 | E6: 597 | F6: =E6/2 -> 298.5
A7: 114 | B7: Beldar | C7: Day | D7: 0.5 | E7: 645 | F7: =E7*D7 -> 322.5
A8: 115 | B8: Coolie | C8: Day | D8: 0.5 | E8: 645 | F8: =E8*D8 -> 322.5
A9: 9999 | B9: Sundries-(Adhesive etc.) | C9: L.S | D9: 10.07 | E9: 2.12 | F9: =E9*D9 -> 21.3484
B10: TOTAL | F10: =SUM(F6:F9) -> 964.8484
B11: Add Water Charges @ 1% | F11: =F10*0.01 -> 9.648484
B12: TOTAL | F12: =SUM(F10:F11) -> 974.49688
B13: Add CPOH @ 15% | F13: =F12*0.15 -> 146.17453
B14: TOTAL | F14: =SUM(F12:F13) -> 1120.6714
B15: Cost of 100.0 metre | F15: =F14 -> 1120.6714
B16: Cost per metre | F16: =F15/100 -> 11.206714
B17: Say | F17: =MROUND(F16, 0.05) -> 11.2
A18: =CONCATENATE("Say ",F17," x Cost Index") -> Say 11.2 x Cost Index

Sheet Electrical Essentials
A1: Spec Code | B1: Specification | C1: Rate (₹) | D1: Unit
A2: 2.10.1 | B2: Supplying and fixing 5 amps to 32 amps rating, 240/415 volts, "C" curve, miniature circuit breaker suitable for inductive load of following poles in the existing MCB DB complete with connections, testing and commissioning etc. as required. Single pole (2.10.1) | C2: 193.76 | D2: each
A3: 2.10.2 | B3: Supplying and fixing 5 amps to 32 amps rating, 240/415 volts, "C" curve, miniature circuit breaker suitable for inductive load of following poles in the existing MCB DB complete with connections, testing and commissioning etc. as required. Single pole and netural (2.10.2) | C3: 452.76 | D3: each
A4: 2.10.3 | B4: Supplying and fixing 5 amps to 32 amps rating, 240/415 volts, "C" curve, miniature circuit breaker suitable for inductive load of following poles in the existing MCB DB complete with connections, testing and commissioning etc. as required. Double pole (2.10.3) | C4: 495.76 | D4: each
A5: 2.10.4 | B5: Supplying and fixing 5 amps to 32 amps rating, 240/415 volts, "C" curve, miniature circuit breaker suitable for inductive load of following poles in the existing MCB DB complete with connections, testing and commissioning etc. as required. Triple pole (2.10.4) | C5: 760.76 | D5: each
A6: 2.10.5 | B6: Supplying and fixing 5 amps to 32 amps rating, 240/415 volts, "C" curve, miniature circuit breaker suitable for inductive load of following poles in the existing MCB DB complete with connections, testing and commissioning etc. as required. Triple pole and neutral (2.10.5) | C6: 927.76 | D6: each
A7: 2.3.1 | B7: Supplying and fixing following way, single pole and neutral, sheet steel, MCB distribution board, 240 V, on surface/ recess, complete with tinned copper bus bar, neutral bus bar, earth bar, din bar, interconnections, powder painted including earthing etc. as required. (But without MCBIRCCB/Isolator 6 way, Double door (2.3.1) | C7: 1668.16 | D7: each
A8: 2.3.2 | B8: Supplying and fixing following way, single pole and neutral, sheet steel, MCB distribution board, 240 V, on surface/ recess, complete with tinned copper bus bar, neutral bus bar, earth bar, din bar, interconnections, powder painted including earthing etc. as required. (But without MCBIRCCB/Isolator 8 way, Double door (2.3.2) | C8: 1945.16 | D8: each
A9: 2.3.3 | B9: Supplying and fixing following way, single pole and neutral, sheet steel, MCB distribution board, 240 V, on surface/ recess, complete with tinned copper bus bar, neutral bus bar, earth bar, din bar, interconnections, powder painted including earthing etc. as required. (But without MCBIRCCB/Isolator 12 way, Double door (2.3.3) | C9: 1750.16 | D9: each
A10: 2.3.4 | B10: Supplying and fixing following way, single pole and neutral, sheet steel, MCB distribution board, 240 V, on surface/ recess, complete with tinned copper bus bar, neutral bus bar, earth bar, din bar, interconnections, powder painted including earthing etc. as required. (But without MCBIRCCB/Isolator 16 way, Double door (2.3.4) | C10: 2374.16 | D10: each
A11: 2.14.1 | B11: Supplying and fixing following rating, double pole, (single phase and neutral), 240 volts, residual current circuit breaker (RCCB), having a sensitivity current upto 300 milliamperes in the existing MCB DB complete with connections, testing and commissioning etc. as required. 25 amps (2.14.1) | C11: 1531.45 | D11: each
A12: 2.14.2 | B12: Supplying and fixing following rating, double pole, (single phase and neutral), 240 volts, residual current circuit breaker (RCCB), having a sensitivity current upto 300 milliamperes in the existing MCB DB complete with connections, testing and commissioning etc. as required. 40 amps (2.14.2) | C12: 1995.45 | D12: each
A13: 2.14.3 | B13: Supplying and fixing following rating, double pole, (single phase and neutral), 240 volts, residual current circuit breaker (RCCB), having a sensitivity current upto 300 milliamperes in the existing MCB DB complete with connections, testing and commissioning etc. as required. 63 amps (2.14.3) | C13: 2055.45 | D13: each
... A53: 1.17.37 | B53: Supplying and drawing following sizes of FRLS PVC insulated copper conductor, single core cable in the existing surface / recessed steel/ PVC conduit as required.10 x 6 sq. mm(1.17.37) | C53: 730.69 | D53: metre

Sheet GI on Wall PRICE
A1: Spec Code | B1: Specification | C1: Rate (₹) | D1: Unit
A2: 18.10.1 | B2: Providing and fixing G.I. pipes complete with G.I. fittings and clamps, including cutting and making good the walls etc. Internal work- Exposed on wall 15 mm dia nominal bore (18.10.1) | C2: 264.02 | D2: meter
A3: 18.10.2 | B3: Providing and fixing G.I. pipes complete with G.I. fittings and clamps, including cutting and making good the walls etc. Internal work- Exposed on wall 20 mm dia nominal bore (18.10.2) | C3: 324.12 | D3: meter
A4: 18.10.3 | B4: Providing and fixing G.I. pipes complete with G.I. fittings and clamps, including cutting and making good the walls etc. Internal work- Exposed on wall 25 mm dia nominal bore (18.10.3) | C4: 426.41 | D4: meter
A5: 18.10.4 | B5: Providing and fixing G.I. pipes complete with G.I. fittings and clamps, including cutting and making good the walls etc. Internal work- Exposed on wall 32 mm dia nominal bore (18.10.4) | C5: 489.26 | D5: meter
A6: 18.10.5 | B6: Providing and fixing G.I. pipes complete with G.I. fittings and clamps, including cutting and making good the walls etc. Internal work- Exposed on wall 40 mm dia nominal bore (18.10.5) | C6: 629.54 | D6: meter
A7: 18.10.6 | B7: Providing and fixing G.I. pipes complete with G.I. fittings and clamps, including cutting and making good the walls etc. Internal work- Exposed on wall 50 mm dia nominal bore (18.10.6) | C7: 775.43 | D7: meter

Sheet GI wo Trench
A1: GI Pipe Without Trenching
A2: 0 | B2: Providing and fixing G.I. pipes complete with G.I fittings: 25 mm dia nominal bore
A3: Code | B3: Description | C3: Unit | D3: Quantity | E3: Rate | F3: Amount
B4: Details of cost for 10 metre
B5: MATERIAL:
A6: 1547 | B6: G.I. pipes 25 mm dia | C6: metre | D6: 10.2 | E6: 196 | F6: =D6*E6 -> 1999.2
B7: Weight for carriage = pipe weight + 2% for fittings =
B8: 1.02 x 24.60 = 25.092 kg = 0.025092 tonne
A9: 2271 | B9: Carriage of G.I. pipes below 100 mm dia | C9: tonne | D9: 0.02509 | E9: 145.72 | F9: =D9*E9 -> 3.6561148
A10: 9999 | B10: Sundries-White lead, hemp, oil etc | C10: L.S | D10: 6.76 | E10: 2.12 | F10: =D10*E10 -> 14.3312
B11: LABOUR:
A12: 116 | B12: Fitter(grade1) | C12: Day | D12: 0.12 | E12: 784 | F12: =D12*E12 -> 94.08
A13: 114 | B13: Beldar | C13: Day | D13: 0.25 | E13: 645 | F13: =D13*E13 -> 161.25
B14: TOTAL | F14: =SUM(F6:F13) -> 2272.5173
B15: Add Water Charges @ 1% | F15: =F14*0.01 -> 22.725173
B16: TOTAL | F16: =SUM(F14:F15) -> 2295.2425
B17: Add CPOH @ 15% | F17: =F16*0.15 -> 344.28637
B18: TOTAL | F18: =SUM(F16:F17) -> 2639.5289
B19: Cost of 10.0 metre | F19: =F18 -> 2639.5289
B20: Cost per metre | F20: =F19/10 -> 263.95289
B21: Say | F21: =MROUND(F20, 0.05) -> 263.95
A22: 0 | B22: Providing and fixing G.I. pipes complete with G.I fittings: 32 mm dia nominal bore
A23: Code | B23: Description | C23: Unit | D23: Quantity | E23: Rate | F23: Amount
B24: Details of cost for 10 metre
B25: MATERIAL:
A26: 1548 | B26: G.I. pipes 32 mm dia | C26: metre | D26: 10.2 | E26: 225 | F26: =10.2*225 -> 2295
B27: Weight for carriage = pipe weight + 2% for fittings =
B28: 1.02 x 31.70 = 32.334 kg = 0.032334 tonne
A29: 2271 | B29: Carriage of G.I. pipes below 100 mm dia | C29: tonne | D29: 0.03233 | E29: 145.72 | F29: =D29*E29 -> 4.7111276
A30: 9999 | B30: Sundries-White lead, hemp, oil etc. | C30: L.S | D30: 6.76 | E30: 2.12 | F30: =D30*E30 -> 14.3312
B31: LABOUR:
A32: 116 | B32: Fitter(grade1) | C32: Day | D32: 0.12 | E32: 784 | F32: =D32*E32 -> 94.08
A33: 114 | B33: Beldar | C33: Day | D33: 0.25 | E33: 645 | F33: =D33*E33 -> 161.25
B34: TOTAL | F34: =SUM(F26:F33) -> 2569.3723
B35: Add Water Charges @ 1% | F35: =F34*0.01 -> 25.693723
B36: TOTAL | F36: =SUM(F34:F35) -> 2595.0661
B37: Add CPOH @ 15% | F37: =F36*0.15 -> 389.25991
B38: TOTAL | F38: =SUM(F36:F37) -> 2984.326
B39: Cost of 10.0 metre | F39: =F38 -> 2984.326
B40: Cost per metre | F40: =F39/10 -> 298.4326
B41: Say | F41: =MROUND(F40, 0.05) -> 298.45
A42: 0 | B42: Providing and fixing G.I. pipes complete with G.I fittings: 40 mm dia nominal bore
A43: Code | B43: Description | C43: Unit | D43: Quantity | E43: Rate | F43: Amount
B44: Details of cost for 10 metre
B45: MATERIAL:
A46: 1549 | B46: G.I. pipes 40 mm dia | C46: metre | D46: 10.2 | E46: 290 | F46: =D46*E46 -> 2958
B47: Weight for carriage = pipe weight + 2% for fittings =
B48: 1.02x36.50 = 37.23 kg = 0.03723tonne
A49: 2271 | B49: Carriage of G.I. pipes below 100 mm dia | C49: tonne | D49: 0.03723 | E49: 145.72 | F49: =D49*E49 -> 5.4251556
A50: 9999 | B50: Sundries-White lead, hemp, oil etc, | C50: L.S | D50: 9.49 | E50: 2.12 | F50: =D50*E50 -> 20.1188
B51: LABOUR:
A52: 116 | B52: Fitter(grade1) | C52: Day | D52: 0.16 | E52: 784 | F52: =D52*E52 -> 125.44
A53: 114 | B53: Beldar | C53: Day | D53: 0.33 | E53: 645 | F53: =D53*E53 -> 212.85
B54: TOTAL | F54: =SUM(F46:F53) -> 3321.834
B55: Add Water Charges @ 1% | F55: =F54*0.01 -> 33.21834
B56: TOTAL | F56: =SUM(F54:F55) -> 3355.0523
B57: Add CPOH @ 15% | F57: =F56*0.15 -> 503.25784
B58: TOTAL | F58: =SUM(F56:F57) -> 3858.3101
B59: Cost of 10.0 metre | F59: =F58 -> 3858.3101
B60: Cost per metre | F60: =F59/10 -> 385.83101
B61: Say | F61: =MROUND(F60, 0.05) -> 385.85
A62: 0 | B62: Providing and fixing G.I. pipes complete with G.I fittings: 50 mm dia nominal bore
A63: Code | B63: Description | C63: Unit | D63: Quantity | E63: Rate | F63: Amount
B64: Details of cost for 10 metre
B65: MATERIAL:
A66: 1550 | B66: G.I pipes 50 mm dia | C66: metre | D66: 10.2 | E66: 360 | F66: =D66*E66 -> 3672
B67: Weight for carriage = pipe weight + 2% for fittings =
B68: 1.02 x 51.70 = 52.73 kg = 0.05273 tonne
A69: 2271 | B69: Carriage of G.I. pipes below 100 mm dia | C69: tonne | D69: 0.05273 | E69: 145.72 | F69: =D69*E69 -> 7.6838156
A70: 9999 | B70: Sundries-White lead, hemp, oil etc | C70: L.S | D70: 9.49 | E70: 2.12 | F70: =D70*E70 -> 20.1188
B71: LABOUR:
A72: 116 | B72: Fitter(grade1) | C72: Day | D72: 0.16 | E72: 784 | F72: =D72*E72 -> 125.44
A73: 114 | B73: Beldar | C73: Day | D73: 0.33 | E73: 645 | F73: =D73*E73 -> 212.85
B74: TOTAL | F74: =SUM(F66:F73) -> 4038.0926
B75: Add Water Charges @ 1% | F75: =F74*0.01 -> 40.380926
B76: TOTAL | F76: =SUM(F74:F75) -> 4078.4735
B77: Add CPOH @ 15% | F77: =F76*0.15 -> 611.77103
B78: TOTAL | F78: =SUM(F76:F77) -> 4690.2446
B79: Cost of 10.0 metre | F79: =F78 -> 4690.2446
B80: Cost per metre | F80: =F79/10 -> 469.02446
B81: Say | F81: =MROUND(F80, 0.05) -> 469
A82: 0 | B82: Providing and fixing G.I. pipes complete with G.I fittings: 65 mm dia nominal bore
A83: Code | B83: Description | C83: Unit | D83: Quantity | E83: Rate | F83: Amount
B84: Details of cost for 10 metre
B85: MATERIAL:
A86: 1551 | B86: G.I. pipes 65 mm dia | C86: metre | D86: 10.2 | E86: 415 | F86: =D86*E86 -> 4233
B87: Weight for carriage = pipe weight + 2% for fittings =
B88: 1.02 x 66.30 = 67.626 kg = 0.067626 tonne
A89: 2271 | B89: Carriage of G.I. pipes below 100 mm dia | C89: tonne | D89: 0.06763 | E89: 145.72 | F89: =D89*E89 -> 9.8550436
A90: 9999 | B90: Sundries-White lead, hemp, oil etc | C90: L.S | D90: 13.52 | E90: 2.12 | F90: =D90*E90 -> 28.6624
B91: LABOUR:
A92: 116 | B92: Fitter(grade1) | C92: Day | D92: 0.25 | E92: 784 | F92: =E92*D92 -> 196
A93: 114 | B93: Beldar | C93: Day | D93: 0.66 | E93: 645 | F93: =D93*E93 -> 425.7
B94: TOTAL | F94: =SUM(F86:F93) -> 4893.2174
B95: Add Water Charges @ 1% | F95: =F94*0.01 -> 48.932174
B96: TOTAL | F96: =SUM(F94:F95) -> 4942.1496
B97: Add CPOH @ 15% | F97: =F96*0.15 -> 741.32244
B98: TOTAL | F98: =SUM(F96:F97) -> 5683.4721
B99: Cost of 10.0 metre | F99: =F98 -> 5683.4721
B100: Cost per metre | F100: =F99/10 -> 568.34721
...

Sheet GI With Trench PRICE
A1: Spec Code | B1: Specification | C1: Rate (₹) | D1: Unit
A2: 18.12.1 | B2: Providing and fixing G.I. pipes complete with G.I fittings including trenching and refilling etc. External work 15 mm dia nominal bore (18.12.1) | C2: 232.24 | D2: meter
A3: 18.12.2 | B3: Providing and fixing G.I. pipes complete with G.I fittings including trenching and refilling etc. External work 20 mm dia nominal bore (18.12.2) | C3: 273.77 | D3: meter
A4: 18.12.3 | B4: Providing and fixing G.I. pipes complete with G.I fittings including trenching and refilling etc. External work 25 mm dia nominal bore (18.12.3) | C4: 362.84 | D4: meter
A5: 18.12.4 | B5: Providing and fixing G.I. pipes complete with G.I fittings including trenching and refilling etc. External work 32 mm dia nominal bore (18.12.4) | C5: 397.33 | D5: meter
A6: 18.12.5 | B6: Providing and fixing G.I. pipes complete with G.I fittings including trenching and refilling etc. External work 40 mm dia nominal bore (18.12.5) | C6: 484.72 | D6: meter
A7: 18.12.6 | B7: Providing and fixing G.I. pipes complete with G.I fittings including trenching and refilling etc. External work 50 mm dia nominal bore (18.12.6) | C7: 567.92 | D7: meter
A8: 18.12.7 | B8: Providing and fixing G.I. pipes complete with G.I fittings including trenching and refilling etc. External work 65 mm dia nominal bore (18.12.7) | C8: 667.24 | D8: meter
A9: 18.12.8 | B9: Providing and fixing G.I. pipes complete with G.I fittings including trenching and refilling etc. External work 80 mm dia nominal bore (18.12.8) | C9: 797.9 | D9: meter

Sheet GI Works
A1: Sor/Spec Code | B1: MR Code | C1: Description | F1: Remarks
C2: Unit | D2: Quantity | E2: Rate (₹) | F2: Amount | G2: Label
A3: GI work in single section, fixed with or without connecting plate, including cutting, hoisting, fixing in position and applying a priming coat of approved steel primer all complete.
B4: Header Unit | C4: kilogram | D4: Header Quantity | E4: 100
A5: Header Details | B5: Details of cost for one quintal
A6: Material | G6: M
A7: 8019 | C7: GI sheet: 1.00q Add wastage @ 5% = 0.05q Total+ 1.05q GI sheet 0.8 mm thick confirming to IS 277:1992
C8: q | D8: 1.05 | E8: 9000 | F8: =D8*E8 -> 9450 | G8: M1
A9: Carriage | G9: C
A10: 2205 | C10: Carriage of Steel
C11: tonne | D11: 0.105 | E11: 145.72 | F11: =D11*E11 -> 15.3006 | G11: C1
A12: Labour | G12: L
A13: 116 | C13: Fitter(grade1)
C14: Day | D14: 0.5 | E14: 784 | F14: =E14*D14 -> 392 | G14: L1
A15: 102 | C15: Blacksmith 1st class
C16: Day | D16: 0.75 | E16: 784 | F16: =E16*D16 -> 588 | G16: L2
A17: 103 | C17: Blacksmith 2nd class
C18: Day | D18: 1 | E18: 714 | F18: =E18*D18 -> 714 | G18: L2
A19: 1214/1215 | C19: Welding by electric/gas plant
C20: cm | D20: 850 | E20: 2 | F20: =D20*E20 -> 1700 | G20: L3
A21: Subdata | G21: L
A22: 13.50.3 | C22: Finishing : With ready mixed red oxide zinc chromate primer of approved brand and manufacture on steel galvanised iron /steel works
C23: sqm | D23: 3 | E23: 48.19 | F23: =D23*E23 -> 144.57 | G23: S1
A24: TOTAL | D24: 100 | E24: kilogram | F24: =SUM(F8,F11,F14,F16,F18,F20+F23) -> 13003.871
A25: UNIT TOTAL | D25: 1 | E25: kilogram | F25: =F24/100 -> 130.03871
A26: Water Charge@ 1.00 % | E26: =F25 -> 130.03871 | F26: =E26/100 -> 1.3003871
A27: TOTAL | F27: =F25+F26 -> 131.33909
A28: Contractors Profit & Overhead@ 15.00 % | E28: =F27 -> 131.33909 | F28: =E28*0.15 -> 19.700864
A29: TOTAL | F29: =F27+F28 -> 151.03996
A30: Grand Total | F30: =round(F29,2) -> 151.04 | G30: /kg

Sheet Gravel for TWC
A1: Sor/Spec Code | B1: MR Code | C1: Description | F1: Remarks
C2: Unit | D2: Quantity | E2: Rate (₹) | F2: Amount | G2: Label
A3: Supplying of 4.75 to 8mm size pebble (pebbles shall be hard, clean, free from clay, dust and other impurities), stacking in standard heaps for measurement including cost, conveyance up to 5km and labour charges for stacking, spreading, testing and as per the directions of the department officers etc complete and as per CPHEEO specification.
B4: Header Unit | C4: cum | D4: Header Quantity | E4: 1
A5: Header Details | B5: Details of cost for 1 cum
A6: Material | G6: M
B7: MR10044 | C7: Cost of pebble 2 mm to 6 mm / 6mm to 12mm.
C8: cum | D8: 1 | E8: {=IFERROR(INDEX(LMRRates,MATCH(B7,LMRCodes,0), ), )} -> 6553 | F8: =D8*E8 -> 6553 | G8: M1
A9: TOTAL | D9: 1 | E9: cum | F9: =F8 -> 6553
A10: UNIT TOTAL | D10: 1 | E10: cum | F10: =F9/D9 -> 6553
A11: Water Charge@ 1.00 % | E11: =F10 -> 6553 | F11: =E11*1% -> 65.53
A12: TOTAL | F12: =F10+F11 -> 6618.53
A13: Contractors Profit & Overhead@ 15.00 % | E13: =F12 -> 6618.53 | F13: =E13*15% -> 992.7795
A14: TOTAL | F14: =round(F12+F13,2) -> 7611.31
A15: Carriage | G15: C
A16: 2202 | C16: Carriage of Stone aggregate below 40 mm nominal size
C17: cum | D17: 1 | E17: 163.93 | F17: =D17*E17 -> 163.93 | G17: C1
A18: Labour | G18: L
A19: 115 | C19: Coolie For spreading.
C20: Day | D20: 0.8 | E20: 645 | F20: =D20*E20 -> 516 | G20: L1
A21: Tools & Plants | G21: L
A22: 9999 | C22: Sundries Hire for tools.
C23: L.S | D23: 10 | E23: 2.12 | F23: =D23*E23 -> 21.2 | G23: T1
A24: 9999 | C24: Sundries Charges for testing.
C25: L.S | D25: 5 | E25: 2.12 | F25: =D25*E25 -> 10.6 | G25: T2
A26: TOTAL | D26: 1 | E26: cum | F26: =F17+F20+F23+F25 -> 711.73
A27: UNIT TOTAL | D27: 1 | E27: cum | F27: =F26/D26 -> 711.73
A28: Water Charge@ 1.00 % | E28: =F27 -> 711.73 | F28: =E28*1% -> 7.1173
A29: TOTAL | F29: =F27+F28 -> 718.8473
A30: Contractors Profit & Overhead@ 15.00 % | E30: =F29 -> 718.8473 | F30: =E30*15% -> 107.82709
A31: TOTAL | F31: =round(F29+F30,2) -> 826.67
A32: =CONCATENATE("Say ₹ ",F14," + ",F31," x Cost Index") -> Say ₹ 7611.31 + 826.67 x Cost Index | H32: =F8*1.01*1.15 -> 7611.3095 | I32: =(F17+F20+F23+F25)*1.01*1.15 -> 826.6744

Sheet Gutter&Clamp
A1: Gutter & Clamp
A2: 0 | B2: Providing and fixing PVC full pipe as gutter pipes includes laying jointing of pipes complete as per direction of Engineer in Charge for 140 mm dia 6 KGF/cm2
A3: Code | B3: Description | C3: Unit | D3: Quantity | E3: Rate | F3: Amount
B4: Details of cost for 10 metre
B5: MATERIALS:
A6: MR10215 | B6: PVC Pipe, 6kg/cm2, 140mm Dia | C6: metre | D6: 10.5 | E6: {=IFERROR(INDEX(LMRRates,MATCH(A6,LMRCodes,0), ), )} -> 281 | F6: =D6*E6 -> 2950.5
B7: Add 5% for fittings and wastage etc. on (A)
B8: Total | F8: =SUM(F6:F7) -> 2950.5
B9: Add Water Charges @ 1% | F9: =F8*0.01 -> 29.505
B10: TOTAL | F10: =F8+F9 -> 2980.005
B11: Add CPOH @ 15% | F11: =F10*0.15 -> 447.00075
B12: TOTAL | F12: =F10+F11 -> 3427.0057
B13: Cost of 10.0 metre | F13: =F12 -> 3427.0057
B14: Cost per metre | F14: =round((F13/10),2) -> 342.7
A15: 116 | B15: Fitter(grade1) | C15: Day | D15: 0.33 | E15: 784 | F15: =D15*E15 -> 258.72
A16: 117 | B16: Assistant Fitter or 2nd class fitter | C16: Day | D16: 0.4 | E16: 714 | F16: =D16*E16 -> 285.6
A17: 114 | B17: Beldar | C17: Day | D17: 0.4 | E17: 645 | F17: =D17*E17 -> 258
B18: TOTAL | F18: =SUM(F15:F17) -> 802.32
B19: Add Water Charges @ 1% | F19: =F18*0.01 -> 8.0232
B20: TOTAL | F20: =SUM(F18:F19) -> 810.3432
B21: Add CPOH @ 15% | F21: =F20*0.15 -> 121.55148
B22: TOTAL | F22: =SUM(F20:F21) -> 931.89468
B23: Cost of 10.0 metre | F23: =F22 -> 931.89468
B24: Cost per metre | F24: =round((F23/10),2) -> 93.19
A25: =CONCATENATE("Say ₹ ",F14," + ",F24," x Cost Index") -> Say ₹ 342.7 + 93.19 x Cost Index
A26: 0 | B26: Providing and fixing PVC gutter pipes includes laying jointing of pipes, complete as per direction of Engineer in Charge.for 160 mm dia 6 KGF/cm2
A27: Code | B27: Description | C27: Unit | D27: Quantity | E27: Rate | F27: Amount
B28: Details of cost for 10 metre
B29: MATERIALS:
A30: MR10216 | B30: PVC Pipe, 6kg/cm2, 160mm Dia | C30: metre | D30: 10.5 | E30: {=IFERROR(INDEX(LMRRates,MATCH(A30,LMRCodes,0), ), )} -> 387 | F30: =D30*E30 -> 4063.5
B31: Add 5% for fittings and wastage etc. on (A)
B32: Total | F32: =SUM(F30:F31) -> 4063.5
B33: Add Water Charges @ 1% | F33: =F32*0.01 -> 40.635
B34: TOTAL | F34: =F32+F33 -> 4104.135
B35: Add CPOH @ 15% | F35: =F34*0.15 -> 615.62025
B36: TOTAL | F36: =F34+F35 -> 4719.7553
B37: Cost of 10.0 metre | F37: =F36 -> 4719.7553
B38: Cost per metre | F38: =round((F37/10),2) -> 471.98
A39: 116 | B39: Fitter(grade1) | C39: Day | D39: 0.33 | E39: 784 | F39: =D39*E39 -> 258.72
A40: 117 | B40: Assistant Fitter or 2nd class fitter | C40: Day | D40: 0.4 | E40: 714 | F40: =D40*E40 -> 285.6
A41: 114 | B41: Beldar | C41: Day | D41: 0.4 | E41: 645 | F41: =D41*E41 -> 258
B42: TOTAL | F42: =SUM(F39:F41) -> 802.32
B43: Add Water Charges @ 1% | F43: =F42*0.01 -> 8.0232
B44: TOTAL | F44: =SUM(F42:F43) -> 810.3432
B45: Add CPOH @ 15% | F45: =F44*0.15 -> 121.55148
B46: TOTAL | F46: =SUM(F44:F45) -> 931.89468
B47: Cost of 10.0 metre | F47: =F46 -> 931.89468
B48: Cost per metre | F48: =round((F47/10),2) -> 93.19
A49: =CONCATENATE("Say ₹ ",F38," + ",F48," x Cost Index") -> Say ₹ 471.98 + 93.19 x Cost Index
A50: 0 | B50: Providing and fixing 140mm square PVC gutter pipes includes laying jointing of pipes including clamp, complete as per direction of Engineer in Charge
A51: Code | B51: Description | C51: Unit | D51: Quantity | E51: Rate | F51: Amount
B52: Details of cost for 10 metre
B53: MATERIALS:
A54: 0 | B54: PVC pipe 140 mm square | C54: metre | D54: 10.5 | E54: 340 | F54: =D54*E54 -> 3570
B55: Add 5% for fittings and wastage etc. on (A)
B56: Total | F56: =SUM(F54:F55) -> 3570
B57: Add Water Charges @ 1% | F57: =F56*0.01 -> 35.7
B58: TOTAL | F58: =F56+F57 -> 3605.7
B59: Add CPOH @ 15% | F59: =F58*0.15 -> 540.855
B60: TOTAL | F60: =F58+F59 -> 4146.555
B61: Cost of 10.0 metre | F61: =F60 -> 4146.555
B62: Cost per metre | F62: =round((F61/10),2) -> 414.66
A63: 116 | B63: Fitter(grade1) | C63: Day | D63: 0.33 | E63: 784 | F63: =D63*E63 -> 258.72
A64: 117 | B64: Assistant Fitter or 2nd class fitter | C64: Day | D64: 0.4 | E64: 714 | F64: =D64*E64 -> 285.6
A65: 114 | B65: Beldar | C65: Day | D65: 0.4 | E65: 645 | F65: =D65*E65 -> 258
B66: TOTAL | F66: =SUM(F63:F65) -> 802.32
B67: Add Water Charges @ 1% | F67: =F66*0.01 -> 8.0232
B68: TOTAL | F68: =SUM(F66:F67) -> 810.3432
B69: Add CPOH @ 15% | F69: =F68*0.15 -> 121.55148
B70: TOTAL | F70: =SUM(F68:F69) -> 931.89468
B71: Cost of 10.0 metre | F71: =F70 -> 931.89468
B72: Cost per metre | F72: =round((F71/10),2) -> 93.19
A73: =CONCATENATE("Say ₹ ",F62," + ",F72," x Cost Index") -> Say ₹ 414.66 + 93.19 x Cost Index
A74: 0 | B74: Providing and fixing 160mm square PVC gutter pipes includes laying jointing of pipes including clamp, complete as per direction of Engineer in Charge
A75: Code | B75: Description | C75: Unit | D75: Quantity | E75: Rate | F75: Amount
B76: Details of cost for 10 metre
B77: MATERIALS:
A78: 0 | B78: PVC pipe 160 mm square | C78: metre | D78: 11.5 | E78: 350 | F78: =D78*E78 -> 4025
B79: Add 15% for fittings and wastage etc. on (A)
B80: Total | F80: =SUM(F78:F79) -> 4025
B81: Add Water Charges @ 1% | F81: =F80*0.01 -> 40.25
B82: TOTAL | F82: =F80+F81 -> 4065.25
B83: Add CPOH @ 15% | F83: =F82*0.15 -> 609.7875
B84: TOTAL | F84: =F82+F83 -> 4675.0375
B85: Cost of 10.0 metre | F85: =F84 -> 4675.0375
B86: Cost per metre | F86: =round((F85/10),2) -> 467.5
A87: 116 | B87: Fitter(grade1) | C87: Day | D87: 0.33 | E87: 784 | F87: =D87*E87 -> 258.72
A88: 117 | B88: Assistant Fitter or 2nd class fitter | C88: Day | D88: 0.4 | E88: 714 | F88: =D88*E88 -> 285.6
A89: 114 | B89: Beldar | C89: Day | D89: 0.4 | E89: 645 | F89: =D89*E89 -> 258
B90: TOTAL | F90: =SUM(F87:F89) -> 802.32
B91: Add Water Charges @ 1% | F91: =F90*0.01 -> 8.0232
B92: TOTAL | F92: =SUM(F90:F91) -> 810.3432
B93: Add CPOH @ 15% | F93: =F92*0.15 -> 121.55148
B94: TOTAL | F94: =SUM(F92:F93) -> 931.89468
B95: Cost of 10.0 metre | F95: =F94 -> 931.89468
B96: Cost per metre | F96: =round((F95/10),2) -> 93.19
A97: =CONCATENATE("Say ₹ ",F86," + ",F96," x Cost Index") -> Say ₹ 467.5 + 93.19 x Cost Index
A98: 0 | B98: Providing and fixing MS Clamp for gutter pipe as per direction of Engineer in Charge.
A99: Code | B99: Description | C99: Unit | D99: Quantity | E99: Rate | F99: Amount
B100: Details of cost for 10 Nos
...

Sheet HP Erection and Pullout
A1: Hand Pump Erection and Pullout
A2: 0 | B2: Hand pump erection (deep well)
A3: Code | B3: Description | C3: Unit | D3: Quantity | E3: Rate | F3: Amount
B4: Tools hire charge (DSR 0015) | C4: day | D4: 0.2 | E4: 3000 | F4: =D4*E4 -> 600
A5: 116 | B5: Fitter, Plumber, Electrician | C5: Day | D5: 1.5 | E5: 784 | F5: =D5*E5 -> 1176
A6: 114 | B6: Beldar | C6: Day | D6: 3 | E6: 645 | F6: =D6*E6 -> 1935
B7: TOTAL | F7: =SUM(F4:F6) -> 3711
B8: Add Water Charges @ 1% | F8: =F7*0.01 -> 37.11
B9: TOTAL | F9: =SUM(F7:F8) -> 3748.11
B10: Add CPOH @ 15% | F10: =F9*0.15 -> 562.2165
B11: TOTAL | F11: =Mround(SUM(F9:F10),1) -> 4310
A12: =CONCATENATE("Say Rs (",F11," x Cost Index)") -> Say Rs (4310 x Cost Index)
A13: 0 | B13: Hand pump erection (extra deep well)
A14: Code | B14: Description | C14: Unit | D14: Quantity | E14: Rate | F14: Amount
A15: 0015 | B15: Tools hire charge (DSR 0015) | C15: day | D15: 0.3 | E15: 3000 | F15: =D15*E15 -> 900
A16: 0116 | B16: Fitter, Plumber, Electrician | C16: Day | D16: 2.5 | E16: 784 | F16: =D16*E16 -> 1960
A17: 0114 | B17: Beldar | C17: Day | D17: 3 | E17: 645 | F17: =D17*E17 -> 1935
B18: TOTAL | F18: =SUM(F15:F17) -> 4795
B19: Add Water Charges @ 1% | F19: =F18*0.01 -> 47.95
B20: TOTAL | F20: =SUM(F18:F19) -> 4842.95
B21: Add CPOH @ 15% | F21: =F20*0.15 -> 726.4425
B22: TOTAL | F22: =Mround(SUM(F20:F21),1) -> 5569
A23: =CONCATENATE("Say Rs (",F22," x Cost Index)") -> Say Rs (5569 x Cost Index)
A24: 0 | B24: Hand pump pullout (deep well)
A25: Code | B25: Description | C25: Unit | D25: Quantity | E25: Rate | F25: Amount
B26: Tools hire charge (DSR 0015) | C26: day | D26: 0.1 | E26: 3000 | F26: =D26*E26 -> 300
A27: 116 | B27: Fitter, Plumber, Electrician | C27: Day | D27: 0.75 | E27: 784 | F27: =D27*E27 -> 588
A28: 114 | B28: Beldar | C28: Day | D28: 1.5 | E28: 645 | F28: =D28*E28 -> 967.5
B29: TOTAL | F29: =SUM(F26:F28) -> 1855.5
B30: Add Water Charges @ 1% | F30: =F29*0.01 -> 18.555
B31: TOTAL | F31: =SUM(F29:F30) -> 1874.055
B32: Add CPOH @ 15% | F32: =F31*0.15 -> 281.10825
B33: TOTAL | F33: =Mround(SUM(F31:F32),1) -> 2155
A34: =CONCATENATE("Say Rs (",F33," x Cost Index)") -> Say Rs (2155 x Cost Index)
A35: 0 | B35: Hand pump pullout (extra deep well)
A36: Code | B36: Description | C36: Unit | D36: Quantity | E36: Rate | F36: Amount
B37: Tools hire charge (DSR 0015) | C37: day | D37: 0.15 | E37: 3000 | F37: =D37*E37 -> 450
A38: 116 | B38: Fitter, Plumber, Electrician | C38: Day | D38: 1.25 | E38: 784 | F38: =D38*E38 -> 980
A39: 114 | B39: Beldar | C39: Day | D39: 1.5 | E39: 645 | F39: =D39*E39 -> 967.5
B40: TOTAL | F40: =SUM(F37:F39) -> 2397.5
B41: Add Water Charges @ 1% | F41: =F40*0.01 -> 23.975
B42: TOTAL | F42: =SUM(F40:F41) -> 2421.475
B43: Add CPOH @ 15% | F43: =F42*0.15 -> 363.22125
B44: TOTAL | F44: =Mround(SUM(F42:F43),1) -> 2785
A45: =CONCATENATE("Say Rs (",F44," x Cost Index)") -> Say Rs (2785 x Cost Index)
A46: 0 | B46: Hand pump pullout and re-erection (deep well)
A47: Code | B47: Description | C47: Unit | D47: Quantity | E47: Rate | F47: Amount
B48: Tools hire charge (DSR 0015) | C48: day | D48: 0.1 | E48: 3000 | F48: =D48*E48 -> 300
A49: 116 | B49: Fitter, Plumber, Electrician | C49: Day | D49: 2 | E49: 784 | F49: =D49*E49 -> 1568
A50: 114 | B50: Beldar | C50: Day | D50: 3.5 | E50: 645 | F50: =D50*E50 -> 2257.5
B51: TOTAL | F51: =SUM(F48:F50) -> 4125.5
B52: Add Water Charges @ 1% | F52: =F51*0.01 -> 41.255
B53: TOTAL | F53: =SUM(F51:F52) -> 4166.755
B54: Add CPOH @ 15% | F54: =F53*0.15 -> 625.01325
B55: TOTAL | F55: =Mround(SUM(F53:F54),1) -> 4792
A56: =CONCATENATE("Say Rs (",F55," x Cost Index)") -> Say Rs (4792 x Cost Index)
A57: 0 | B57: Hand pump pullout and re-erection (extra deep well)
A58: Code | B58: Description | C58: Unit | D58: Quantity | E58: Rate | F58: Amount
B59: Tools hire charge (DSR 0015) | C59: day | D59: 0.2 | E59: 3000 | F59: =D59*E59 -> 600
A60: 116 | B60: Fitter, Plumber, Electrician | C60: Day | D60: 2.5 | E60: 784 | F60: =D60*E60 -> 1960
A61: 114 | B61: Beldar | C61: Day | D61: 4 | E61: 645 | F61: =D61*E61 -> 2580
B62: TOTAL | F62: =SUM(F59:F61) -> 5140
B63: Add Water Charges @ 1% | F63: =F62*0.01 -> 51.4
B64: TOTAL | F64: =SUM(F62:F63) -> 5191.4
B65: Add CPOH @ 15% | F65: =F64*0.15 -> 778.71
B66: TOTAL | F66: =Mround(SUM(F64:F65),1) -> 5970
A67: =CONCATENATE("Say Rs (",F66," x Cost Index)") -> Say Rs (5970 x Cost Index)

Sheet HP Repair Labour
A1: India Mark II Hand Pump Pullout, Repairing and Re-Erection Labour Charges
A2: (i) | B2: Labour charges for detaching the handpump, pullout of pipe and cylinder from the borewell, washing and cleaning of parts, renovation of damaged pipe threads, replacement of spare parts as required, and reinstallation of the handpump after necessary repairs, including loading and unloading of tools and machinery (excluding cost of spare parts).
A3: 0116 | B3: Fitter (grade I) | C3: 1 | D3: day | E3: 784 | F3: /day | G3: =E3*C3 -> 784
A4: 0117 | B4: Assistant Fitter or 2nd class Fitter | C4: 1 | D4: day | E4: 714 | F4: /day | G4: =E4*C4 -> 714
A5: 0115 | B5: Coolie | C5: 4 | D5: day | E5: 645 | F5: /day | G5: =E5*C5 -> 2580
A6: (ii) | B6: Hire charges for vehicle for to and fro transportation of tools, tripod with winch machine, etc.
A7: 0083 | B7: Hire charges of TATA 407 or equivalent for local shifting. | C7: 1 | D7: day | E7: 1400 | F7: /day | G7: =E7*C7 -> 1400
A8: 9999 | B8: Sundries | C8: 50 | D8: LS | E8: 2.12 | F8: /LS | G8: =E8*C8 -> 106
B9: Total | G9: =(SUM(G3:G5,G7:G8,)) -> 5584
B10: Water charges 1% | G10: =G9*1% -> 55.84
B11: Total | G11: =SUM(G9:G10) -> 5639.84
B12: CPOH 15% | G12: =G11*15% -> 845.976
B13: Total | G13: =round(SUM(G11:G12),2) -> 6485.82
A14: =CONCATENATE("Say ₹ ",G13," x Cost Index") -> Say ₹ 6485.82 x Cost Index | H14: 0 | I14: =G13 -> 6485.82

Sheet HP Repair Spares
A1: GROUND WATER DEPARTMENT | E1: =B7 -> Head Assembly complete (with Head, Handle, Ball Bearings and Chain Assembly) | F1: =C7 -> 4800 | G1: =D7 -> 0
A2: REVISED RATES 2021 FOR REPAIR AND SPARE PARTS OF INDIA MARK II | E2: =B8 -> Head with welded components only without cover | F2: =C8 -> 2280 | G2: =D8 -> 0
A3: DEEP WELL HAND PUMPS CONFIRMING TO IS: 15500 (Part II) 2004 | E3: =B9 -> Handle (welded components only) | F3: =C9 -> 1800 | G3: =D9 -> 0
A4: (MR) | E4: =B10 -> Additional Plate | F4: =C10 -> 450 | G4: =D10 -> 0
A5: Price list for Spare Parts | E5: =B13 -> Ball Bearing 6204 Z | F5: =C13 -> 216 | G5: =D13 -> 0
A6: Conversion Head Assembly | E6: =B14 -> Chain with coupling | F6: =C14 -> 240 | G6: =D14 -> 0
A7: 1 | B7: Head Assembly complete (with Head, Handle, Ball Bearings and Chain Assembly) | C7: 4800 | D7: 0 | E7: =B15 -> Spacer for Axle Pin | F7: =C15 -> 24 | G7: =D15 -> 0
A8: 2 | B8: Head with welded components only without cover | C8: 2280 | D8: 0 | E8: =B16 -> M 12 x 20 Hex Bolt for Top Head Cover | F8: =C16 -> 18 | G8: =D16 -> 0
A9: 3 | B9: Handle (welded components only) | C9: 1800 | D9: 0 | E9: =B17 -> M 12 x 40 Hex Bolt | F9: =C17 -> 18 | G9: =D17 -> 0
A10: 4 | B10: Additional Plate | C10: 450 | D10: 0 | E10: =B18 -> M 12 Nut | F10: =C18 -> 12 | G10: =D18 -> 0
A11: 5 | B11: Front Cover | C11: 300 | D11: 0 | E11: =B19 -> M.12 Washer | F11: =C19 -> 12 | G11: =D19 -> 0
A12: 6 | B12: Axle (Stainless Steel) | C12: 228 | D12: 0 | E12: =B20 -> M 10 x 40 H.T Bolt | F12: =C20 -> 18 | G12: =D20 -> 0
A13: 7 | B13: Ball Bearing 6204 Z | C13: 216 | D13: 0 | E13: =B21 -> M.10 Nylon Nut | F13: =C21 -> 12 | G13: =D21 -> 0
A14: 8 | B14: Chain with coupling | C14: 240 | D14: 0 | E14: =B22 -> Special Washer for Axle | F14: =C22 -> 12 | G14: =D22 -> 0
A15: 9 | B15: Spacer for Axle Pin | C15: 24 | D15: 0 | E15: =B24 -> Cylinder Assembly Complete | F15: =C24 -> 3000 | G15: =D24 -> 0
A16: 10 | B16: M 12 x 20 Hex Bolt for Top Head Cover | C16: 18 | D16: 0 | E16: =B25 -> C.I.Cylinder Body with liner | F16: =C25 -> 1080 | G16: =D25 -> 0
A17: 11 | B17: M 12 x 40 Hex Bolt | C17: 18 | D17: 0 | E17: =B26 -> Plunger Rod S.S | F17: =C26 -> 216 | G17: =D26 -> 0
A18: 12 | B18: M 12 Nut | C18: 12 | D18: 0 | E18: =B27 -> Reducer cap | F18: =C27 -> 156 | G18: =D27 -> 0
A19: 13 | B19: M.12 Washer | C19: 12 | D19: 0 | E19: =B28 -> Plunger Yoke body | F19: =C28 -> 288 | G19: =D28 -> 0
A20: 14 | B20: M 10 x 40 H.T Bolt | C20: 18 | D20: 0 | E20: =B29 -> Spacer | F20: =C29 -> 228 | G20: =D29 -> 0
A21: 15 | B21: M.10 Nylon Nut | C21: 12 | D21: 0 | E21: =B30 -> Follower | F21: =C30 -> 252 | G21: =D30 -> 0
A22: 16 | B22: Special Washer for Axle | C22: 12 | D22: 0 | E22: =B31 -> Upper Valve ( one piece) | F22: =C31 -> 90 | G22: =D31 -> 0
A23: Cylinder Assembly | E23: =B32 -> Check valve guide | F23: =C32 -> 120 | G23: =D32 -> 0
A24: 1 | B24: Cylinder Assembly Complete | C24: 3000 | D24: 0 | E24: =B33 -> Check valve seat | F24: =C33 -> 192 | G24: =D33 -> 0
A25: 2 | B25: C.I.Cylinder Body with liner | C25: 1080 | D25: 0 | E25: =B34 -> Rubber seat Retainer | F25: =C34 -> 96 | G25: =D34 -> 0
A26: 3 | B26: Plunger Rod S.S | C26: 216 | D26: 0 | E26: =B35 -> Sealing ring (Nitrile Rubber) | F26: =C35 -> 18 | G26: =D35 -> 0
A27: 4 | B27: Reducer cap | C27: 156 | D27: 0 | E27: =B36 -> Rubber seating upper valve | F27: =C36 -> 12 | G27: =D36 -> 0
A28: 5 | B28: Plunger Yoke body | C28: 288 | D28: 0 | E28: =B37 -> Rubber seating check valve | F28: =C37 -> 12 | G28: =D37 -> 0
A29: 6 | B29: Spacer | C29: 228 | D29: 0 | E29: =B38 -> Pump Bucket (Nitrile Rubber) | F29: =C38 -> 30 | G29: =D38 -> 0
A30: 7 | B30: Follower | C30: 252 | D30: 0 | E30: =B39 -> Upper valve Assembly comprising of SS Plunger rod, Plunger Yoke body, 2 spacer & 2 bucket washers | F30: =C39 -> 1200 | G30: =D39 -> 0
A31: 8 | B31: Upper Valve ( one piece) | C31: 90 | D31: 0 | E31: =B40 -> Same as above but without plunger rod | F31: =C40 -> 1080 | G31: =D40 -> 0
A32: 9 | B32: Check valve guide | C32: 120 | D32: 0 | E32: =B41 -> Lower Valve Assembly comprising of Rubber Seat Retainer, Check valve guide and rubber seating | F32: =C41 -> 540 | G32: =D41 -> 0
A33: 10 | B33: Check valve seat | C33: 192 | D33: 0 | E33: =B43 -> Water Tank | F33: =C43 -> 1800 | G33: =D43 -> 0
A34: 11 | B34: Rubber seat Retainer | C34: 96 | D34: 0 | E34: =B44 -> Pipe Sockets | F34: =C44 -> 120 | G34: =D44 -> 0
A35: 12 | B35: Sealing ring (Nitrile Rubber) | C35: 18 | D35: 0 | E35: =B46 -> Pedestal (Ordinary) | F35: =C46 -> 3120 | G35: =D46 -> 0
A36: 13 | B36: Rubber seating upper valve | C36: 12 | D36: 0 | E36: =B48 -> 12 mm dia x 3 m electro galvanized | F36: =C48 -> 336 | G36: =D48 -> 0
A37: 14 | B37: Rubber seating check valve | C37: 12 | D37: 0 | E37: =B49 -> Hex. Coupler 12 x 50 mm | F37: =C49 -> 30 | G37: =D49 -> 0
A38: 15 | B38: Pump Bucket (Nitrile Rubber) | C38: 30 | D38: 0 | E38: =B50 -> Hex. Coupler 12 x 20 mm | F38: =C50 -> 24 | G38: =D50 -> 0
A39: 16 | B39: Upper valve Assembly comprising of SS Plunger rod, Plunger Yoke body, 2 spacer & 2 bucket washers | C39: 1200 | D39: 0 | E39: =B52 -> GI Riser pipe (B class) 3 m long 32mm bore size both end threaded with one end socket (Code: 1548 - Including Water Charge and CPOH) | F39: =C52 -> 0 | G39: =D52 -> 784.02
A40: 17 | B40: Same as above but without plunger rod | C40: 1080 | D40: 0 | E40: =B54 -> Cylinder Extra deep well hand pump | F40: =C54 -> 4320 | G40: =D54 -> 0
A41: 18 | B41: Lower Valve Assembly comprising of Rubber Seat Retainer, Check valve guide and rubber seating | C41: 540 | D41: 0 | E41: =B55 -> Head Assembly for extra deep well pump with T | F41: =C55 -> 7200 | G41: =D55 -> 0
A42: Water Tank | E42: =B57 -> ISI marked India Mark II (Standard) Deep well hand pumps confirming to IS: 15500 (Part II) 2004 complete with 10 Nos. GI pipe (B class) 3m long 32mm bore both end threaded with one end socket and 10 Nos connecting rods | F42: =C57 -> 31000 | G42: =D57 -> 0
A43: 1 | B43: Water Tank | C43: 1800 | D43: 0 | E43: =B58 -> ISI marked India Mark II (Standard) Extra Deep well hand pumps confirming to IS: 15500 (Part II) 2004 complete with 20 Nos. GI pipe (B class) 3m long 32mm bore both end threaded with one end socket and 20 Nos connecting rods | F43: =C58 -> 49000 | G43: =D58 -> 0
A44: 2 | B44: Pipe Sockets | C44: 120 | D44: 0 | E44: =B59
A45: Pedestal | E45: =B60
A46: 1 | B46: Pedestal (Ordinary) | C46: 3120 | D46: 0 | E46: =B61
A47: Connecting Rods | E47: =B62
A48: 1 | B48: 12 mm dia x 3 m electro galvanized | C48: 336 | D48: 0 | E48: =B63
A49: 2 | B49: Hex. Coupler 12 x 50 mm | C49: 30 | D49: 0 | E49: =B64
A50: 3 | B50: Hex. Coupler 12 x 20 mm | C50: 24 | D50: 0 | E50: =B65
A51: Riser Pipe | E51: =B66
A52: 1 | B52: GI Riser pipe (B class) 3 m long 32mm bore size both end threaded with one end socket (Code: 1548 - Including Water Charge and CPOH) | C52: 0 | D52: =261.34*3 -> 784.02
A53: Additional Spares
A54: 1 | B54: Cylinder Extra deep well hand pump | C54: 4320 | D54: 0
A55: 2 | B55: Head Assembly for extra deep well pump with T | C55: 7200 | D55: 0
A56: New Hand Pump Rate
A57: 1 | B57: ISI marked India Mark II (Standard) Deep well hand pumps confirming to IS: 15500 (Part II) 2004 complete with 10 Nos. GI pipe (B class) 3m long 32mm bore both end threaded with one end socket and 10 Nos connecting rods | C57: 31000 | D57: 0
A58: 2 | B58: ISI marked India Mark II (Standard) Extra Deep well hand pumps confirming to IS: 15500 (Part II) 2004 complete with 20 Nos. GI pipe (B class) 3m long 32mm bore both end threaded with one end socket and 20 Nos connecting rods | C58: 49000 | D58: 0

Sheet Hydrants
A1: Hydrants with tap (for common use of size 0.8 x 0.5 m platform) | H1: Code
A2: 1 | B2: 110 mm 4kg/cm2 PVC Pipe (MR55) | C2: 110 | D2: cm | E2: 170 | F2: /m | G2: =C2*E2/100 -> 187
A3: 2 | B3: 32mm 10kg/cm2 PVC Pipe (MR44) | C3: 150 | D3: cm | E3: 65 | F3: /m | G3: =C3*E3/100 -> 97.5
A4: 3 | B4: PVC tap | C4: 1 | D4: No | E4: {=IFERROR(INDEX(LMRRates,MATCH(H4,LMRCodes,0), ), )} -> 64 | F4: /E | G4: =C4*E4 -> 64 | H4: MR10048
A5: 4 | B5: 25mm GI Nipple | C5: 1 | D5: No | E5: 40 | F5: /E | G5: =C5*E5 -> 40
A6: 5 | B6: 25mm GI elbow | C6: 2 | D6: No | E6: 45 | F6: /E | G6: =C6*E6 -> 90
A7: 6 | B7: ¾" X ½" GI Reducer | C7: 1 | D7: No | E7: 45 | F7: /E | G7: =C7*E7 -> 45
A8: 7 | B8: 1" X ¾" GI Reducer | C8: 1 | D8: No | E8: 55 | F8: /E | G8: =C8*E8 -> 55
B9: Sub Total | G9: =SUM(G2:G8) -> 578.5
B10: Water charges 1% | G10: =G9*0.01 -> 5.785
B11: Total | G11: =SUM(G9:G10) -> 584.285
B12: CPOH 15% | G12: =G11*15% -> 87.64275
B13: Total | G13: =round(SUM(G11:G12),2) -> 671.93
A14: 8 | B14: Earth work excavation as per DSR item 2.8.1 | C14: 0.1 | D14: m3 | E14: 249.03 | F14: /m3 | G14: =C14*E14 -> 24.903
A15: 9 | B15: Cement concrete 1:2:4, 20mm with nominal size graded stone, for filling the PVC Pipe and platform construction as per DSR item 4.1.3 | C15: 0.146 | D15: m3 | E15: 6393.89 | F15: /m3 | G15: =C15*E15 -> 933.50794
A16: 10 | B16: Form work as per DSR item 5.9.1 | C16: =2*(0.8+0.5)*0.1 -> 0.26 | D16: m2 | E16: 267.33 | F16: /m2 | G16: =C16*E16 -> 69.5058
A17: 11 | B17: Plastering with CM 1:4 12cm thick with for platform base as per DSR item 13.1.1 | C17: =0.8*0.5+C16 -> 0.66 | D17: m2 | E17: 255.98 | F17: /m2 | G17: =C17*E17 -> 168.9468
A18: 12 | B18: Labour charge for Hydrants for all fittings Fitter (0116) | C18: 0.22 | D18: day | E18: 784 | F18: /day | G18: =C18*E18 -> 172.48
B19: Beldar (0114) | C19: 0.22 | D19: day | E19: 645 | F19: /day | G19: =C19*E19 -> 141.9
B20: Sub Total | G20: =SUM(G18:G19) -> 314.38
B21: Water charges 1% | G21: =G20*0.01 -> 3.1438
B22: Total | G22: =SUM(G20:G21) -> 317.5238
B23: CPOH 15% | G23: =G22*15% -> 47.62857
B24: Total for labour | G24: =SUM(G22:G23) -> 365.15237
B25: Total | G25: =round(G14+G15+G16+G17+G24,2) -> 1562.02
A26: =CONCATENATE("Say ₹ ",G13," + ",G25," x Cost Index") -> Say ₹ 671.93 + 1562.02 x Cost Index
A27: Hydrants with tap ( for individual families of size 0.6 X 0.3 M platform)
A28: 1 | B28: 110 mm 4kg/cm2 PVC Pipe (MR55) | C28: 110 | D28: cm | E28: 170 | F28: /m | G28: =C28*E28/100 -> 187
A29: 2 | B29: 32mm 10kg/cm2 PVC Pipe (MR44) | C29: 150 | D29: cm | E29: 65 | F29: /m | G29: =C29*E29/100 -> 97.5
A30: 3 | B30: PVC tap | C30: 1 | D30: No | E30: {=IFERROR(INDEX(LMRRates,MATCH(H30,LMRCodes,0), ), )} -> 64 | F30: /E | G30: =C30*E30 -> 64 | H30: MR10048
A31: 4 | B31: 25mm GI Nipple | C31: 1 | D31: No | E31: 40 | F31: /E | G31: =C31*E31 -> 40
A32: 5 | B32: 25mm GI elbow | C32: 2 | D32: Nos | E32: 45 | F32: /E | G32: =C32*E32 -> 90
A33: 6 | B33: ¾" X ½" GI Reducer | C33: 1 | D33: No | E33: 45 | F33: /E | G33: =C33*E33 -> 45
A34: 7 | B34: 1" X ¾" GI Reducer | C34: 1 | E34: 55 | F34: /E | G34: =C34*E34 -> 55
B35: Sub Total | G35: =SUM(G28:G34) -> 578.5
B36: Water charges 1% | G36: =G35*0.01 -> 5.785
B37: Total | G37: =SUM(G35:G36) -> 584.285
B38: CPOH 15% | G38: =G37*15% -> 87.64275
B39: Total | G39: =round(SUM(G37:G38),2) -> 671.93
A40: 8 | B40: Earth work excavation as per DSR item 2.8.1 | C40: 0.054 | D40: m3 | E40: 249.03 | F40: /m3 | G40: =C40*E40 -> 13.44762
A41: 9 | B41: Cement concrete 1:2:4, 20mm with nominal size graded stone, for filling the PVC Pipe and platform construction as per DSR item 4.1.3 | C41: 0.08 | D41: m3 | E41: 6393.89 | F41: /m3 | G41: =C41*E41 -> 511.5112
A42: 10 | B42: Form work as per DSR item 5.9.1 | C42: 0.18 | D42: m2 | E42: 267.33 | F42: /m2 | G42: =C42*E42 -> 48.1194
A43: 11 | B43: Plastering with CM 1:4 12cm thick with for platform base as per DSR item 13.1.1 | C43: 0.36 | D43: m2 | E43: 255.98 | F43: /m2 | G43: =C43*E43 -> 92.1528
A44: 12 | B44: Labour charge for Hydrants for all fittings Fitter (0116) | C44: 0.22 | D44: Nos | E44: 784 | F44: /E | G44: =C44*E44 -> 172.48
B45: Beldar (0114) | C45: 0.22 | D45: Nos | E45: 645 | F45: /E | G45: =C45*E45 -> 141.9
B46: Sub Total | G46: =SUM(G44:G45) -> 314.38
B47: Water charges 1% | G47: =G46*0.01 -> 3.1438
B48: Total | G48: =SUM(G46:G47) -> 317.5238
B49: CPOH 15% | G49: =G48*15% -> 47.62857
B50: Total for labour | G50: =SUM(G48:G49) -> 365.15237
B51: Total | G51: =round(G40+G41+G42+G43+G50,2) -> 1030.38
A52: =CONCATENATE("Say ₹ ",G39," + ",G51," x Cost Index") -> Say ₹ 671.93 + 1030.38 x Cost Index

Sheet Iron Structure
A1: Angle Iron Structure To Support 5000 Litres Capacity Water Tank At 4 m Height
A2: 1 | B2: Quantity of angle iron, flats, M.S. sheets etc
B3: Item | G3: No. | H3: L | I3: Unit | J3: Total
B4: Columns | C4: 752 x 6 | G4: 4 | H4: 4.6 | I4: m | J4: =G4*H4 -> 18.4
B5: Columns (extra in foundation) | C5: 752 x 6 | G5: 4 | H5: 0.9 | I5: m | J5: =G5*H5 -> 3.6
B6: Horizontal bracing (1st portion) | C6: 502 x 6 | G6: 4 | H6: 2.6 | I6: m | J6: =G6*H6 -> 10.4
B7: Horizontal bracing (2nd portion) | C7: 502 x 6 | G7: 4 | H7: 2.4 | I7: m | J7: =G7*H7 -> 9.6
B8: Horizontal bracing (3rd portion) | C8: 502 x 6 | G8: 4 | H8: 2.3 | I8: m | J8: =G8*H8 -> 9.2
B9: Diagonal bracing (1st portion) | C9: 352 x 5 | G9: 8 | H9: 2.9 | I9: m | J9: =G9*H9 -> 23.2
B10: Diagonal bracing (2nd portion) | C10: 352 x 5 | G10: 8 | H10: 2.8 | I10: m | J10: =G10*H10 -> 22.4
B11: Vertical bracing (top section) | C11: 502 x 6 | G11: 8 | H11: 0.5 | I11: m | J11: =G11*H11 -> 4
B12: Platform
B13: Top bracing | C13: 752 x 6 | G13: 4 | H13: 2.2 | I13: m | J13: =G13*H13 -> 8.8
B14: Cross bracing (Top Middle) | C14: 502 x 6 | G14: 6 | H14: 2.2 | I14: m | J14: =G14*H14 -> 13.2
B15: Platform Parapet
B16: Vertical post | C16: 252 x 5 | G16: 16 | H16: 0.9 | I16: m | J16: =G16*H16 -> 14.4
B17: Horizontal post | C17: 352 x 5 | G17: 4 | H17: 2.2 | I17: m | J17: =G17*H17 -> 8.8
B18: Ladder
B19: Ladder Post (flat) | C19: 35 x 6 | G19: 2 | H19: 4.4 | I19: m | J19: =G19*H19 -> 8.8
B20: Ladder steps | C20: 35 x 6 | G20: 12 | H20: 0.3 | I20: m | J20: =G20*H20 -> 3.6
B21: M. S. Sheet 16 gauge thick | G21: 2.2 | H21: 2.2 | I21: m2 | J21: =G21*H21 -> 4.84
B22: M. S. plate 15 mm thick | C22: 4 | G22: 0.3 | H22: 0.3 | I22: m2 | J22: =G22*H22*C22 -> 0.36
B24: Abstract | G24: L | H24: Weight | I24: Unit | J24: Total (Kg)
B25: M. S. Angles | C25: 752 x 6 | G25: 30.8 | H25: 6.8 | I25: Kg/m | J25: =G25*H25 -> 209.44
B26: M. S. Angles | C26: 502 x 6 | G26: 46.4 | H26: 4.5 | I26: Kg/m | J26: =G26*H26 -> 208.8
B27: M. S. Angles | C27: 352 x 5 | G27: 54.4 | H27: 2.6 | I27: Kg/m | J27: =G27*H27 -> 141.44
B28: M. S. Angles | C28: 252 x 5 | G28: 14.4 | H28: 1.8 | I28: Kg/m | J28: =G28*H28 -> 25.92
B29: M. S. Flats | C29: 35 x 6 | G29: 12.4 | H29: 1.68 | I29: Kg/m | J29: =G29*H29 -> 20.832
B30: Sub Total | J30: =SUM(J25:J29) -> 606.432
B31: M. S. Sheet 16 gauge thick | G31: 4.84 | H31: 12.56 | I31: Kg/m2 | J31: =G31*H31 -> 60.7904
B32: M. S. plate 15 mm thick | G32: 0.36 | H32: 117.8 | I32: Kg/m2 | J32: =G32*H32 -> 42.408
B33: Total | J33: =SUM(J30:J32) -> 709.6304
B34: Description of work | C34: No | D34: L | E34: B | F34: H | G34: Quantity | H34: Rate | I34: Unit | J34: Amount
A35: 2 | B35: Structural steel work including wastage, cutting, hoisting, fixing in position and applying a priming coat of approved steel primer all complete as per DSR 10.1 | G35: =J33 -> 709.6304 | H35: 80.78 | I35: /Kg | J35: =G35*H35 -> 57323.944
A36: 3 | B36: Providing and fixing bolts including nuts and washers complete as per DSR item 10.20 | G36: 4 | H36: 121.67 | I36: /Kg | J36: =G36*H36 -> 486.68
A37: 4 | B37: Earth work in excavation by mechanical means (Hydraulic excavator) / manual means in foundation trenches or drains (not exceeding 1.5 m in width or 10 sqm on plan), including dressing of sides and ramming of bottoms, lift up to 1.5 m, including getting out the excavated soil and disposal of surplus excavated soil as directed, within a lead of 50 m as per DSR item 2.8.1 | C37: 4 | D37: 0.75 | E37: 0.75 | F37: 1 | G37: =C37*D37*E37*F37 -> 2.25 | H37: 249.03 | I37: /m3 | J37: =G37*H37 -> 560.3175
A38: 5 | B38: Providing and laying in position cement concrete of specified grade excluding the cost of centering and shuttering - All work up to plinth level: 1:2:4 as per DSR item 4.1.3 | C38: 4 | D38: 0.75 | E38: 0.75 | F38: 0.4 | G38: =C38*D38*E38*F38 -> 0.9
C39: 4 | D39: 0.6 | E39: 0.6 | F39: 0.7 | G39: =C39*D39*E39*F39 -> 1.008
C40: Total | G40: =SUM(G38:G39) -> 1.908 | H40: 6393.89 | I40: /m3 | J40: =G40*H40 -> 12199.542
A41: 6 | B41: Unforeseen items | J41: 429.52
A42: 7 | B42: Total | J42: =SUM(J35:J41) -> 71000.003
A43: 8 | B43: Say Rs. 71000 x Index
A44: Angle Iron Structure To Support 3000 Litres Capacity Water Tank At 4 m Height
A45: 1 | B45: Quantity of angle iron, flats, M.S. sheets etc
B46: Item | G46: No. | H46: L | I46: Unit | J46: Total
B47: Columns | C47: 652 x 6 | G47: 4 | H47: 4.6 | I47: m | J47: 18.4
B48: Columns (extra in foundation) | C48: 652 x 6 | G48: 4 | H48: 0.9 | I48: m | J48: 3.6
B49: Horizontal bracing (1st portion) | C49: 502 x 6 | G49: 4 | H49: 2.2 | I49: m | J49: 8.8
B50: Horizontal bracing (2nd portion) | C50: 502 x 6 | G50: 4 | H50: 2 | I50: m | J50: 8
B51: Horizontal bracing (3rd portion) | C51: 502 x 6 | G51: 4 | H51: 1.8 | I51: m | J51: 7.2
B52: Diagonal bracing (1st portion) | C52: 352 x 5 | G52: 8 | H52: 2.6 | I52: m | J52: 20.8
B53: Diagonal bracing (2nd portion) | C53: 352 x 5 | G53: 8 | H53: 2.4 | I53: m | J53: 19.2
B54: Vertical bracing (top section) | C54: 352 x 5 | G54: 8 | H54: 0.5 | I54: m | J54: 4
B55: Platform
B56: Top bracing | C56: 652 x 6 | G56: 4 | H56: 1.8 | I56: m | J56: 7.2
B57: Cross bracing (Top Middle) | C57: 502 x 6 | G57: 6 | H57: 1.8 | I57: m | J57: 10.8
B58: Platform Parapet
B59: Vertical post | C59: 252 x 5 | G59: 16 | H59: 0.9 | I59: m | J59: 14.4
B60: Horizontal post | C60: 352 x 5 | G60: 4 | H60: 1.8 | I60: m | J60: 7.2
B61: Ladder
B62: Ladder Post (flat) | C62: 35 x 6 | G62: 2 | H62: 4.7 | I62: m | J62: 9.4
B63: Ladder steps | C63: 35 x 6 | G63: 12 | H63: 0.3 | I63: m | J63: 3.6
B64: M. S. Sheet 16 gauge thick | G64: 1.8 | H64: 1.8 | I64: m2 | J64: 3.24
B65: M. S. plate 15 mm thick | C65: 4 | G65: 0.3 | H65: 0.3 | I65: m2 | J65: 0.36
B67: Abstract | G67: L | H67: Weight | I67: Unit | J67: Total (Kg)
B68: M. S. Angles | C68: 652 x 6 | G68: 29.2 | H68: 5.8 | I68: Kg/m | J68: 169.36
B69: M. S. Angles | C69: 502 x 6 | G69: 34.8 | H69: 4.5 | I69: Kg/m | J69: 156.6
B70: M. S. Angles | C70: 352 x 5 | G70: 51.2 | H70: 2.6 | I70: Kg/m | J70: 133.12
B71: M. S. Angles | C71: 252 x 5 | G71: 14.4 | H71: 1.8 | I71: Kg/m | J71: 25.92
B72: M. S. Flats | C72: 35 x 6 | G72: 13 | H72: 1.68 | I72: Kg/m | J72: 21.84
B73: Sub Total | J73: 506.84
B74: M. S. Sheet 16 gauge thick | G74: 3.24 | H74: 12.56 | I74: Kg/m2 | J74: 40.69
B75: M. S. plate 15 mm thick | G75: 0.36 | H75: 117.8 | I75: Kg/m2 | J75: 42.41
B76: Total | J76: 589.94
B77: Description of work | C77: No | D77: L | E77: B | F77: H | G77: Quantity | H77: Rate | I77: Unit | J77: Amount
A78: 2 | B78: Structural steel work including wastage, cutting, hoisting, fixing in position and applying a priming coat of approved steel primer all complete as per DSR 10.1 | G78: 589.94 | H78: 80.78 | I78: /Kg | J78: 47655.55
A79: 3 | B79: Providing and fixing bolts including nuts and washers complete as per DSR item 10.20 | G79: 3 | H79: 121.67 | I79: /Kg | J79: 365.01
A80: 4 | B80: Earth work in excavation by mechanical means (Hydraulic excavator) / manual means in foundation trenches or drains (not exceeding 1.5 m in width or 10 sqm on plan), including dressing of sides and ramming of bottoms, lift up to 1.5 m, including getting out the excavated soil and disposal of surplus excavated soil as directed, within a lead of 50 m as per DSR item 2.8.1 | C80: 4 | D80: 0.75 | E80: 0.75 | F80: 1 | G80: 2.25 | H80: 249.03 | I80: /m3 | J80: 560.32
A81: 5 | B81: Providing and laying in position cement concrete of specified grade excluding the cost of centering and shuttering - All work up to plinth level: 1:2:4 as per DSR item 4.1.3 | C81: 4 | D81: 0.75 | E81: 0.75 | F81: 0.4 | G81: 0.9
C82: 4 | D82: 0.6 | E82: 0.6 | F82: 0.7 | G82: 1.008
C83: Total | G83: 1.908 | H83: 6393.89 | I83: /m3 | J83: 12199.54
A84: 6 | B84: Unforeseen items | J84: 1219.58
A85: 7 | B85: Total | J85: 62000
A86: 8 | B86: Say Rs. 62000 x Index
A87: Angle Iron Structure To Support 5000 Litres Capacity Water Tank At 6 m Height
A88: 1 | B88: Quantity of angle iron, flats, M.S. sheets etc
B89: Item | G89: No. | H89: L | I89: Unit | J89: Total
B90: Columns | C90: 752 x 6 | G90: 4 | H90: 7 | I90: m | J90: =G90*H90 -> 28
B91: Columns (extra in foundation) | C91: 752 x 6 | G91: 4 | H91: 0.9 | I91: m | J91: =G91*H91 -> 3.6
B92: Horizontal bracing (1st portion) | C92: 502 x 6 | G92: 4 | H92: 2.8 | I92: m | J92: =G92*H92 -> 11.2
B93: Horizontal bracing (2nd portion) | C93: 502 x 6 | G93: 4 | H93: 2.6 | I93: m | J93: =G93*H93 -> 10.4
B94: Horizontal bracing (3rd portion) | C94: 502 x 6 | G94: 4 | H94: 2.5 | I94: m | J94: =G94*H94 -> 10
B95: Horizontal bracing (4th portion) | C95: 502 x 6 | G95: 4 | H95: 2.3 | I95: m | J95: =G95*H95 -> 9.2
B96: Diagonal bracing (1st portion) | C96: 352 x 5 | G96: 8 | H96: 3.1 | I96: m | J96: =G96*H96 -> 24.8
B97: Diagonal bracing (2nd portion) | C97: 352 x 5 | G97: 8 | H97: 2.9 | I97: m | J97: =G97*H97 -> 23.2
B98: Diagonal bracing (3rd portion) | C98: 352 x 5 | G98: 8 | H98: 2.8 | I98: m | J98: =G98*H98 -> 22.4
B99: Vertical bracing (top section) | C99: 502 x 6 | G99: 8 | H99: 1 | I99: m | J99: =G99*H99 -> 8
B100: Platform
B101: Top bracing | C101: 752 x 6 | G101: 4 | H101: 2.2 | I101: m | J101: =G101*H101 -> 8.8
B102: Cross bracing (Top Middle) | C102: 502 x 6 | G102: 6 | H102: 2.2 | I102: m | J102: =G102*H102 -> 13.2
...

Sheet Lock
A1: Locking Arrangements - Supplying and Fixing lock and locking arrangements with suitable chain hooks,and padlock of 65mm size. (60.4)
B2: Header Unit | C2: each | D2: Header Quantity | E2: 1
A3: Header Details
A4: Material
B5: MR302 | C5: Hooks for locking arrangements
C6: each | D6: 1 | E6: 70 | F6: =D6*E6 -> 70
B7: MR303 | C7: Chain for locking arrangemet
C8: metre | D8: 3.5 | E8: 72 | F8: =D8*E8 -> 252
B9: MR304 | C9: Padlock 65mm
C10: each | D10: 1 | E10: 230 | F10: =D10*E10 -> 230
A11: TOTAL (Material) | D11: 1 | E11: no | F11: =F10+F8+F6 -> 552
A12: UNIT TOTAL | D12: 1 | E12: no | F12: =F11 -> 552
A13: Water Charge@ 1.00 % | F13: =F12*1% -> 5.52
A14: TOTAL | F14: =F12+F13 -> 557.52
A15: Contractors Profit & Overhead@ 15.00 % | F15: =F14*15% -> 83.628
A16: TOTAL | F16: =round(F14+F15,2) -> 641.15
A17: Labour
A18: 112 | C18: Carpenter 2nd class
C19: Day | D19: 0.25 | E19: 714 | F19: =D19*E19 -> 178.5
A20: TOTAL | D20: 1 | E20: each | F20: =F19 -> 178.5
A21: UNIT TOTAL | D21: 1 | E21: each | F21: =F20/1 -> 178.5
A22: Water Charge@ 1.00 % | E22: =F21 -> 178.5 | F22: =E22*1% -> 1.785
A23: TOTAL | F23: =SUM(F21:F22) -> 180.285
A24: Contractors Profit & Overhead@ 15.00 % | E24: =F23 -> 180.285 | F24: =E24*15% -> 27.04275
A25: TOTAL | F25: =SUM(F23:F24) -> 207.32775
A26: =CONCATENATE("Say ₹ ",F16," + ",F25," x Cost Index") -> Say ₹ 641.15 + 207.32775 x Cost Index | G26: =F16 -> 641.15 | H26: =F25 -> 207.32775

Sheet Metallic PH
A1: Metallic Pump House of size 1.2 x 0.9 x 2 m
A2: Sl. No. | B2: Item | C2: No. | D2: L | E2: B | F2: D | G2: Total | H2: Unit | I2: Rate | J2: Amount
A3: 1 | B3: Surface dressing of the ground including removing vegetation and in-equalities not exceeding 15 cm deep and disposal of rubbish, lead up to 50 m and lift up to 1.5 m. All kinds of soil as per DSR item 2.28.1
B4: Area | C4: 1 | D4: 2 | E4: 1.5 | G4: =PRODUCT(C4:F4) -> 3
B5: Total | G5: =SUM(G4) -> 3 | H5: m2 | I5: 24.43 | J5: =G5*I5 -> 73.29
A6: 2 | B6: Earth work in excavation by mechanical means (Hydraulic excavator) / manual means in foundation trenches or drains (not exceeding 1.5 m in width or 10 sqm on plan), including dressing of sides and ramming of bottoms, lift up to 1.5 m, including getting out the excavated soil and disposal of surplus excavated soil as directed, within a lead of 50 m. as per DSR item 2.8.1
B7: Foundation | C7: 1 | D7: =2*(1.2+0.9) -> 4.2 | E7: 0.3 | F7: 0.3 | G7: =PRODUCT(C7:F7) -> 0.378
B8: Step | C8: 1 | D8: 0.5 | E8: 0.3 | F8: 0.2 | G8: =PRODUCT(C8:F8) -> 0.03
B9: Total | G9: =SUM(G7:G8) -> 0.408 | H9: m3 | I9: 249.04 | J9: =G9*I9 -> 101.60832
A10: 3 | B10: Providing and laying in position cement concrete of specified grade excluding the cost of centering and shuttering - All work up to plinth level: 1:4:8 as per DSR item 4.1.8
B11: Foundation | C11: 1 | D11: =D7 -> 4.2 | E11: =E7 -> 0.3 | F11: 0.1 | G11: =PRODUCT(C11:F11) -> 0.126
B12: Step | C12: 1 | D12: =D8 -> 0.5 | E12: =E8 -> 0.3 | F12: 0.1 | G12: =PRODUCT(C12:F12) -> 0.015
B13: Total | G13: =SUM(G11:G12) -> 0.141 | H13: m3 | I13: 5491.79 | J13: =G13*I13 -> 774.34239
A14: 4 | B14: Coursed rubble masonry (first sort) with hard stone in foundation and plinth with Cement mortar 1:6 as per DSR item 7.6.1
B15: Foundation & Basement | C15: 1 | D15: =D11 -> 4.2 | E15: =E11 -> 0.3 | F15: =0.2+0.3 -> 0.5 | G15: =PRODUCT(C15:F15) -> 0.63
B16: Step | C16: 1 | D16: =D12 -> 0.5 | E16: =E12 -> 0.3 | F16: =0.1+0.15 -> 0.25 | G16: =PRODUCT(C16:F16) -> 0.0375
B17: Total | G17: =SUM(G15:G16) -> 0.6675 | H17: m3 | I17: 6870.79 | J17: =G17*I17 -> 4586.2523
A18: 5 | B18: 12 mm cement plaster of mix 1:4 as per DSR item 13.1.1
B19: Outside | C19: 1 | D19: =2*(1.2+0.3+0.9+0.3) -> 5.4 | G19: =PRODUCT(C19:F19) -> 5.4
B20: Top | C20: 1 | D20: =D15 -> 4.2 | E20: =E15 -> 0.3 | G20: =PRODUCT(C20:F20) -> 1.26
B21: Step sides | C21: 2 | E21: =E12 -> 0.3 | F21: 0.15 | G21: =PRODUCT(C21:F21) -> 0.09
B22: Step top | C22: 1 | D22: =D16 -> 0.5 | E22: =E16 -> 0.3 | G22: =PRODUCT(C22:F22) -> 0.15
B23: Total | G23: =SUM(G19:G22) -> 6.9 | H23: m2 | I23: 255.98 | J23: =G23*I23 -> 1766.262
A24: 6 | B24: Filling available excavated earth (excluding rock) in trenches, plinth, sides of foundations etc. in layers not exceeding 20 cm in depth, consolidating each deposited layer by ramming and watering, lead up to 50 m and lift up to 1.5 m as per DSR item 2.25
B25: Inside Area of Basement | C25: 1 | D25: =1.2-E15 -> 0.9 | E25: =0.9-E15 -> 0.6 | F25: 0.27 | G25: =PRODUCT(C25:F25) -> 0.1458
B26: Total | G26: =SUM(G25) -> 0.1458 | H26: m3 | I26: 220.47 | J26: =G26*I26 -> 32.144526
A27: 7 | B27: Cement concrete flooring 1:2:4 finished with a floating coat of neat cement, including cement slurry complete (40 mm thick with 20 mm nominal size stone aggregate) as per DSR item 11.3.1
B28: Inside Area | C28: 1 | D28: =D25 -> 0.9 | E28: =E25 -> 0.6 | G28: =PRODUCT(C28:F28) -> 0.54
B29: Total | G29: =SUM(G27:G28) -> 0.54 | H29: m2 | I29: 473.11 | J29: =G29*I29 -> 255.4794
A30: 8 | B30: Structural steel work including wastage, cutting, hoisting, fixing in position and applying a priming coat of approved steel primer all complete as per DSR 10.1
B31: MS angle 35 x 35 x 5mm | C31: No. | D31: L | E31: Total L | F31: Weight | G31: Unit | H31: Total Weight | I31: Rate
B32: Front side corner | C32: 2 | D32: 2.1 | E32: =C32*D32 -> 4.2
B33: Back side corner | C33: 2 | D33: 2.3 | E33: =C33*D33 -> 4.6
B34: Top edge front & back | C34: 2 | D34: 1.2 | E34: =C34*D34 -> 2.4
B35: Top edge sides | C35: 2 | D35: 0.9 | E35: =C35*D35 -> 1.8
B36: Door vertical | C36: 2 | D36: 1.8 | E36: =C36*D36 -> 3.6
B37: Door Horizontal | C37: 2 | D37: 0.6 | E37: =C37*D37 -> 1.2
B38: Total Length | E38: =SUM(E32:E37) -> 17.8 | F38: 2.6 | G38: Kg/m | H38: =E38*F38 -> 46.28 | I38: 80.78 | J38: =H38*I38 -> 3738.4984
B39: MS Flat 35 x 6mm
B40: Back side vertical | C40: 2 | D40: 2.3 | E40: =C40*D40 -> 4.6
B41: Back side Horizontal | C41: 2 | D41: 1.2 | E41: =C41*D41 -> 2.4
B42: Front side vertical | C42: 1 | D42: 2.1 | E42: =C42*D42 -> 2.1
B43: Front side Horizontal | C43: 2 | D43: 0.6 | E43: =C43*D43 -> 1.2
B44: side vertical | C44: 2 | D44: 2.2 | E44: =C44*D44 -> 4.4
B45: side Horizontal | C45: 4 | D45: 0.9 | E45: =C45*D45 -> 3.6
B46: Door vertical | C46: 1 | D46: 1.8 | E46: =C46*D46 -> 1.8
B47: Door Horizontal | C47: 2 | D47: 0.6 | E47: =C47*D47 -> 1.2
B48: Roof | C48: 2 | D48: 1.2 | E48: =C48*D48 -> 2.4
C49: 1 | D49: 0.9 | E49: =C49*D49 -> 0.9
B50: Total Length | E50: =SUM(E40:E49) -> 24.6 | F50: 1.68 | G50: Kg/m | H50: =E50*F50 -> 41.328 | I50: 80.78 | J50: =H50*I50 -> 3338.4758
A51: 9 | B51: GI Sheet work including wastage, cutting, hoisting, fixing in position, welding and applying a priming coat of approved steel primer all complete
B52: GI sheet 0.8 mm thick 8019 | C52: L | D52: B
B53: Front side | C53: 1.2 | D53: 2 | E53: =C53*D53 -> 2.4
B54: Back side | C54: 1.2 | D54: 1.8 | E54: =C54*D54 -> 2.16
B55: Sides | C55: 1.8 | D55: 1.9 | E55: =C55*D55 -> 3.42
B56: roof | C56: 1.6 | D56: 1.3 | E56: =C56*D56 -> 2.08
B57: Total Area | E57: =SUM(E53:E56) -> 10.06 | F57: 6.3 | G57: Kg/m2 | H57: =E57*F57 -> 63.378
B58: Total | G58: 63.38 | H58: kg | I58: ='GI Works'!F29 -> 151.03996 | J58: =G58*I58 -> 9572.9125
A59: 10 | B59: Locking arrangements and handles 14.41 | G59: 1 | H59: Nos | I59: 222.08 | J59: =G59*I59 -> 222.08
A60: 11 | B60: Supplying and fixing Hinges for doors 14.40.2 | G60: 3 | H60: Nos | I60: 128.23 | J60: =G60*I60 -> 384.69
A61: 12 | B61: Unforeseen if any | J61: 1153.96
A62: 13 | B62: TOTAL | J62: =SUM(J5:J61) -> 25999.996
A63: 14 | B63: Say Rs.26000 x Cost Index

Sheet Motor Starter GWD
A1: Sor/Spec Code | B1: MR Code | C1: Description | F1: Remarks
C2: Unit | D2: Quantity | E2: Rate (₹) | F2: Amount | G2: Label
A3: S & F Motor starters of the following ratings Submersible pump controllers with ammeter,DPMCB for single phase 2.5HP submersible motor pumps (DOL)
B4: Header Unit | C4: each | D4: Header Quantity | E4: 1
A5: Header Details | B5: COST FOR 1 EACH A1 MATERIALS
A6: Material (M), Labour (L), Additional Charges (A)
B7: D | C7: Submersible pump controllers with ammeter,DPMCB for single phase 2.5HP submersible motor pumps (DOL)
C8: each | D8: 1 | E8: 1850 | F8: =D8*E8 -> 1850 | G8: M1
B9: MR704 | C9: Man Mazdoor
C10: Day | D10: 0.01 | E10: 675 | F10: =D10*E10 -> 6.75 | G10: L2
A11: tcode | C11: Other Charge @ .5% of :(M1+L2) Add Hire charges for T&P @ 0.5%
C12: LS | F12: =(F8+F10)*0.5% -> 9.28375 | G12: A1
A13: TOTAL | D13: 1 | E13: each | F13: =F8+F10+F12 -> 1866.0338
A14: UNIT TOTAL | D14: 1 | E14: each | F14: =F13/D13 -> 1866.0338
A15: Cartage@ 1.00 % (for material) | E15: =F8*100.5%/D13 -> 1859.25 | F15: =E15*1% -> 18.5925
A16: TOTAL | F16: =F14+F15 -> 1884.6263
A17: Contractors Profit & Overhead@ 15.00 % | E17: =F16 -> 1884.6263 | F17: =E17*15% -> 282.69394
A18: TOTAL | F18: =round(F16+F17,2) -> 2167.32
A19: 2852 | C19: Iron screws, 35 mm X 6 mm
C20: each | D20: 4 | E20: 1.8 | F20: =D20*E20 -> 7.2 | G20: M2
A21: 1005 | C21: Fitter, Grade 2
C22: Day | D22: 0.01 | E22: 734 | F22: =D22*E22 -> 7.34 | G22: L1
A23: tcode | C23: Other Charge @ .5% of :(M2+L1) Add Hire charges for T&P @ 0.5%
C24: LS | F24: =(F20+F22)*0.5% -> 0.0727 | G24: A2
A25: TOTAL | D25: 1 | E25: each | F25: =F20+F22+F24 -> 14.6127
A26: UNIT TOTAL | D26: 1 | E26: each | F26: =F25/D25 -> 14.6127
A27: Cartage@ 1.00 % (for material) | E27: =F20*100.5%/D25 -> 7.236 | F27: =E27*1% -> 0.07236
A28: TOTAL | F28: =F26+F27 -> 14.68506
A29: Contractors Profit & Overhead@ 15.00 % | E29: =F28 -> 14.68506 | F29: =E29*15% -> 2.202759
A30: TOTAL | F30: =round(F28+F29,2) -> 16.89
A31: =CONCATENATE("Say ₹ ",F18," + ",F30," x Cost Index") -> Say ₹ 2167.32 + 16.89 x Cost Index | G31: /E | H31: =((F8*1.005*1.01)+(F10*1.005))*1.15 -> 2167.3202 | I31: =((F20*1.005*1.01)+(F22*1.005))*1.15 -> 16.887819
A32: Sor/Spec Code | B32: MR Code | C32: Description | F32: Remarks
C33: Unit | D33: Quantity | E33: Rate (₹) | F33: Amount | G33: Label
A34: S & F Motor starters of the following ratings Submersible pump controllers with ammeter,DPMCB for single phase 3HP submersible motor pumps (DOL)
B35: Header Unit | C35: each | D35: Header Quantity | E35: 1
A36: Header Details | B36: COST FOR 1 EACH A1 MATERIALS
A37: Material (M), Labour (L), Additional Charges (A)
B38: D | C38: Submersible pump controllers with ammeter,DPMCB for single phase 3HP submersible motor pumps (DOL)
C39: each | D39: 1 | E39: 2100 | F39: =D39*E39 -> 2100 | G39: M1
B40: MR704 | C40: Man Mazdoor
C41: Day | D41: 0.01 | E41: 675 | F41: =D41*E41 -> 6.75 | G41: L2
A42: tcode | C42: Other Charge @ .5% of :(M1+L2) Add Hire charges for T&P @ 0.5%
C43: LS | F43: =(F39+F41)*0.5% -> 10.53375 | G43: A1
A44: TOTAL | D44: 1 | E44: each | F44: =F39+F41+F43 -> 2117.2838
A45: UNIT TOTAL | D45: 1 | E45: each | F45: =F44/D44 -> 2117.2838
A46: Cartage@ 1.00 % (for material) | E46: =F39*100.5%/D44 -> 2110.5 | F46: =E46*1% -> 21.105
A47: TOTAL | F47: =F45+F46 -> 2138.3888
A48: Contractors Profit & Overhead@ 15.00 % | E48: =F47 -> 2138.3888 | F48: =E48*15% -> 320.75831
A49: TOTAL | F49: =round(F47+F48,2) -> 2459.15
A50: 2852 | C50: Iron screws, 35 mm X 6 mm
C51: each | D51: 4 | E51: 1.8 | F51: =D51*E51 -> 7.2 | G51: M2
A52: 1005 | C52: Fitter, Grade 2
C53: Day | D53: 0.01 | E53: 734 | F53: =D53*E53 -> 7.34 | G53: L1
A54: tcode | C54: Other Charge @ .5% of :(M2+L1) Add Hire charges for T&P @ 0.5%
C55: LS | F55: =(F51+F53)*0.5% -> 0.0727 | G55: A2
A56: TOTAL | D56: 1 | E56: each | F56: =F51+F53+F55 -> 14.6127
A57: UNIT TOTAL | D57: 1 | E57: each | F57: =F56/D56 -> 14.6127
A58: Cartage@ 1.00 % (for material) | E58: =F51*100.5%/D56 -> 7.236 | F58: =E58*1% -> 0.07236
A59: TOTAL | F59: =F57+F58 -> 14.68506
A60: Contractors Profit & Overhead@ 15.00 % | E60: =F59 -> 14.68506 | F60: =E60*15% -> 2.202759
A61: TOTAL | F61: =round(F59+F60,2) -> 16.89
A62: =CONCATENATE("Say ₹ ",F49," + ",F61," x Cost Index") -> Say ₹ 2459.15 + 16.89 x Cost Index | G62: /E | H62: =((F39*1.005*1.01)+(F41*1.005))*1.15 -> 2459.1471 | I62: =((F51*1.005*1.01)+(F53*1.005))*1.15 -> 16.887819
A63: Sor/Spec Code | B63: MR Code | C63: Description | F63: Remarks
C64: Unit | D64: Quantity | E64: Rate (₹) | F64: Amount | G64: Label
A65: S & F Motor starters of the following ratings Submersible pump controllers with ammeter,DPMCB for single phase 3.5HP submersible motor pumps (DOL)
B66: Header Unit | C66: each | D66: Header Quantity | E66: 1
A67: Header Details | B67: COST FOR 1 EACH A1 MATERIALS
A68: Material (M), Labour (L), Additional Charges (A)
B69: D | C69: Submersible pump controllers with ammeter,DPMCB for single phase 3.5 HP submersible motor pumps (DOL)
C70: each | D70: 1 | E70: 2400 | F70: =D70*E70 -> 2400 | G70: M1
B71: MR704 | C71: Man Mazdoor
C72: Day | D72: 0.01 | E72: 675 | F72: =D72*E72 -> 6.75 | G72: L2
A73: tcode | C73: Other Charge @ .5% of :(M1+L2) Add Hire charges for T&P @ 0.5%
C74: LS | F74: =(F70+F72)*0.5% -> 12.03375 | G74: A1
A75: TOTAL | D75: 1 | E75: each | F75: =F70+F72+F74 -> 2418.7838
A76: UNIT TOTAL | D76: 1 | E76: each | F76: =F75/D75 -> 2418.7838
A77: Cartage@ 1.00 % (for material) | E77: =F70*100.5%/D75 -> 2412 | F77: =E77*1% -> 24.12
A78: TOTAL | F78: =F76+F77 -> 2442.9037
A79: Contractors Profit & Overhead@ 15.00 % | E79: =F78 -> 2442.9037 | F79: =E79*15% -> 366.43556
A80: TOTAL | F80: =round(F78+F79,2) -> 2809.34
A81: 2852 | C81: Iron screws, 35 mm X 6 mm
C82: each | D82: 4 | E82: 1.8 | F82: =D82*E82 -> 7.2 | G82: M2
A83: 1005 | C83: Fitter, Grade 2
C84: Day | D84: 0.01 | E84: 734 | F84: =D84*E84 -> 7.34 | G84: L1
A85: tcode | C85: Other Charge @ .5% of :(M2+L1) Add Hire charges for T&P @ 0.5%
C86: LS | F86: =(F82+F84)*0.5% -> 0.0727 | G86: A2
A87: TOTAL | D87: 1 | E87: each | F87: =F82+F84+F86 -> 14.6127
A88: UNIT TOTAL | D88: 1 | E88: each | F88: =F87/D87 -> 14.6127
A89: Cartage@ 1.00 % (for material) | E89: =F82*100.5%/D87 -> 7.236 | F89: =E89*1% -> 0.07236
A90: TOTAL | F90: =F88+F89 -> 14.68506
A91: Contractors Profit & Overhead@ 15.00 % | E91: =F90 -> 14.68506 | F91: =E91*15% -> 2.202759
A92: TOTAL | F92: =round(F90+F91,2) -> 16.89
A93: =CONCATENATE("Say ₹ ",F80," + ",F92," x Cost Index") -> Say ₹ 2809.34 + 16.89 x Cost Index | G93: /E | H93: =((F70*1.005*1.01)+(F72*1.005))*1.15 -> 2809.3393 | I93: =((F82*1.005*1.01)+(F84*1.005))*1.15 -> 16.887819
A94: Sor/Spec Code | B94: MR Code | C94: Description | F94: Remarks
C95: Unit | D95: Quantity | E95: Rate (₹) | F95: Amount | G95: Label
A96: S & F Motor starters of the following ratings Submersible pump controllers with ammeter,TPMCB for three phase 2 to 4.5 HP submersible motor pumps (DOL)
B97: Header Unit | C97: each | D97: Header Quantity | E97: 1
A98: Header Details | B98: COST FOR 1 EACH A1 MATERIALS
A99: Material (M), Labour (L), Additional Charges (A)
B100: D | C100: Submersible pump controllers with ammeter,TPMCB for three phase 2 to 4.5 HP submersible motor pumps (DOL)
...

Sheet Motor Starter Monoblock
A1: Sor/Spec Code | B1: MR Code | C1: Description | F1: Remarks
C2: Unit | D2: Quantity | E2: Rate (₹) | F2: Amount | G2: Label
A3: S & F Motor starters of the following ratings Single phase DOL starters for 0.25HP to 3HP motor (90.14.28.1)
B4: Header Unit | C4: each | D4: Header Quantity | E4: 1
A5: Header Details | B5: COST FOR 1 EACH A1 MATERIALS
A6: Material (M), Labour (L), Additional Charges (A)
B7: MR1980 | C7: Single Phase DOL starters for 0.25 to 3 HP motor
C8: each | D8: 1 | E8: 728.81 | F8: =D8*E8 -> 728.81 | G8: M1
B9: MR2112 | C9: Spring washer for M8 nut
C10: each | D10: 4 | E10: 0.25 | F10: =D10*E10 -> 1 | G10: M4
B11: MR704 | C11: Man Mazdoor
C12: Day | D12: 0.01 | E12: 675 | F12: =D12*E12 -> 6.75 | G12: L2
A13: tcode | C13: Other Charge @ .5% of :(M1+M4+L2) Add Hire charges for T&P @ 0.5%
C14: LS | F14: =(F8+F10+F12)*0.5% -> 3.6828 | G14: A1
A15: TOTAL | D15: 1 | E15: each | F15: =F8+F10+F12+F14 -> 740.2428
A16: UNIT TOTAL | D16: 1 | E16: each | F16: =F15/D15 -> 740.2428
A17: Cartage@ 1.00 % (for material) | E17: =(F8+F10)*1.005 -> 733.45905 | F17: =E17*1% -> 7.3345905
A18: TOTAL | F18: =F16+F17 -> 747.57739
A19: Contractors Profit & Overhead@ 15.00 % | E19: =F18 -> 747.57739 | F19: =E19*15% -> 112.13661
A20: TOTAL | F20: =round(F18+F19,2) -> 859.71
A21: 2862 | C21: 32mm X 8mm bolts & nuts
C22: each | D22: 4 | E22: 5.4 | F22: =D22*E22 -> 21.6 | G22: M2
A23: 2920 | C23: Washers
C24: each | D24: 4 | E24: 0 | F24: =D24*E24 -> 0 | G24: M3
A25: 1005 | C25: Fitter, Grade 2
C26: Day | D26: 0.01 | E26: 734 | F26: =D26*E26 -> 7.34 | G26: L1
A27: tcode | C27: Other Charge @ .5% of :(M2+M3+L1) Add Hire charges for T&P @ 0.5%
C28: LS | F28: =(F22+F24+F26)*0.5% -> 0.1447 | G28: A2
A29: TOTAL | D29: 1 | E29: each | F29: =F22+F24+F26+F28 -> 29.0847
A30: UNIT TOTAL | D30: 1 | E30: each | F30: =F29/D29 -> 29.0847
A31: Cartage@ 1.00 % (for material) | E31: =(F22+F24)*1.005 -> 21.708 | F31: =E31*1% -> 0.21708
A32: TOTAL | F32: =F30+F31 -> 29.30178
A33: Contractors Profit & Overhead@ 15.00 % | E33: =F32 -> 29.30178 | F33: =E33*15% -> 4.395267
A34: TOTAL | F34: =round(F32+F33,2) -> 33.7
A35: =CONCATENATE("Say ₹ ",F20," + ",F34," x Cost Index") -> Say ₹ 859.71 + 33.7 x Cost Index | G35: /E | H35: =((F8+F10)*1.005*1.01*1.15)+(F12*1.005*1.15) -> 859.714 | I35: =((F22+F24)*1.005*1.01*1.15)+(F26*1.005*1.15) -> 33.697047

Sheet Motor Starter PRICE
A1: Sor/Spec Code | B1: MR Code | C1: Description | F1: Remarks
C2: Unit | D2: Quantity | E2: Rate (₹) | F2: Amount | G2: Label
A3: S & F Motor starters of the following ratings Submersible pump controllers with ammeter,DPMCB for single phase 0.5HP submersible motor pumps (DOL) (90.14.28.10)
B4: Header Unit | C4: each | D4: Header Quantity | E4: 1
A5: Header Details | B5: COST FOR 1 EACH A1 MATERIALS
A6: Material (M), Labour (L), Additional Charges (A)
B7: MR2001 | C7: Submersible pump controllers with ammeter,DPMCB for single phase 0.5HP submersible motor pumps (DOL)
C8: each | D8: 1 | E8: 1525.42 | F8: =D8*E8 -> 1525.42 | G8: M1
B9: MR704 | C9: Man Mazdoor
C10: Day | D10: 0.01 | E10: 675 | F10: =D10*E10 -> 6.75 | G10: L2
A11: tcode | C11: Other Charge @ .5% of :(M1+L2) Add Hire charges for T&P @ 0.5%
C12: LS | F12: =(F8+F10)*0.5% -> 7.66085 | G12: A1
A13: TOTAL | D13: 1 | E13: each | F13: =F8+F10+F12 -> 1539.8309
A14: UNIT TOTAL | D14: 1 | E14: each | F14: =F13/D13 -> 1539.8309
A15: Cartage@ 1.00 % (for material) | E15: =F8*100.5%/D13 -> 1533.0471 | F15: =E15*1% -> 15.330471
A16: TOTAL | F16: =F14+F15 -> 1555.1613
A17: Contractors Profit & Overhead@ 15.00 % | E17: =F16 -> 1555.1613 | F17: =E17*15% -> 233.2742
A18: TOTAL | F18: =round(F16+F17,2) -> 1788.44
A19: 2852 | C19: Iron screws, 35 mm X 6 mm
C20: each | D20: 4 | E20: 1.8 | F20: =D20*E20 -> 7.2 | G20: M2
A21: 1005 | C21: Fitter, Grade 2
C22: Day | D22: 0.01 | E22: 734 | F22: =D22*E22 -> 7.34 | G22: L1
A23: tcode | C23: Other Charge @ .5% of :(M2+L1) Add Hire charges for T&P @ 0.5%
C24: LS | F24: =(F20+F22)*0.5% -> 0.0727 | G24: A2 | H24: =F24+F12 -> 7.73355
A25: TOTAL | D25: 1 | E25: each | F25: =F20+F22+F24 -> 14.6127
A26: UNIT TOTAL | D26: 1 | E26: each | F26: =F25/D25 -> 14.6127
A27: Cartage@ 1.00 % (for material) | E27: =F20*100.5%/D25 -> 7.236 | F27: =E27*1% -> 0.07236
A28: TOTAL | F28: =F26+F27 -> 14.68506
A29: Contractors Profit & Overhead@ 15.00 % | E29: =F28 -> 14.68506 | F29: =E29*15% -> 2.202759
A30: TOTAL | F30: =round(F28+F29,2) -> 16.89 | I30: =F30+F18 -> 1805.33
A31: =CONCATENATE("Say ₹ ",F18," + ",F30," x Cost Index") -> Say ₹ 1788.44 + 16.89 x Cost Index | G31: /E | H31: =((F8*1.005*1.01)+(F10*1.005))*1.15 -> 1788.4355 | I31: =((F20*1.005*1.01)+(F22*1.005))*1.15 -> 16.887819
A32: Sor/Spec Code | B32: MR Code | C32: Description | F32: Remarks
C33: Unit | D33: Quantity | E33: Rate (₹) | F33: Amount | G33: Label
A34: S & F Motor starters of the following ratings Submersible pump controllers with ammeter,DPMCB for single phase 1 HP submersible motor pumps (DOL) (90.14.28.11)
B35: Header Unit | C35: each | D35: Header Quantity | E35: 1
A36: Header Details | B36: COST FOR 1 EACH A1 MATERIALS
A37: Material (M), Labour (L), Additional Charges (A)
B38: MR2002 | C38: Submersible pump controllers with ammeter,DPMCB for single phase 1 HP submersible motor pumps (DOL)
C39: each | D39: 1 | E39: 1567.8 | F39: =D39*E39 -> 1567.8 | G39: M1
B40: MR704 | C40: Man Mazdoor
C41: Day | D41: 0.01 | E41: 675 | F41: =D41*E41 -> 6.75 | G41: L2
A42: tcode | C42: Other Charge @ .5% of :(M1+L2) Add Hire charges for T&P @ 0.5%
C43: LS | F43: =(F39+F41)*0.5% -> 7.87275 | G43: A1
A44: TOTAL | D44: 1 | E44: each | F44: =F39+F41+F43 -> 1582.4227
A45: UNIT TOTAL | D45: 1 | E45: each | F45: =F44/D44 -> 1582.4227
A46: Cartage@ 1.00 % (for material) | E46: =F39*100.5%/D44 -> 1575.639 | F46: =E46*1% -> 15.75639
A47: TOTAL | F47: =F45+F46 -> 1598.1791
A48: Contractors Profit & Overhead@ 15.00 % | E48: =F47 -> 1598.1791 | F48: =E48*15% -> 239.72687
A49: TOTAL | F49: =round(F47+F48,2) -> 1837.91
A50: 2852 | C50: Iron screws, 35 mm X 6 mm
C51: each | D51: 4 | E51: 1.8 | F51: =D51*E51 -> 7.2 | G51: M2
A52: 1005 | C52: Fitter, Grade 2
C53: Day | D53: 0.01 | E53: 734 | F53: =D53*E53 -> 7.34 | G53: L1
A54: tcode | C54: Other Charge @ .5% of :(M2+L1) Add Hire charges for T&P @ 0.5%
C55: LS | F55: =(F51+F53)*0.5% -> 0.0727 | G55: A2 | H55: =F55+F43 -> 7.94545
A56: TOTAL | D56: 1 | E56: each | F56: =F51+F53+F55 -> 14.6127
A57: UNIT TOTAL | D57: 1 | E57: each | F57: =F56/D56 -> 14.6127
A58: Cartage@ 1.00 % (for material) | E58: =F51*100.5%/D56 -> 7.236 | F58: =E58*1% -> 0.07236
A59: TOTAL | F59: =F57+F58 -> 14.68506
A60: Contractors Profit & Overhead@ 15.00 % | E60: =F59 -> 14.68506 | F60: =E60*15% -> 2.202759
A61: TOTAL | F61: =round(F59+F60,2) -> 16.89 | I61: =F61+F49 -> 1854.8
A62: =CONCATENATE("Say ₹ ",F49," + ",F61," x Cost Index") -> Say ₹ 1837.91 + 16.89 x Cost Index | G62: /E | H62: =((F39*1.005*1.01)+(F41*1.005))*1.15 -> 1837.906 | I62: =((F51*1.005*1.01)+(F53*1.005))*1.15 -> 16.887819
A63: Sor/Spec Code | B63: MR Code | C63: Description | F63: Remarks
C64: Unit | D64: Quantity | E64: Rate (₹) | F64: Amount | G64: Label
A65: S & F Motor starters of the following ratings Submersible pump controllers with ammeter,DPMCB for single phase 1.5 HP submersible motor pumps (DOL) (90.14.28.12)
B66: Header Unit | C66: each | D66: Header Quantity | E66: 1
A67: Header Details | B67: COST FOR 1 EACH A1 MATERIALS
A68: Material (M), Labour (L), Additional Charges (A)
B69: MR2003 | C69: Submersible pump controllers with ammeter,DPMCB for single phase 1.5HP submersible motor pumps (DOL)
C70: each | D70: 1 | E70: 1610.17 | F70: =D70*E70 -> 1610.17 | G70: M1
B71: MR704 | C71: Man Mazdoor
C72: Day | D72: 0.01 | E72: 675 | F72: =D72*E72 -> 6.75 | G72: L2
A73: tcode | C73: Other Charge @ .5% of :(M1+L2) Add Hire charges for T&P @ 0.5%
C74: LS | F74: =(F70+F72)*0.5% -> 8.0846 | G74: A1
A75: TOTAL | D75: 1 | E75: each | F75: =F70+F72+F74 -> 1625.0046
A76: UNIT TOTAL | D76: 1 | E76: each | F76: =F75/D75 -> 1625.0046
A77: Cartage@ 1.00 % (for material) | E77: =F70*100.5%/D75 -> 1618.2208 | F77: =E77*1% -> 16.182209
A78: TOTAL | F78: =F76+F77 -> 1641.1868
A79: Contractors Profit & Overhead@ 15.00 % | E79: =F78 -> 1641.1868 | F79: =E79*15% -> 246.17802
A80: TOTAL | F80: =round(F78+F79,2) -> 1887.36
A81: 2852 | C81: Iron screws, 35 mm X 6 mm
C82: each | D82: 4 | E82: 1.8 | F82: =D82*E82 -> 7.2 | G82: M2
A83: 1005 | C83: Fitter, Grade 2
C84: Day | D84: 0.01 | E84: 734 | F84: =D84*E84 -> 7.34 | G84: L1
A85: tcode | C85: Other Charge @ .5% of :(M2+L1) Add Hire charges for T&P @ 0.5%
C86: LS | F86: =(F82+F84)*0.5% -> 0.0727 | G86: A2 | H86: =F86+F74 -> 8.1573
A87: TOTAL | D87: 1 | E87: each | F87: =F82+F84+F86 -> 14.6127
A88: UNIT TOTAL | D88: 1 | E88: each | F88: =F87/D87 -> 14.6127
A89: Cartage@ 1.00 % (for material) | E89: =F82*100.5%/D87 -> 7.236 | F89: =E89*1% -> 0.07236
A90: TOTAL | F90: =F88+F89 -> 14.68506
A91: Contractors Profit & Overhead@ 15.00 % | E91: =F90 -> 14.68506 | F91: =E91*15% -> 2.202759
A92: TOTAL | F92: =round(F90+F91,2) -> 16.89 | I92: =F92+F80 -> 1904.25
A93: =CONCATENATE("Say ₹ ",F80," + ",F92," x Cost Index") -> Say ₹ 1887.36 + 16.89 x Cost Index | G93: /E | H93: =((F70*1.005*1.01)+(F72*1.005))*1.15 -> 1887.3648 | I93: =((F82*1.005*1.01)+(F84*1.005))*1.15 -> 16.887819
A94: Sor/Spec Code | B94: MR Code | C94: Description | F94: Remarks
C95: Unit | D95: Quantity | E95: Rate (₹) | F95: Amount | G95: Label
A96: S & F Motor starters of the following ratings Submersible pump controllers with ammeter,DPMCB for single phase 2 HP submersible motor pumps (DOL) (90.14.28.13)
B97: Header Unit | C97: each | D97: Header Quantity | E97: 1
A98: Header Details | B98: COST FOR 1 EACH A1 MATERIALS
A99: Material (M), Labour (L), Additional Charges (A)
B100: MR2004 | C100: Submersible pump controllers with ammeter,DPMCB for single phase 2 HP submersible motor pumps (DOL)
...

Sheet Other Fittings PRICE
A1: Spec Code | B1: Specification | C1: Rate (₹) | D1: Unit
A2: 18.17.1 | B2: Providing and fixing gun metal gate valve with C.I. wheel of approved quality (screwed end) : 25 mm nominal bore (18.17.1) | C2: 462.13 | D2: each
A3: 18.17.2 | B3: Providing and fixing gun metal gate valve with C.I. wheel of approved quality (screwed end) : 32 mm nominal bore (18.17.2) | C3: 512.12 | D3: each
A4: 18.17.3 | B4: Providing and fixing gun metal gate valve with C.I. wheel of approved quality (screwed end) : 40 mm nominal bore (18.17.3) | C4: 614.04 | D4: each
A5: 18.17.4 | B5: Providing and fixing gun metal gate valve with C.I. wheel of approved quality (screwed end) : 50 mm nominal bore (18.17.4) | C5: 762.43 | D5: each
A6: 18.17.5 | B6: Providing and fixing gun metal gate valve with C.I. wheel of approved quality (screwed end) : 65 mm nominal bore (18.17.5) | C6: 1294.11 | D6: each
A7: 18.17.6 | B7: Providing and fixing gun metal gate valve with C.I. wheel of approved quality (screwed end) : 80 mm nominal bore (18.17.6) | C7: 1933.85 | D7: each
A8: 18.17.1A | B8: Providing and fixing gun metal gate valve with C.I. wheel of approved quality (screwed end) : 20 mm nominal bore (18.17.1A) | C8: 400.86 | D8: each
A9: 18.19.1.1 | B9: Providing and fixing gun metal non-return valve of approved quality (screwed end): 25 mm nominal bore Horizontal (18.19.1.1) | C9: 439.81 | D9: each
A10: 18.19.1.2 | B10: Providing and fixing gun metal non-return valve of approved quality (screwed end): 25 mm nominal bore Vertical (18.19.1.2) | C10: 497.89 | D10: each
A11: 18.19.2.1 | B11: Providing and fixing gun metal non-return valve of approved quality (screwed end): 32 mm nominal bore Horizontal (18.19.2.1) | C11: 588.21 | D11: each
A12: 18.19.2.2 | B12: Providing and fixing gun metal non-return valve of approved quality (screwed end): 32 mm nominal bore Vertical (18.19.2.2) | C12: 675.32 | D12: each
A13: 18.19.3.1 | B13: Providing and fixing gun metal non-return valve of approved quality (screwed end): 40 mm nominal bore Horizontal (18.19.3.1) | C13: 707.55 | D13: each
... A36: 18.47.8 | B36: Providing and fixing G.I Union in existing G.I pipe line, cutting and threading the pipe and making long screws, including excavation, refilling the earth or cutting of wall and making good the same complete wherever required: 80 mm nominal bore (18.47.8) | C36: 1419.25 | D36: each

Sheet Panel Board
A1: Panel Board
A2: (i) | B2: Installation of Single Phase Panel board where new electricity connection is required (Excluding Motor Starter)
A3: MR | B3: 75x75 cm Metal Box | C3: 1 | D3: each | E3: 1620 | F3: /each | G3: =C3*E3 -> 1620
A4: MR1428 (PRICE Electrical) | B4: 32A, 4 pole On-Load Change Over Switches In Open Execution (ICDP) | C4: 1 | D4: each | E4: 1355 | F4: /each | G4: =C4*E4 -> 1355
A5: MR1717 (PRICE Electrical) | B5: CT for 3P and 4P circuit breakers for neutral overload and ground fault protection for 630 - 1600 A, ACBs. (ELCB) | C5: 1 | D5: each | E5: 2196 | F5: /each | G5: =C5*E5 -> 2196
A6: MR1459 (PRICE Electrical) | B6: 32, HRC Fuse Base with HRC Fuse link | C6: 1 | D6: each | E6: 105 | F6: /each | G6: =C6*E6 -> 105
A7: MR1467 (PRICE Electrical) | B7: 32 A, 2 Way neutral links mounted on DMC/SMC base | C7: 1 | D7: each | E7: 84 | F7: /each | G7: =C7*E7 -> 84
A8: MR1638 (PRICE Electrical) | B8: 3 Pole Capacitor duty contactors for switching capacitor banks 4 - 7 kVAR with AC Coil | C8: 1 | D8: each | E8: 1016 | F8: /each | G8: =C8*E8 -> 1016
A9: 0 | B9: Nut & Bolt | C9: 1 | D9: LS | E9: 100 | F9: LS | G9: =C9*E9 -> 100
A10: 0 | B10: Metal Box for Meter | C10: 1 | D10: each | E10: 540 | F10: /each | G10: =C10*E10 -> 540
B11: Sub Total | G11: =SUM(G3:G10) -> 7016
B12: Water charges/Cartage 1% | G12: =G11*1% -> 70.16
B13: Total | G13: =SUM(G11:G12) -> 7086.16
B14: CPOH 15% | G14: =G13*15% -> 1062.924
B15: Total | G15: =round(SUM(G13:G14),2) -> 8149.08
A16: 2826 (DSR 2022 Electrical) | B16: 40 mm dia. G.I. pipe (medium class) for earthing | C16: 1 | D16: meter | E16: 383 | F16: /meter | G16: =C16*E16 -> 383
A17: 2838 (DSR 2022 Electrical) | B17: 40 mm dia. G.I. bend (medium class) for earthing | C17: 1 | D17: each | E17: 61 | F17: /each | G17: =C17*E17 -> 61
A18: 2902 (DSR 2022 Electrical) | B18: 25 mm X 5 mm copper tape (1.15 kg/mtr) for earthing | C18: 1.15 | D18: kg | E18: 612 | F18: /kg | G18: =C18*E18 -> 703.8
A19: 1102 (DSR 2022 Electrical) | B19: 2.5 sq. mm ISI marked, FRLS PVC insulated, single core copper conductor cable | C19: 10 | D19: meter | E19: 28 | F19: /meter | G19: =C19*E19 -> 280
A20: 0116 | B20: Fitter (grade I) | C20: 1 | D20: day | E20: 784 | F20: /day | G20: =C20*E20 -> 784
A21: 0114 | B21: Beldar | C21: 1 | D21: day | E21: 645 | F21: /day | G21: =C21*E21 -> 645
B22: Sub Total | G22: =SUM(G16:G21) -> 2856.8
B23: Water charges/Cartage 1% | G23: =G22*0.01 -> 28.568
B24: Total | G24: =SUM(G22:G23) -> 2885.368
A25: 1001 (DSR 2022 Electrical) | B25: Wireman | C25: 1 | D25: day | E25: 806 | F25: /day | G25: =C25*E25 -> 806
B26: Total | G26: =SUM(G24:G25) -> 3691.368
B27: CPOH 15% | G27: =G26*15% -> 553.7052
B28: Total | G28: =round(SUM(G26:G27),2) -> 4245.07
A29: =CONCATENATE("Say ₹ ",G15," + ",G28," x Cost Index") -> Say ₹ 8149.08 + 4245.07 x Cost Index | H29: =SUM(G3:G10)*1.01*1.15 -> 8149.084 | I29: =SUM(G16:G21)*1.01*1.15+(G25*1.15) -> 4245.0732
A30: (ii) | B30: Installation of Three Phase Panel board where new electricity connection is required (Excluding Motor Starter)
A31: 0 | B31: 75x75 cm Metal Box | C31: 1 | D31: each | E31: 1620 | F31: /each | G31: =C31*E31 -> 1620
A32: MR1428 (PRICE Electrical) | B32: 32A, 4 pole On-Load Change Over Switches In Open Execution (ICDP) | C32: 1 | D32: each | E32: 1355 | F32: /each | G32: =C32*E32 -> 1355
A33: MR1717 (PRICE Electrical) | B33: CT for 3P and 4P circuit breakers for neutral overload and ground fault protection for 630 - 1600 A, ACBs. (ELCB) | C33: 1 | D33: each | E33: 2196 | F33: /each | G33: =C33*E33 -> 2196
A34: MR1459 (PRICE Electrical) | B34: 32, HRC Fuse Base with HRC Fuse link | C34: 3 | D34: each | E34: 105 | F34: /each | G34: =C34*E34 -> 315
A35: MR1467 (PRICE Electrical) | B35: 32 A, 2 Way neutral links mounted on DMC/SMC base | C35: 1 | D35: each | E35: 84 | F35: /each | G35: =C35*E35 -> 84
A36: MR1638 (PRICE Electrical) | B36: 3 Pole Capacitor duty contactors for switching capacitor banks 4 - 7 kVAR with AC Coil | C36: 1 | D36: each | E36: 1016 | F36: /each | G36: =C36*E36 -> 1016
A37: 0 | B37: Nut & Bolt | C37: 1 | D37: LS | E37: 100 | F37: LS | G37: =C37*E37 -> 100
A38: 0 | B38: Metal Box for Meter | C38: 1 | D38: each | E38: 540 | F38: /each | G38: =C38*E38 -> 540
B39: Sub Total | G39: =SUM(G31:G38) -> 7226
B40: Water charges/Cartage 1% | G40: =G39*1% -> 72.26
B41: Total | G41: =SUM(G39:G40) -> 7298.26
B42: CPOH 15% | G42: =G41*15% -> 1094.739
B43: Total | G43: =round(SUM(G41:G42),2) -> 8393
A44: 2826 (DSR 2022 Electrical) | B44: 40 mm dia. G.I. pipe (medium class) for earthing | C44: 1 | D44: meter | E44: 383 | F44: /meter | G44: =C44*E44 -> 383
A45: 2838 (DSR 2022 Electrical) | B45: 40 mm dia. G.I. bend (medium class) for earthing | C45: 1 | D45: each | E45: 61 | F45: /each | G45: =C45*E45 -> 61
A46: 2902 (DSR 2022 Electrical) | B46: 25 mm X 5 mm copper tape (1.15 kg/mtr) for earthing | C46: 1.15 | D46: kg | E46: 612 | F46: /kg | G46: =C46*E46 -> 703.8
A47: 1102 (DSR 2022 Electrical) | B47: 2.5 sq. mm ISI marked, FRLS PVC insulated, single core copper conductor cable | C47: 15 | D47: meter | E47: 28 | F47: /meter | G47: =C47*E47 -> 420
A48: 0116 | B48: Fitter (grade I) | C48: 2 | D48: day | E48: 784 | F48: /day | G48: =C48*E48 -> 1568
A49: 0114 | B49: Beldar | C49: 2 | D49: day | E49: 645 | F49: /day | G49: =C49*E49 -> 1290
B50: Sub Total | G50: =SUM(G44:G49) -> 4425.8
B51: Water charges/Cartage 1% | G51: =G50*0.01 -> 44.258
B52: Total | G52: =SUM(G50:G51) -> 4470.058
A53: 1001 (DSR 2022 Electrical) | B53: Wireman | C53: 2 | D53: day | E53: 806 | F53: /day | G53: =C53*E53 -> 1612
B54: Total | G54: =SUM(G52:G53) -> 6082.058
B55: CPOH 15% | G55: =G54*15% -> 912.3087
B56: Total | G56: =round(SUM(G54:G55),2) -> 6994.37
A57: =CONCATENATE("Say ₹ ",G43," + ",G56," x Cost Index") -> Say ₹ 8393 + 6994.37 x Cost Index | H57: =SUM(G31:G38)*1.01*1.15 -> 8392.999 | I57: =SUM(G44:G49)*1.01*1.15+(G53*1.15) -> 6994.3667

Sheet Pump Cover
A1: Metallic Pump Cover of size 1 x 1 x 0.7 m
A2: Sl. No. | B2: Item | C2: No. | D2: L | E2: B | F2: D | G2: Total | H2: Unit | I2: Rate | J2: Amount
A3: 1 | B3: Surface dressing of the ground including removing vegetation and in-equalities not exceeding 15 cm deep and disposal of rubbish, lead up to 50 m and lift up to 1.5 m. All kinds of soil (Code: 2.28.1)
B4: Area | C4: 1 | D4: 1 | E4: 1 | F4: 1 | G4: =PRODUCT(C4:F4) -> 1
B5: Total | G5: =SUM(G4) -> 1 | H5: m2 | I5: 24.43 | J5: =G5*I5 -> 24.43
A6: 2 | B6: Earth work in excavation by mechanical means (Hydraulic excavator) /manual means in foundation trenches or drains (not exceeding 1.5 m in width or 10 sqm on plan), including dressing of sides and ramming of bottoms, lift up to 1.5 m, including getting out the excavated soil and disposal of surplus excavated soil as directed, within a lead of 50 m. All kinds of soil (Code: 2.8.1)
B7: Foundation | C7: 1 | D7: 1 | E7: 1 | F7: 0.2 | G7: =PRODUCT(C7:F7) -> 0.2
B8: Total | G8: =SUM(G7) -> 0.2 | H8: m3 | I8: 249.04 | J8: =G8*I8 -> 49.808
A9: 3 | B9: Providing and laying in position cement concrete of specified grade excluding the cost of centering and shuttering - All work up to plinth level: 1:4:8 (1 cement : 4 coarse sand : 8 graded stone aggregate 40 nominal size) (Code: 4.1.8)
B10: Foundation | C10: 1 | D10: 1 | E10: 1 | F10: 0.3 | G10: =PRODUCT(C10:F10) -> 0.3
B11: Total | G11: =SUM(G10) -> 0.3 | H11: m3 | I11: 5491.79 | J11: =G11*I11 -> 1647.537
A12: 4 | B12: 12 mm cement plaster of mix: 1:4 ( 1 cement : 4 fine sand) (Code: 13.1.1)
B13: Basement | C13: 4 | D13: 1 | F13: 0.1 | G13: =PRODUCT(C13:F13) -> 0.4
B14: Floor | C14: 1 | D14: 1 | E14: 1 | G14: =PRODUCT(C14:F14) -> 1
B15: Total | G15: =SUM(G13:G14) -> 1.4 | H15: m3 | I15: 255.98 | J15: =G15*I15 -> 358.372
A16: 5 | B16: Structural steel work in single section, fixed with or without connecting plate, including cutting, hoisting, fixing in position and applying a priming coat of approved steel primer all complete. (Code: 10.1)
B17: MS Sq Tube 25mm | C17: No. | D17: L | E17: Total | F17: Weight | G17: Unit | H17: Total Weight | I17: Rate
B18: Front & Back bottom & Top | C18: 4 | D18: 1 | E18: =C18*D18 -> 4
B19: Side top & bottom | C19: 4 | D19: 1 | E19: =C19*D19 -> 4
B20: Front & Back corner vertical | C20: 4 | D20: 0.7 | E20: =C20*D20 -> 2.8
B21: Door Horizontal | C21: 2 | D21: 1 | E21: =C21*D21 -> 2
B22: Door vertical | C22: 2 | D22: 0.7 | E22: =C22*D22 -> 1.4
B23: Total Length | E23: =SUM(E18:E22) -> 14.2 | F23: 1.43 | G23: kg/m | H23: =E23*F23 -> 20.306 | I23: 80.77 | J23: =H23*I23 -> 1640.1156
A24: 6 | B24: M.S. Wire mesh (rabbit) (Code: 1220 - Water Charge and CPOH Added)
B25: MS Weld Mesh | C25: No | D25: L | E25: B | F25: H | G25: Total
C26: 4 | D26: 1 | F26: 0.7 | G26: =PRODUCT(C26:F26) -> 2.8
B27: Total Area | G27: =SUM(G26) -> 2.8 | H27: m2 | I27: 48.78 | J27: =G27*I27 -> 136.584
A28: 7 | B28: Providing corrugate G.S. sheet roofing including vertical/ curved surface fixed with polymer coated J or L hooks, bolts and nuts 8 mm diameter with bitumen and G.I. limpet washers or with G.I. limpet washers filled with white lead, including a coat of approved steel primer and two coats of approved paint on overlapping of sheets complete ( up to any pitch in horizontal / vertical or curved surfaces), excluding the cost of purlins, rafters and trusses and including cutting to size and shape wherever required. 0.63 mm thick with zinc coating not less than 275 gm/m2 (Code: 12.1.3)
C29: 1 | D29: 1.5 | E29: 1.5 | G29: =PRODUCT(C29:F29) -> 2.25 | H29: m2 | I29: 849.04 | J29: =G29*I29 -> 1910.34
A30: 8 | B30: Providing and fixing bright finished brass butt hinges with necessary screws etc. complete: 50x40x2.5 mm (ordinary type) (Code: 9.72.7)
C31: 3 | G31: =PRODUCT(C31:F31) -> 3 | H31: No. | I31: 30.15 | J31: =G31*I31 -> 90.45
A32: 9 | B32: Fitter (grade 1) (Code: 0116 - Water Charge and CPOH Added)
G33: 0.25 | H33: Day | I33: 910.62 | J33: =G33*I33 -> 227.655
A34: 10 | B34: Locking Arrangements - Supplying and Fixing lock and locking arrangements with suitable chain hooks,and padlock of 65mm size. (Code: 60.4)
B35: Non Index | C35: 1 | G35: =PRODUCT(C35:F35) -> 1 | H35: No. | I35: =Lock!F16 -> 641.15 | J35: =G35*I35 -> 641.15
B36: Index | I36: =Lock!F24 -> 27.04275 | J36: =I36*G35 -> 27.04275
A37: Index TOTAL | J37: =SUM(J3:J34,J36) -> 6112.3344
A38: Non Index TOTAL | J38: =SUM(J35) -> 641.15
A39: =CONCATENATE("Say ₹ ",J38," + ",J37," x Cost Index") -> Say ₹ 641.15 + 6112.33437 x Cost Index | K39: =J38 -> 641.15 | L39: =J37 -> 6112.3344

Sheet Pump Erection 
A1: Pump Erection
A2: 0 | B2: Borewell submersible pump erection charges upto 3 HP
A3: Code | B3: Description | C3: Unit | D3: Quantity | E3: Rate | F3: Amount
B4: MATERIALS:
A5: 0 | B5: 40mm Cast Iron Clamp | C5: set | D5: 1 | E5: 935 | F5: =D5*E5 -> 935
B6: Add Water Charges @ 1% | F6: =F5*0.01 -> 9.35
B7: TOTAL | F7: =SUM(F5:F6) -> 944.35
B8: Add CPOH @ 15% | F8: =F7*0.15 -> 141.6525
B9: TOTAL | F9: =SUM(F7:F8) -> 1086.0025
A10: 0015 | B10: Tools hire charge (DSR 0015) | C10: day | D10: 0.5 | E10: 3000 | F10: =D10*E10 -> 1500
A11: 0116 | B11: Fitter, Plumber, Electrician | C11: Day | D11: 3 | E11: 784 | F11: =D11*E11 -> 2352
A12: 0114 | B12: Beldar | C12: Day | D12: 2 | E12: 645 | F12: =D12*E12 -> 1290
B13: TOTAL | F13: =SUM(F10:F12) -> 5142
B14: Add Water Charges @ 1% | F14: =F13*0.01 -> 51.42
B15: TOTAL | F15: =SUM(F13:F14) -> 5193.42
B16: Add CPOH @ 15% | F16: =F15*0.15 -> 779.013
B17: TOTAL | F17: =SUM(F15:F16) -> 5972.433
A18: =CONCATENATE("Say Rs ",F9," + (",F17," x Cost Index)") -> Say Rs 1086.0025 + (5972.433 x Cost Index)
A19: 0 | B19: Borewell submersible pump erection charges above 3 h.P. To 7.5 H.P.
A20: Code | B20: Description | C20: Unit | D20: Quantity | E20: Rate | F20: Amount
B21: MATERIALS:
A22: 0 | B22: 40mm Cast iron Clamp | C22: set | D22: 1 | E22: 935 | F22: =D22*E22 -> 935
B23: Add Water Charges @ 1% | F23: =F22*0.01 -> 9.35
B24: TOTAL | F24: =SUM(F22:F23) -> 944.35
B25: Add CPOH @ 15% | F25: =F24*0.15 -> 141.6525
B26: TOTAL | F26: =SUM(F24:F25) -> 1086.0025
A27: 0015 | B27: Tools hire charge (DSR 0015) | C27: day | D27: 0.75 | E27: 3000 | F27: =D27*E27 -> 2250
A28: 0116 | B28: Fitter, Plumber, Electrician | C28: Day | D28: 3 | E28: 784 | F28: =D28*E28 -> 2352
A29: 0114 | B29: Beldar | C29: Day | D29: 3 | E29: 645 | F29: =D29*E29 -> 1935
B30: TOTAL | F30: =SUM(F27:F29) -> 6537
B31: Add Water Charges @ 1% | F31: =F30*0.01 -> 65.37
B32: TOTAL | F32: =SUM(F30:F31) -> 6602.37
B33: Add CPOH @ 15% | F33: =F32*0.15 -> 990.3555
B34: TOTAL | F34: =SUM(F32:F33) -> 7592.7255
A35: =CONCATENATE("Say Rs ",F26," + (",F34," x Cost Index)") -> Say Rs 1086.0025 + (7592.7255 x Cost Index)
A36: 0 | B36: Borewell submersible pump erection charges above 7.5 H.P.
A37: Code | B37: Description | C37: Unit | D37: Quantity | E37: Rate | F37: Amount
B38: MATERIALS:
A39: 0 | B39: 40mm Cast iron Clamp | C39: set | D39: 1 | E39: 935 | F39: =D39*E39 -> 935
B40: Add Water Charges @ 1% | F40: =F39*0.01 -> 9.35
B41: TOTAL | F41: =SUM(F39:F40) -> 944.35
B42: Add CPOH @ 15% | F42: =F41*0.15 -> 141.6525
B43: TOTAL | F43: =SUM(F41:F42) -> 1086.0025
A44: 0015 | B44: Tools hire charge (DSR 0015) | C44: day | D44: 1 | E44: 3000 | F44: =D44*E44 -> 3000
A45: 0116 | B45: Fitter, Plumber, Electrician | C45: Day | D45: 3 | E45: 784 | F45: =D45*E45 -> 2352
A46: 0114 | B46: Beldar | C46: Day | D46: 4 | E46: 645 | F46: =D46*E46 -> 2580
B47: TOTAL | F47: =SUM(F44:F46) -> 7932
B48: Add Water Charges @ 1% | F48: =F47*0.01 -> 79.32
B49: TOTAL | F49: =SUM(F47:F48) -> 8011.32
B50: Add CPOH @ 15% | F50: =F49*0.15 -> 1201.698
B51: TOTAL | F51: =SUM(F49:F50) -> 9213.018
A52: =CONCATENATE("Say Rs ",F43," + (",F51," x Cost Index)") -> Say Rs 1086.0025 + (9213.018 x Cost Index)
A53: 0 | B53: Compressor pump fitting charge
A54: Code | B54: Description | C54: Unit | D54: Quantity | E54: Rate | F54: Amount
A55: 0015 | B55: Tools hire charge (DSR 0015) | C55: day | D55: 0.3 | E55: 3000 | F55: =D55*E55 -> 900
A56: 0116 | B56: Fitter, Plumber, Electrician | C56: Day | D56: 2 | E56: 784 | F56: =D56*E56 -> 1568
A57: 0114 | B57: Beldar | C57: Day | D57: 1 | E57: 645 | F57: =D57*E57 -> 645
B58: TOTAL | F58: =SUM(F55:F57) -> 3113
B59: Add Water Charges @ 1% | F59: =F58*0.01 -> 31.13
B60: TOTAL | F60: =SUM(F58:F59) -> 3144.13
B61: Add CPOH @ 15% | F61: =F60*0.15 -> 471.6195
B62: TOTAL | F62: =SUM(F60:F61) -> 3615.7495
A63: =CONCATENATE("Say Rs (",F62," x Cost Index)") -> Say Rs (3615.7495 x Cost Index)

Sheet Pump Pullout
A1: Pump Pullout
A2: 0 | B2: Borewell submersible pump pullout charges upto 3 HP
A3: Code | B3: Description | C3: Unit | D3: Quantity | E3: Rate | F3: Amount
B4: MATERIALS:
A5: 0 | B5: 40mm Cast Iron Clamp | C5: set | D5: 0 | E5: 935 | F5: =D5*E5 -> 0
B6: Add Water Charges @ 1% | F6: =F5*0.01 -> 0
B7: TOTAL | F7: =SUM(F5:F6) -> 0
B8: Add CPOH @ 15% | F8: =F7*0.15 -> 0
B9: TOTAL | F9: =SUM(F7:F8) -> 0
A10: 0015 | B10: Tools hire charge (DSR 0015) | C10: day | D10: 0.5 | E10: 3000 | F10: =D10*E10 -> 1500
A11: 0116 | B11: Fitter, Plumber, Electrician | C11: Day | D11: 1 | E11: 784 | F11: =D11*E11 -> 784
A12: 0114 | B12: Beldar | C12: Day | D12: 1 | E12: 645 | F12: =D12*E12 -> 645
B13: TOTAL | F13: =SUM(F10:F12) -> 2929
B14: Add Water Charges @ 1% | F14: =F13*0.01 -> 29.29
B15: TOTAL | F15: =SUM(F13:F14) -> 2958.29
B16: Add CPOH @ 15% | F16: =F15*0.15 -> 443.7435
B17: TOTAL | F17: =mround(SUM(F15:F16),1) -> 3402
A18: =CONCATENATE("Say Rs (",F17," x Cost Index)") -> Say Rs (3402 x Cost Index)
A19: 0 | B19: Borewell submersible pump pullout charges above 3 H.P. To 7.5 H.P.
A20: Code | B20: Description | C20: Unit | D20: Quantity | E20: Rate | F20: Amount
B21: MATERIALS:
A22: 0 | B22: 40mm Cast iron Clamp | C22: set | D22: 0 | E22: 935 | F22: =D22*E22 -> 0
B23: Add Water Charges @ 1% | F23: =F22*0.01 -> 0
B24: TOTAL | F24: =SUM(F22:F23) -> 0
B25: Add CPOH @ 15% | F25: =F24*0.15 -> 0
B26: TOTAL | F26: =SUM(F24:F25) -> 0
A27: 0015 | B27: Tools hire charge (DSR 0015) | C27: day | D27: 0.75 | E27: 3000 | F27: =D27*E27 -> 2250
A28: 0116 | B28: Fitter, Plumber, Electrician | C28: Day | D28: 1 | E28: 784 | F28: =D28*E28 -> 784
A29: 0114 | B29: Beldar | C29: Day | D29: 1 | E29: 645 | F29: =D29*E29 -> 645
B30: TOTAL | F30: =SUM(F27:F29) -> 3679
B31: Add Water Charges @ 1% | F31: =F30*0.01 -> 36.79
B32: TOTAL | F32: =SUM(F30:F31) -> 3715.79
B33: Add CPOH @ 15% | F33: =F32*0.15 -> 557.3685
B34: TOTAL | F34: =mround(SUM(F32:F33),1) -> 4273
A35: =CONCATENATE("Say Rs (",F34," x Cost Index)") -> Say Rs (4273 x Cost Index)
A36: 0 | B36: Borewell submersible pump pullout charges above 7.5 H.P.
A37: Code | B37: Description | C37: Unit | D37: Quantity | E37: Rate | F37: Amount
B38: MATERIALS:
A39: 0 | B39: 40mm Cast iron Clamp | C39: set | D39: 0 | E39: 935 | F39: =D39*E39 -> 0
B40: Add Water Charges @ 1% | F40: =F39*0.01 -> 0
B41: TOTAL | F41: =SUM(F39:F40) -> 0
B42: Add CPOH @ 15% | F42: =F41*0.15 -> 0
B43: TOTAL | F43: =SUM(F41:F42) -> 0
A44: 0015 | B44: Tools hire charge (DSR 0015) | C44: day | D44: 1 | E44: 3000 | F44: =D44*E44 -> 3000
A45: 0116 | B45: Fitter, Plumber, Electrician | C45: Day | D45: 1 | E45: 784 | F45: =D45*E45 -> 784
A46: 0114 | B46: Beldar | C46: Day | D46: 1 | E46: 645 | F46: =D46*E46 -> 645
B47: TOTAL | F47: =SUM(F44:F46) -> 4429
B48: Add Water Charges @ 1% | F48: =F47*0.01 -> 44.29
B49: TOTAL | F49: =SUM(F47:F48) -> 4473.29
B50: Add CPOH @ 15% | F50: =F49*0.15 -> 670.9935
B51: TOTAL | F51: =mround(SUM(F49:F50),1) -> 5144
A52: =CONCATENATE("Say Rs (",F51," x Cost Index)") -> Say Rs (5144 x Cost Index)
A53: 0 | B53: Compressor pump detaching charge
A54: Code | B54: Description | C54: Unit | D54: Quantity | E54: Rate | F54: Amount
A55: 0015 | B55: Tools hire charge (DSR 0015) | C55: day | D55: 0.3 | E55: 3000 | F55: =D55*E55 -> 900
A56: 0116 | B56: Fitter, Plumber, Electrician | C56: Day | D56: 0.5 | E56: 784 | F56: =D56*E56 -> 392
A57: 0114 | B57: Beldar | C57: Day | D57: 0.5 | E57: 645 | F57: =D57*E57 -> 322.5
B58: TOTAL | F58: =SUM(F55:F57) -> 1614.5
B59: Add Water Charges @ 1% | F59: =F58*0.01 -> 16.145
B60: TOTAL | F60: =SUM(F58:F59) -> 1630.645
B61: Add CPOH @ 15% | F61: =F60*0.15 -> 244.59675
B62: TOTAL | F62: =mround(SUM(F60:F61),1) -> 1875
A63: =CONCATENATE("Say Rs (",F62," x Cost Index)") -> Say Rs (1875 x Cost Index)

Sheet PVC Fittings
A1: Sor/Spec Code | B1: MR Code | C1: Description | F1: Remarks
C2: Unit | D2: Quantity | E2: Rate (₹) | F2: Amount | G2: Label
A3: Providing and fixing PVC moulded fittings/ accessories for Rigid PVC pipes, including jointing with PVC solvent cement - 150 mm dia Bend
B4: Header Unit | C4: no | D4: Header Quantity | E4: 1
